Workbook
Name \5: #REF!
Name \5: 'Cuadro 5'!#REF!
Name \5: #REF!
Name \6: #REF!
Name \6: 'Cuadro 5'!#REF!
Name \6: #REF!
Name \7: #REF!
Name \7: 'Cuadro 5'!#REF!
Name \7: #REF!
Name \A: #REF!
Name \A: 'Cuadro 5'!#REF!
Name \A: #REF!
Name \B: #REF!
Name \B: 'Cuadro 5'!#REF!
Name \B: #REF!
Name \C: #REF!
Name \C: 'Cuadro 5'!#REF!
Name \C: #REF!
Name \D: #REF!
Name \D: 'Cuadro 5'!#REF!
Name \D: #REF!
Name \E: #REF!
Name \E: 'Cuadro 5'!#REF!
Name \E: #REF!
Name \F: #REF!
Name \F: 'Cuadro 5'!#REF!
Name \F: #REF!
Name \I: #REF!
Name \I: #REF!
Name \I2: #REF!
Name \I2: #REF!
Name \K: #REF!
Name \K: 'Cuadro 5'!#REF!
Name \K: #REF!
Name \L: #REF!
Name \L: 'Cuadro 5'!#REF!
Name \L: #REF!
Name \P: #REF!
Name \P: #REF!
Name \Z: #REF!
Name \Z: 'Cuadro 5'!#REF!
Name \Z: #REF!
Name __123Graph_A: #REF!
Name __123Graph_A: #REF!
Name __123Graph_ABERLGRAP: 'Cuadro 5'!#REF!
Name __123Graph_ABERLGRAP: #REF!
Name __123Graph_ABKSRESRV: 'Cuadro 5'!#REF!
Name __123Graph_ABKSRESRV: #REF!
Name __123Graph_ACATCH1: 'Cuadro 5'!#REF!
Name __123Graph_ACATCH1: #REF!
Name __123Graph_AChart1: 'Cuadro 5'!#REF!
Name __123Graph_AChart1: #REF!
Name __123Graph_AChart2: 'Cuadro 5'!#REF!
Name __123Graph_AChart2: #REF!
Name __123Graph_AChart3: 'Cuadro 5'!#REF!
Name __123Graph_AChart3: #REF!
Name __123Graph_ACONVERG1: 'Cuadro 5'!#REF!
Name __123Graph_ACONVERG1: #REF!
Name __123Graph_ACurrent: 'Cuadro 5'!#REF!
Name __123Graph_ACurrent: #REF!

Sheet Cuadros
B2: ESTUDIO DE EVALUACIÓN DE LA REGLA DE GASTO EN PENSIONES
B6: Capítulo | C6: Título Nivel 1 | D6: Título Nivel 2 | E6: Página | F6: Hoja | G6: Título | H6: Fuente
B8: RESUMEN EJECUTIVO | E8: 6 | F8: Cuadro 1 | G8: Impacto medio anual de las medidas adoptadas a partir de 2020 para fortalecer los ingresos del sistema público de pensiones (% PIB)
E9: 7 | F9: Cuadro 2 | G9: Gasto bruto público en pensiones neto de medidas de ingresos (% PIB)
B10: 2. REGLA DE GASTO EN PENSIONES | C10: 2.3. Evaluación del impacto de las medidas de ingresos | E10: 19 | F10: Cuadro 3 | G10: Impacto medio anual de las medidas adoptadas a partir de 2020 para fortalecer los ingresos del sistema público de pensiones (% PIB)
D11: 2.3.2. Medidas indirectas de ingresos | E11: 29 | F11: Cuadro 4 | G11: Comparación del impacto estimado del SMI sobre el empleo
E12: 30 | F12: Cuadro 5 | G12: Impacto del incremento del salario mínimo interprofesional (desviaciones respecto al escenario sin medidas, % y puntos porcentuales)
E13: 33 | F13: Cuadro 6 | G13: Comparación del impacto estimado de las medidas laborales sobre las transiciones laborales
E14: 34 | F14: Cuadro 7 | G14: Impacto de las medidas de mercado laboral (desviaciones respecto al escenario sin medidas, % y puntos porcentuales)
C15: 2.4. Resultado de la regla de gasto en pensiones | E15: 52 | F15: Cuadro 8 | G15: Gasto bruto público en pensiones neto de medidas de ingresos (% PIB)
C16: 2.5. Encaje de la regla de gasto de pensiones con el marco fiscal | E16: 52 | F16: Cuadro 9 | G16: Cuenta de control anual y acumulada de la regla de gasto europea
E17: 53 | F17: Cuadro 10 | G17: Gasto primario neto de medidas de ingresos por subsectores (% variación)
B18: 3. SUPUESTOS DEMOGRÁFICOS Y MACROECONÓMICOS | C18: 3.1. Proyecciones demográficas de la AIReF | E18: 57 | F18: Cuadro 11 | G18: Comparativa de las proyecciones demográficas de la AIReF con las de otros organismos para diversos años
B19: 4. ESCENARIO FISCAL A LARGO PLAZO | C19: 4.2 Evolución de los empleos de las Administraciones Públicas | E19: 65 | F19: Cuadro 12 | G19: Empleos no financieros sin PRTR (% PIB)
B20: ANEXO I. ACTUALIZACIÓN DE LAS PROYECCIONES DE POBLACIÓN DE RESIDENTES 2026-2050 | C20: Anexo I. 3. Proyección de las migraciones | D20: Anexo I. 3.3. Pirámide de población | E20: 94 | F20: Anexo I. Cuadro 1. | G20: Estructura porcentual de la población según tramos etarios

Sheet Gráficos
B2: ESTUDIO DE EVALUACIÓN DE LA REGLA DE GASTO EN PENSIONES
B6: Capítulo | C6: Título Nivel 1 | D6: Título Nivel 2 | E6: Página | F6: Hoja | G6: Título | H6: Fuente
B8: RESUMEN EJECUTIVO | E8: 6 | F8: Gráfico 1 | G8: Gasto bruto público en pensiones (% PIB)
E9: 7 | F9: Gráfico 2 | G9: Deuda pública (% PIB)
E10: 7 | F10: Gráfico 3 | G10: Saldo público (% PIB)
B11: 2. REGLA DE GASTO EN PENSIONES | C11: 2.1. Gasto bruto público en pensiones | E11: 15 | F11: Gráfico 4 | G11: Evolución del gasto en pensiones (% PIB)
E12: 16 | F12: Gráfico 5 | G12: Descomposición del crecimiento del gasto en pensiones
E13: 16 | F13: Gráfico 6 | G13: Número de pensiones (millones)
E14: 17 | F14: Gráfico 7 | G14: Tasa de generosidad (pensión media/ salario medio)
C15: 2.2. La senda de crecimiento del PIB nominal de la regla de gasto en pensiones | E15: 18 | F15: Gráfico 8. A. | G15: Proyecciones de PIB nominal (miles de millones de euros)
E16: 18 | F16: Gráfico 8. B. | G16: Proyecciones de población (miles de residentes)
C17: 2.3. Evaluación del impacto de las medidas de ingresos | D17: 2.3.2. Medidas indirectas de ingresos | E17: 27 | F17: Gráfico 9 | G17: Incidencia del SMI (porcentaje de trabajadores sobre el total de afiliados al régimen general). 2018-2024
E18: 28 | F18: Gráfico 10 | G18: Distribución de las bases de cotización mensuales, 2018, 2023 y 2024
E19: 32 | F19: Gráfico 11. A. | G19: Salida del no empleo al empleo
E20: 32 | F20: Gráfico 11. B. | G20: Salida del empleo al no empleo
B21: RECUADRO 2. LA REGULACIÓN EXTRAORDINARIA. UNA ESTIMACIÓN TENTATIVA DE SU IMPACTO EN COTIZACIONES | E21: 45 | F21: Gráfico RE_2. 1. | G21: Tasa de parcialidad por sexo y origen de los inmigrantes (%)
E22: 45 | F22: Gráfico RE_2. 2. | G22: Estimación flujos personas regularizables DA21
E23: 46 | F23: Gráfico RE 2. 3. | G23: Afiliados extranjeros en 2005: observado vs. contrafactual (miles)
E24: 47 | F24: Gráfico RE_2.4. | G24: Base media anual de cotización de inmigrantes (miles de euros)
E25: 51 | F25: Gráfico RE_2.5. | G25: Distribución del impacto potencial de cotizaciones (% PIB) con distintas combinaciones de parámetros para el primer año
C26: 2.5. Encaje de la regla de gasto de pensiones con el marco fiscal | E26: 54 | F26: Gráfico 12 | G26: Fuentes de financiación del sistema público de pensiones
B27: 3. SUPUESTOS DEMOGRÁFICOS Y MACROECONÓMICOS | C27: 3.1. Proyecciones demográficas de la AIReF | E27: 56 | F27: Gráfico 13. A. | G27: Población total
E28: 56 | F28: Gráfico 13. B. | G28: Población de 15-74 años
E29: 58 | F29: Gráfico 14. A. | G29: Descomposición de la tasa de dependencia
E30: 58 | F30: Gráfico 14. B. | G30: Comparativa de tasas de dependencia
C31: 3. 2. Supuestos macroeconómicos | E31: 59 | F31: Gráfico 15 | G31: Crecimiento promedio del PIB potencial (% 2022-2050)
E32: 60 | F32: Gráfico 16 | G32: Tasa de participación (% población 15-74 años)
E33: 50 | F33: Gráfico 17 | G33: Nawru (%)
B34: 4. ESCENARIO FISCAL A LARGO PLAZO | C34: 4.1. Evolución de los recursos de las Administraciones públicas | E34: 62 | F34: Gráfico 18 | G34: Evolución de la recaudación impositiva entre 1995 y 2050 (% PIB)
E35: 63 | F35: Gráfico 19 | G35: Evolución de los recursos hasta 2050 (% PIB)
C36: 4.2. Evolución de los empleos de las Administraciones públicas | E36: 65 | F36: Gráfico 20 | G36: Empleos no financieros sin PRTR (% PIB)
E37: 66 | F37: Gráfico 21 | G37: Proyección tipo medio de emisión y tipo implícito
E38: 66 | F38: Gráfico 22 | G38: Intereses (% PIB)
E39: 67 | F39: Gráfico 23 | G39: Evolución del gasto en sanidad (% PIB)
E40: 67 | F40: Gráfico 24 | G40: Evolución del gasto en cuidados de larga duración (% PIB)
E41: 68 | F41: Gráfico 25 | G41: Evolución del gasto en educación (% PIB)
E42: 68 | F42: Gráfico 26 | G42: Evolución del gasto en prestaciones por desempleo (% PIB)
B43: 5. ANÁLISIS DE SOSTENIBILIDAD | E43: 69 | F43: Gráfico 27 | G43: Evolución de la ratio de deuda (% PIB)
E44: 69 | F44: Gráfico 28 | G44: Deuda (% PIB). Países de la Unión Europea con más del 80%.
E45: 70 | F45: Gráfico 29 | G45: Deuda (% PIB)
E46: 70 | F46: Gráfico 30 | G46: Diferencia con la Opinión de 2025 en la ratio de deuda en 2050 (p. p.)
E47: 71 | F47: Gráfico 31. A. | G47: Contribuciones a la variación de la deuda (p. p.). Por años
E48: 71 | F48: Gráfico 31. B. | G48: Contribuciones a la variación de la deuda (p. p.). Por periodos
E49: 71 | F49: Gráfico 32 | G49: Saldo público (% PIB)
E50: 71 | F50: Gráfico 33 | G50: Diferencial interés-crecimiento (p.p.)
E51: 72 | F51: Gráfico 34 | G51: Necesidades brutas de financiación (% PIB)
E52: 72 | F52: Gráfico 35 | G52: Intervalo de deuda (% PIB). Escenarios de evolución del PIB.
C53: 5.1. Impacto en las variables fiscales del gasto asociado al envejecimiento de la población | E53: 73 | F53: Gráfico 36 | G53: Contribuciones a la variación del saldo primario de los componentes del envejecimiento (puntos de PIB)
E54: 74 | F54: Gráfico 37 | G54: Contribuciones a la variación de la deuda de los componentes del envejecimiento
B55: ANEXO I. ACTUALIZACIÓN DE LAS PROYECCIONES DE POBLACIÓN DE RESIDENTES 2026-2050 | C55: Anexo I. 1. Proyecciones de fecundidad | D55: Anexo I. 1.1. Evolución reciente de la fecundidad | E55: 79 | F55: Anexo I. Gráfico 1. A. | G55: Número de hijos por mujer. Según nacionalidad de la madre
E56: 79 | F56: Anexo I. Gráfico 1. B. | G56: Diferencial en el número de hijos por mujer entre madres extranjeras y españolas
E57: 80 | F57: Anexo I. Gráfico 2. A. | G57: Evolución del número de hijos por mujer. España en el contexto mundial y de principales países emisores
E58: 80 | F58: Anexo I. Gráfico 2. B. | G58: Evolución del número de hijos por mujer. España en el contexto europeo.
E59: 81 | F59: Anexo I. Gráfico 3. A. | G59: Proporción de mujeres que tienen hijos
E60: 81 | F60: Anexo I. Gráfico 3. B. | G60: Número de hijos por mujer de las que acceden a la maternidad
E61: 82 | F61: Anexo I. Gráfico 4. A. | G61: Evolución del número de hijos de cada generación de mujeres. España en el contexto mundial y de principales países emisores
E62: 82 | F62: Anexo I. Gráfico 4. B. | G62: Evolución del número de hijos de cada generación de mujeres. España en el contexto europeo.
D63: Anexo I. 1. 2. Actualización de las proyecciones de fecundidad | E63: 83 | F63: Anexo I. Gráfico 5 | G63: Evolución de las proyecciones del número de hijos por mujer de la AIReF
E64: 84 | F64: Anexo I. Gráfico 6. A. | G64: Número de hijos por mujer. Madres de nacionalidad española
E65: 84 | F65: Anexo I. Gráfico 6. B. | G65: Número de hijos por mujer. Madres de nacionalidad extranjera
E66: 85 | F66: Anexo I. Gráfico 7. A. | G66: Número de hijos por mujer
E67: 85 | F67: Anexo I. Gráfico 7. B. | G67: Diferencia en el número de hijos por mujer de madres con nacionalidad extranjera y española
E68: 86 | F68: Anexo I. Gráfico 8. A. | G68: Proporción de mujeres que tienen hijos. Según nacionalidad
E69: 86 | F69: Anexo I. Gráfico 8. B. | G69: Número de hijos por mujer de cada generación de mujeres
C70: Anexo I. 2. Proyecciones de supervivencia | D70: Anexo I.2.1. Evolución reciente de la mortalidad | E70: 87 | F70: Anexo I. Gráfico 9. A. | G70: Esperanza de vida al nacer. Según sexo
E71: 87 | F71: Anexo I. Gráfico 9. B. | G71: Esperanza de vida a los 65 años. Según sexo
E72: 88 | F72: Anexo I. Gráfico 10. A. | G72: Esperanza de vida al nacer. Según sexo en España y el entorno inmediato (años). Hombres
E73: 88 | F73: Anexo I. Gráfico 10. B. | G73: Esperanza de vida al nacer. Según sexo en España y el entorno inmediato (años). Mujeres
D74: Anexo I.2.2. Actualización de las proyecciones de mortalidad | E74: 89 | F74: Anexo I. Gráfico 11. A. | G74: Proyecciones de la esperanza de vida. Según sexo (años). Al nacer
E75: 89 | F75: Anexo I. Gráfico 11. B. | G75: Proyecciones de la esperanza de vida. Según sexo (años). A los 65 años
E76: 90 | F76: Anexo I. Gráfico 12. A. | G76: Proyecciones de la esperanza de vida (años). Al nacer
E77: 90 | F77: Anexo I. Gráfico 12. B. | G77: Proyecciones de la esperanza de vida (años). A los 65 años
C78: Anexo I. 3. Proyección de las migraciones | D78: Anexo I.3.1. Evolución reciente de los flujos migratorios | E78: 91 | F78: Anexo I. Gráfico 13. A. | G78: Flujos migratorios observados (miles de personas). Flujos de inmigración y emigración
E79: 91 | F79: Anexo I. Gráfico 13. B. | G79: Flujos migratorios observados (miles de personas). Flujo neto de inmigración
E80: 91 | F80: Anexo I. Gráfico 14 | G80: Perfil etario de los flujos de inmigración
D81: Anexo I.3.2. Actualización de las proyecciones de flujos migratorios | E81: 93 | F81: Anexo I. Gráfico 15. A. | G81: Proyecciones de flujos migratorios exteriores (miles de personas). Flujo neto de inmigración
E82: 93 | F82: Anexo I. Gráfico 15. B. | G82: Proyecciones de flujos migratorios exteriores (miles de personas). Flujos de inmigración y emigración exterior
D83: Anexo I.3.3. Pirámide de población | E83: 94 | F83: Anexo I. Gráfico 16. A. | G83: Pirámide poblacional a 1 de enero (grupos quinquenales de edad, miles de personas). Población residente española.
E84: 94 | F84: Anexo I. Gráfico 16. B. | G84: Pirámide poblacional a 1 de enero (grupos quinquenales de edad, miles de personas). Población residente extranjera.
E85: 94 | F85: Anexo I. Gráfico 16. C. | G85: Pirámide poblacional a 1 de enero (grupos quinquenales de edad, miles de personas). Población residente total.

Sheet Cuadro 1 y 3
A1: Índice de cuadros
B3: CUADRO 1. IMPACTO MEDIO ANUAL DE LAS MEDIDAS ADOPTADAS A PARTIR DE 2020 PARA FORTALECER LOS INGRESOS DEL SISTEMA PÚBLICO DE PENSIONES (% PIB)
C5: Impacto hasta 2025 | D5: Impacto promedio 2022-2050
B6: Variación ingresos | C6: 0.92273954 | D6: 1.571092
B7: Mecanismo de Equidad Intergeneracional | C7: 0.29079478 | D7: 0.39115046
B8: Evolución Bases Máximas Cotización | C8: 0.22879191 | D8: 0.31966452
B9: Cotización adicional de solidaridad | C9: 0.019466266 | D9: 0.077498131
B10: Reforma cotizaciones trabajadores autónomos | C10: 0.015128785 | D10: 0.33386648
B11: Transferencias | C11: 0.26855779 | D11: 0.3189124
B12: Incrementos Salario Mínimo Interprofesional | C12: 0.1 | D12: 0.1
B13: Reforma laboral | C13: 0 | D13: 0
B14: Regularización inmigrantes (*) | C14: 0 | D14: 0.03

Sheet Cuadro 2 y 8
A1: Índice de cuadros
B3: CUADRO 2. GASTO PÚBLICO EN PENSIONES NETO DE MEDIDAS DE INGRESOS (% PIB)
B5: Regla de gasto | C5: Gastos | F5: Medidas ingresos | I5: Gasto neto de medidas
C6: Dato | D6: Límite | E6: Cumple | F6: Dato | G6: Límite | H6: Cumple | I6: Dato | J6: Límite | K6: Cumple
B7: AR 2024 actualizado | C7: 14.567182 | D7: 15 | E7: P | F7: 1.571092 | G7: 1.7 | H7: O | I7: 12.99609 | J7: 13.3 | K7: P
B8: AIReF | C8: 14.548278 | D8: 15 | E8: P | F8: 1.571092 | G8: 1.7 | H8: O | I8: 12.977186 | J8: 13.3 | K8: P

Sheet Cuadro 4
A1: Índice de cuadros
B3: CUADRO 4. COMPARACIÓN DEL IMPACTO ESTIMADO DEL SMI SOBRE EL EMPLEO
B7: Concepto | C7: Documento Técnico 9/25 (sept. 2025) | D7: Actualización (mayo 2026)
B8: Subida SMI 2019 (+22,3%)
B9: Impacto sobre la afiliación | C9: Entre −0,25 y −0,41 pp | D9: Entre −0,28 y −0,36 pp
B10: Pérdida de afiliados (Régimen General) | C10: Entre 40.000 y 65.000 | D10: Entre 45.000 y 54.000
B11: Subida SMI 2023 (+8,0%)
B12: Impacto sobre la afiliación | C12: Entre −0,34 y −0,53 pp | D12: Entre −0,32 y −0,39 pp
B13: Pérdida de afiliados (Régimen General) | C13: Entre 55.000 y 85.000 | D13: Entre 50.000 y 61.000
B14: Subida SMI 2024 (+5,0%)
B15: Impacto sobre la afiliación | C15: No estimado | D15: Entre −0,49 y −0,56 pp
B16: Pérdida de afiliados (Régimen General) | C16: — | D16: Entre 78.000 y 90.000
B18: Fuente: AIReF, a partir de la MCVL
B19: Nota: Los rangos corresponden a los intervalos de confianza al 95 % sobre la afiliación en el Régimen General de la Seguridad Social.

Sheet Cuadro 5
A1: Índice de cuadros
B3: CUADRO 5. IMPACTO DEL INCREMENTO DEL SALARIO MÍNIMO INTERPROFESIONAL (DESVIACIONES RESPECTO AL ESCENARIO SIN MEDIDAS, % Y PUNTOS PORCENTUALES)
C5: t+5 | F5: t+10 | I5: Promedio 2022-2050
C6: MTA | D6: MEGAIReF eficiencia | E6: MEGAIReF shifter | F6: MTA | G6: MEGAIReF eficiencia | H6: MEGAIReF shifter | I6: MTA | J6: MEGAIReF eficiencia | K6: MEGAIReF shifter
B7: PIB | C7: 0.0019147146 | D7: 0.12420201 | E7: -0.11272687 | F7: 0.18931288 | G7: 0.17064327 | H7: -0.2374577 | I7: 0.1472604 | J7: 0.16393465 | K7: -0.24645912
B8: Empleo | C8: -0.012035788 | D8: 0.13448714 | E8: -0.27481518 | F8: -0.010111564 | G8: 0.18408118 | H8: -0.34454956 | I8: -0.0094423451 | J8: 0.17540208 | K8: -0.34648359
B9: Saldo Público (% PIB) | C9: 0.1499287 | D9: 0.0085592622 | E9: -0.029580998 | F9: 0.39419135 | G9: 0.0031556252 | H9: -0.05427177 | I9: 0.31037972 | J9: 0.00010525476 | K9: -0.044491712
B10: Cotizaciones | C10: 0.61927022 | D10: 0.11403628 | E10: 0.0037076998 | F10: 1.637295 | G10: 0.15783635 | H10: 0.028395086 | I10: 1.3907428 | J10: 0.1518147 | K10: 0.062636591
B11: Cotizaciones (% PIB) | C11: 0.068838947 | D11: 0 | E11: 0.00096557338 | F11: 0.1598643 | G11: -0.001682056 | H11: 0.0071573888 | I11: 0.12659325 | J11: -0.0015918297 | K11: 0.011137947
B13: Fuente: | C13: AIReF

Sheet Cuadro 6
A1: Índice de cuadros
B3: CUADRO 6. COMPARACIÓN DEL IMPACTO ESTIMADO DE LAS MEDIDAS LABORALES SOBRE LAS TRANSICIONES LABORALES
B5: Transición laboral | C5: Documento Técnico 8/25 (sept. 2025) | D5: Actualización (mayo 2026)
B6: Probabilidad mensual de transición del desempleo al empleo | C6: +0,61 pp | D6: Entre +0,61 y +0,33 pp
B7: Probabilidad mensual de transición del empleo al desempleo | C7: -0,68pp | D7: Entre -0,39 y -0,79 pp

Sheet Cuadro 7
A1: Índice de cuadros
B3: CUADRO 7. IMPACTO DE LAS MEDIDAS DE MERCADO LABORAL (DESVIACIONES RESPECTO AL ESCENARIO SIN MEDIDAS, % Y PUNTOS PORCENTUALES)
C5: t+5 | F5: t+10 | I5: Promedio 2022-2050
C6: MTA | D6: MEGAIReF eficiencia | E6: MEGAIReF shifter | F6: MTA | G6: MEGAIReF eficiencia | H6: MEGAIReF shifter | I6: MTA | J6: MEGAIReF eficiencia | K6: MEGAIReF shifter
B7: PIB | C7: 0.0019147146 | D7: 0.12420201 | E7: 0.12420201 | F7: 0.1 | G7: 0.1 | H7: 0.1 | I7: 0 | J7: 0.1 | K7: 0.1
B8: Empleo | C8: 0.12420201 | D8: 0.12420201 | E8: 0.12420201 | F8: 0.1 | G8: 0.2 | H8: 0.1 | I8: 0.1 | J8: 0.1 | K8: 0.1
B9: Saldo Público (% PIB) | C9: 0.0085592622 | D9: 0.0085592622 | E9: -0.029580998 | F9: 0.1 | G9: 0.1 | H9: 0 | I9: 0 | J9: 0.00010525476 | K9: -0.044491712
B10: Cotizaciones | C10: 0.12420201 | D10: 0.0085592622 | E10: 0.3 | F10: 0.1 | G10: 0 | H10: 0.3 | I10: 0.1 | J10: 0 | K10: 0.3
B11: Cotizaciones (% PIB) | C11: 0 | D11: 0 | E11: 0.00096557338 | F11: 0 | G11: -0.001682056 | H11: 0.0071573888 | I11: 0 | J11: -0.0015918297 | K11: 0.011137947
B13: Fuente: | C13: AIReF

Sheet Cuadro 9
A1: Índice de cuadros
B3: CUADRO 9. CUENTA DE CONTROL ANUAL Y ACUMULADA DE LA REGLA DE GASTO EUROPEA (%PIB)
B5: Cuenta de control | C5: 2024 | E5: 2025 | G5: 2026 | I5: 2027 | K5: 2028
B6: Anual | C6: 0.45045555 | D6: P | E6: -0.44098201 | F6: O | G6: -0.91380644 | H6: O | I6: -0.78747132 | J6: O | K6: -0.49827993 | L6: O
B7: Acumulada | C7: 0.45045555 | D7: P | E7: -0.01530916 | F7: P | G7: -0.92841677 | H7: O | I7: -1.6748586 | J7: O | K7: -2.1050425 | L7: O
B8: Acumulada tras cláusula de escape de defensa | E8: 0.16057498 | F8: P | G8: -0.63233095 | H8: P | I8: -1.2161628 | J8: O | K8: -1.5046596 | L8: O
B12: Fuente: Informe de Progreso Anual y AIReF

Sheet Cuadro 10
A1: Índice de cuadros
B4: CUADRO 10. GASTO PRIMARIO NETO DE MEDIDAS DE INGRESOS POR SUBSECTORES (% VARIACIÓN)
C6: 2025 | D6: 2026 | E6: 2027 | F6: 2028
B7: AA. PP. | C7: 4.8439715 | D7: 5.8197375 | E7: 5.1804364 | F7: 4.2353121
B8: A. C. | C8: 5.8841269 | D8: 8.9138939 | E8: 4.0398187 | F8: 4.7935471
B9: F. S. S. | C9: 4.7425377 | D9: 4.9863013 | E9: 4.7079701 | F9: 3.8670315
B10: CC. AA. | C10: 4.9375607 | D10: 4.2399382 | E10: 6.407784 | F10: 4.470501
B11: CC. LL. | C11: 2.3553798 | D11: 5.3395468 | E11: 5.8850004 | F11: 3.2192645
B13: Fuente: AIReF

Sheet Cuadro 11
A1: Índice de cuadros
B3: CUADRO 11. COMPARATIVA DE LAS PROYECCIONES DEMOGRÁFICAS DE LA AIREF CON LAS DE OTROS ORGANISMOS PARA DIVERSOS AÑOS
D5: 2025 | E5: 2030 | F5: 2035 | G5: 2040 | H5: 2045 | I5: 2050 | J5: Promedio 2025-2050
B6: Población total (Miles) | C6: INE 2024 | D6: 49265.049 | E6: 51876.064 | F6: 53109.718 | G6: 53892.709 | H6: 54514.658 | I6: 54884.721 | J6: 53103.14
C7: EUROPOP2025 | D7: 49128.297 | E7: 50947.559 | F7: 51977.041 | G7: 52872.036 | H7: 53552.939 | I7: 53877.467 | J7: 52176.991
C8: EUROPOP2023 | D8: 48614.06 | E8: 49266.93 | F8: 49760.92 | G8: 50237.193 | H8: 50527.425 | I8: 50460.161 | J8: 49875.377
C9: AIReF 2026 | D9: 49128.297 | E9: 51394.484 | F9: 52260.348 | G9: 52553.403 | H9: 52709.215 | I9: 52728.898 | J9: 51958.762
C10: AIReF 2025 | D10: 49081.526 | E10: 50119.31 | F10: 50691.139 | G10: 51213.189 | H10: 51705.964 | I10: 52094.597 | J10: 50872.391
B11: Población de 15-74 años (Miles) | C11: INE 2024 | D11: 37885.777 | E11: 40273.627 | F11: 40874.263 | G11: 40478.229 | H11: 39874.037 | I11: 39218.456 | J11: 40019.72
C12: EUROPOP2025 | D12: 37745.287 | E12: 39448.752 | F12: 39954.748 | G12: 39707.553 | H12: 39125.215 | I12: 38321.532 | J12: 39259.524
C13: EUROPOP2023 | D13: 37204.985 | E13: 37878.077 | F13: 37799.883 | G13: 37094.416 | H13: 36131.751 | I13: 34998.546 | J13: 37009.577
C14: AIReF 2026 | D14: 37745.287 | E14: 39782.755 | F14: 40183.979 | G14: 39635.958 | H14: 38831.011 | I14: 37966.416 | J14: 39249.957
C15: AIReF 2025 | D15: 37697.449 | E15: 38669.71 | F15: 38722.54 | G15: 38168.376 | H15: 37435.644 | I15: 36718.645 | J15: 38048.813
B16: Número de hijos por mujer | C16: INE 2024 | D16: 1.1329042 | E16: 1.1663795 | F16: 1.2096138 | G16: 1.2560737 | H16: 1.2788302 | I16: 1.2869753 | J16: 1.2244052
C17: EUROPOP2025 | D17: 1.10738 | E17: 1.13097 | F17: 1.15201 | G17: 1.17322 | H17: 1.19445 | I17: 1.21568 | J17: 1.1625996
C18: AIReF 2026 | D18: 1.1036938 | E18: 1.0890768 | F18: 1.0542644 | G18: 1.03337 | H18: 1.0246367 | I18: 1.0166261 | J18: 1.0522255
C19: AIReF 2025 | D19: 1.1276932 | E19: 1.1747067 | F19: 1.2078317 | G19: 1.2432503 | H19: 1.2764137 | I19: 1.3061325 | J19: 1.2246568
B20: Esperanza de vida al nacer (Años) | C20: INE 2024 | D20: 83.652743 | E20: 84.347329 | F20: 84.996714 | G20: 85.594531 | H20: 86.132068 | I20: 86.597376 | J20: 85.239652
C21: EUROPOP2025 | D21: 84.099183 | E21: 84.554876 | F21: 85.106855 | G21: 85.558932 | H21: 86.010728 | I21: 86.562169 | J21: 85.301786
C22: AIReF 2026 | D22: 84.098444 | E22: 84.7803 | F22: 85.36922 | G22: 85.940646 | H22: 86.495735 | I22: 87.035478 | J22: 85.633685
C23: AIReF 2025 | D23: 84.05097 | E23: 84.68061 | F23: 85.288365 | G23: 85.861487 | H23: 86.420643 | I23: 86.963127 | J23: 85.551666
B24: Esperanza de vida a los 65 años (Años) | C24: INE 2024 | D24: 21.547168 | E24: 22.007649 | F24: 22.443159 | G24: 22.846247 | H24: 23.212497 | I24: 23.531349 | J24: 22.610234
C25: EUROPOP2025 | D25: 22.041302 | E25: 22.370957 | F25: 22.758689 | G25: 23.093621 | H25: 23.489 | I25: 23.839705 | J25: 22.928439
C26: AIReF 2026 | D26: 22.033417 | E26: 22.531295 | F26: 22.950454 | G26: 23.371025 | H26: 23.809939 | I26: 24.240248 | J26: 23.16219
C27: AIReF 2025 | D27: 21.996125 | E27: 22.445602 | F27: 22.879256 | G27: 23.301172 | H27: 23.743923 | I27: 24.177556 | J27: 23.091284
B28: Inmigración neta (Miles) | C28: INE 2024 | D28: 775.19801 | E28: 446.78101 | F28: 294.67101 | G28: 280.089 | H28: 284.022 | I28: 286.422 | J28: 369.89897
C29: EUROPOP2025 | D29: 568.24 | E29: 368.487 | F29: 332.095 | G29: 329.129 | H29: 311.887 | I29: 290.95 | J29: 354.35858
C30: AIReF 2026 | D30: 552.49623 | E30: 399.54124 | F30: 233.789 | G30: 234.23498 | H30: 250.23077 | I30: 269.12241 | J30: 320.87808
C31: AIReF 2025 | D31: 399.15038 | E31: 249.81616 | F31: 236.83648 | G31: 245.95164 | H31: 258.45295 | I31: 271.56683 | J31: 263.84942
B33: Fuente: | C33: INE, Eurostat y AIReF

Sheet Cuadro 12
A1: Índice de cuadros
B3: CUADRO 12. EMPLEOS NO FINANCIEROS SIN PRTR (% PIB)
D5: 2025 | E5: 2030 | F5: 2050 | H5: 2025-2030 | I5: 2030-2050
B6: Empleos no Financieros | D6: 44.5245 | E6: 45.688101 | F6: 51.574935 | H6: =E6-D6 -> 1.1636009 | I6: =F6-E6 -> 5.8868334
B7: Modelizados | D7: 28.07566 | E7: 29.032812 | F7: 34.920104 | H7: =E7-D7 -> 0.95715286 | I7: =F7-E7 -> 5.8872911
B8: Pensiones | D8: 12.953716 | E8: 13.519808 | F8: 16.398787 | H8: =E8-D8 -> 0.56609163 | I8: =F8-E8 -> 2.8789794
B9: Intereses | D9: 2.3894705 | E9: 2.8062749 | F9: 4.4105118 | H9: =E9-D9 -> 0.41680438 | I9: =F9-E9 -> 1.6042368
B10: Sanidad | D10: 6.471819 | E10: 6.5642222 | F10: 7.9394281 | H10: =E10-D10 -> 0.092403195 | I10: =F10-E10 -> 1.3752059
B11: Cuidados larga duración | D11: 0.82996582 | E11: 0.9463415 | F11: 1.5624242 | H11: =E11-D11 -> 0.11637568 | I11: =F11-E11 -> 0.61608269
B12: Educación | D12: 3.9823301 | E12: 3.9538204 | F12: 3.3263002 | H12: =E12-D12 -> -0.028509742 | I12: =F12-E12 -> -0.62752015
B13: Desempleo | D13: 1.4483579 | E13: 1.2423457 | F13: 1.2826522 | H13: =E13-D13 -> -0.20601227 | I13: =F13-E13 -> 0.040306481
B14: No modelizados | D14: 16.448841 | E14: 16.655289 | F14: 16.654831 | H14: =E14-D14 -> 0.20644806 | I14: =F14-E14 -> -0.00045762153

Sheet Anexo I. Cuadro 1
A1: Índice de cuadros
B3: ANEXO I. CUADRO 1. ESTRUCTURA PORCENTUAL DE LA POBLACIÓN SEGÚN TRAMOS ETARIOS
D5: 2002 | E5: 2008 | F5: 2025 | G5: 2030 | H5: 2040 | I5: 2050
B6: Tramos de Edad | C6: De 0 a 14 años | D6: 0.14507122 | E6: 0.14632199 | F6: 0.12913256 | G6: 0.11573179 | H6: 0.10469117 | I6: 0.10388804
C7: De 15 a 74 años | D7: 0.78091684 | E7: 0.77148418 | F7: 0.76830033 | G7: 0.77406663 | H7: 0.75420345 | I7: 0.72003052
C8: De 75 a 100 o más años | D8: 0.074011964 | E8: 0.082193766 | F8: 0.1025671 | G8: 0.11020158 | H8: 0.14110538 | I8: 0.17608144
B10: Fuente: | C10: INE y AIReF

Sheet Gráfico 1
A1: Índice de gráficos
B3: GRÁFICO 1. GASTO BRUTO PÚBLICO EN PENSIONES (% PIB)
C6: 2015 | D6: =C6+1 -> 2016 | E6: =D6+1 -> 2017 | F6: =E6+1 -> 2018 | G6: =F6+1 -> 2019 | H6: =G6+1 -> 2020 | I6: =H6+1 -> 2021 | J6: =I6+1 -> 2022 | K6: =J6+1 -> 2023 | ... AL6: =AK6+1 -> 2050
B7: Histórico | C7: 12.046519 | D7: 12.019989 | E7: 11.896469 | F7: 12.022447 | G7: 12.246009 | H7: 14.018142 | I7: 13.412342 | J7: =+J8 -> 12.638754 | K7: =+K8 -> 12.836698 | L7: =+L8 -> 12.92885 | M7: 12.953716
B8: Histórico | J8: 12.638754 | K8: 12.836698 | L8: 12.92885 | M8: 12.952132 | N8: 13.00615 | O8: 13.111129 | P8: 13.202549 | Q8: 13.329442 | R8: 13.494434 | S8: 13.692483 | T8: 13.918135 | U8: 14.140943 | V8: 14.353598 | W8: 14.549267 | X8: 14.725665 | Y8: 14.881369 | Z8: 15.0263 | AA8: 15.156005 | AB8: 15.261924 | AC8: 15.38985 | AD8: 15.526495 | AE8: 15.668027 | AF8: 15.807338 | AG8: 15.936301 | AH8: 16.050974 | AI8: 16.14051 | AJ8: 16.20188 | AK8: 16.247217 | AL8: 16.273844
B9: AR 2024 actualizado | M9: =M8 -> 12.952132 | N9: =N8 -> 13.00615 | O9: =O8 -> 13.111129 | P9: =P8 -> 13.202549 | Q9: =Q8 -> 13.329442 | R9: =R8 -> 13.494434 | S9: =S8 -> 13.692483 | T9: =T8 -> 13.918135 | ... AL9: =AL8 -> 16.273844
B10: AIReF 2026 | M10: 12.953716 | N10: 13.054792 | O10: 13.254478 | P10: 13.343227 | Q10: 13.419087 | R10: 13.519808 | S10: 13.596648 | T10: 13.701217 | U10: 13.831612 | V10: 14.003178 | W10: 14.199524 | X10: 14.400431 | Y10: 14.60412 | Z10: 14.810245 | AA10: 15.022807 | AB10: 15.236914 | AC10: 15.440385 | AD10: 15.636377 | AE10: 15.805875 | AF10: 15.957269 | AG10: 16.089828 | AH10: 16.197861 | AI10: 16.285446 | AJ10: 16.347253 | AK10: 16.384862 | AL10: 16.398787

Sheet Gráfico 2
A1: Índice de gráficos
B3: GRÁFICO 2. DEUDA PÚBLICA (%PIB)
C5: Deuda Pública
B6: 1995 | C6: 61.586474
B7: 1996 | C7: 65.441953
B8: 1997 | C8: 64.286299
B9: 1998 | C9: 62.354666
B10: 1999 | C10: 60.853144
B11: 2000 | C11: 57.840514
B12: 2001 | C12: 54.052229
B13: 2002 | C13: 51.236868
B14: 2003 | C14: 47.686949
B15: 2004 | C15: 45.332696
B16: 2005 | C16: 42.395191
B17: 2006 | C17: 39.019058
... B23: 2012 | C23: 89.560379
B24: 2013 | C24: 100.01494 | F24: Fuente: | G24: AIReF
B25: 2014 | C25: 104.44838
B26: 2015 | C26: 102.48521
B27: 2016 | C27: 102.02036
B28: 2017 | C28: 101.20718
B29: 2018 | C29: 99.790955
B30: 2019 | C30: 97.659249
B31: 2020 | C31: 119.27911
B32: 2021 | C32: 115.69678
B33: 2022 | C33: 109.32085
B34: 2023 | C34: 105.18212
B35: 2024 | C35: 101.64604
B36: 2025 | C36: 100.65629
... B61: 2050 | C61: 123.34752

Sheet Gráfico 3
A1: Índice de gráficos
B3: GRÁFICO 3. SALDO PÚBLICO (% PIB)
C6: Saldo primario | D6: Saldo total
B7: 1995 | C7: -1.8526525 | D7: -6.793349
B8: 1996 | C8: -0.8346525 | D8: -5.8658829
B9: 1997 | C9: 0.67730181 | D9: -3.8591752
B10: 1998 | C10: 1.4390911 | D10: -2.6269037
B11: 1999 | C11: 2.1713858 | D11: -1.2401679
B12: 2000 | C12: 2.0021033 | D12: -1.1612662
B13: 2001 | C13: 2.5145586 | D13: -0.4549488
B14: 2002 | C14: 2.3149235 | D14: -0.31424059
B15: 2003 | C15: 1.9247947 | D15: -0.37486779
B16: 2004 | C16: 1.8792897 | D16: -0.1094111
B17: 2005 | C17: 2.9761174 | D17: 1.2305494
B18: 2006 | C18: 3.7304373 | D18: 2.1216427
... B21: 2009 | C21: -9.526743 | D21: -11.237383
B22: 2010 | C22: -7.5900645 | D22: -9.4873949 | G22: Fuente: | H22: AIReF
B23: 2011 | C23: -7.2062993 | D23: -9.6917722
B24: 2012 | C24: -8.4695028 | D24: -11.495959
B25: 2013 | C25: -3.924528 | D25: -7.4884074
B26: 2014 | C26: -2.5034915 | D26: -6.0364849
B27: 2015 | C27: -2.1966458 | D27: -5.2660627
B28: 2016 | C28: -1.4403807 | D28: -4.2210501
B29: 2017 | C29: -0.53759581 | D29: -3.0685695
B30: 2018 | C30: -0.11136078 | D30: -2.5524715
B31: 2019 | C31: -0.81286741 | D31: -3.0646641
B32: 2020 | C32: -7.6841059 | D32: -9.909282
B33: 2021 | C33: -4.5329971 | D33: -6.6512124
B34: 2022 | C34: -2.2771163 | D34: -4.5865758
... B62: 2050 | C62: -2.1465477 | D62: -6.5427269

Sheet Gráfico 4
A1: Índice de gráficos
B3: GRÁFICO 4. EVOLUCIÓN DEL GASTO EN PENSIONES (% PIB)
C6: 2015 | D6: =C6+1 -> 2016 | E6: =D6+1 -> 2017 | F6: =E6+1 -> 2018 | G6: =F6+1 -> 2019 | H6: =G6+1 -> 2020 | I6: =H6+1 -> 2021 | J6: =I6+1 -> 2022 | K6: =J6+1 -> 2023 | ... AL6: =AK6+1 -> 2050
B7: Histórico | C7: 12.046519 | D7: 12.019989 | E7: 11.896469 | F7: 12.022447 | G7: 12.246009 | H7: 14.018142 | I7: 13.412342 | J7: =+J8 -> 12.638754 | K7: =+K8 -> 12.836698 | L7: =+L8 -> 12.92885 | M7: 12.953716
B8: Histórico | J8: 12.638754 | K8: 12.836698 | L8: 12.92885 | M8: 12.952132 | N8: 13.00615 | O8: 13.111129 | P8: 13.202549 | Q8: 13.329442 | R8: 13.494434 | S8: 13.692483 | T8: 13.918135 | U8: 14.140943 | V8: 14.353598 | W8: 14.549267 | X8: 14.725665 | Y8: 14.881369 | Z8: 15.0263 | AA8: 15.156005 | AB8: 15.261924 | AC8: 15.38985 | AD8: 15.526495 | AE8: 15.668027 | AF8: 15.807338 | AG8: 15.936301 | AH8: 16.050974 | AI8: 16.14051 | AJ8: 16.20188 | AK8: 16.247217 | AL8: 16.273844 | AN8: =AVERAGE(J8:AL8) -> 14.567182
B9: AR 2024 actualizado | M9: =M8 -> 12.952132 | N9: =N8 -> 13.00615 | O9: =O8 -> 13.111129 | P9: =P8 -> 13.202549 | Q9: =Q8 -> 13.329442 | R9: =R8 -> 13.494434 | S9: =S8 -> 13.692483 | T9: =T8 -> 13.918135 | ... AL9: =AL8 -> 16.273844
B10: Opinión 2025 | M10: 12.994066 | N10: 13.075227 | O10: 13.150043 | P10: 13.209202 | Q10: 13.272752 | R10: 13.38896 | S10: 13.520017 | T10: 13.664946 | U10: 13.834009 | V10: 14.009667 | W10: 14.193417 | X10: 14.382237 | Y10: 14.571124 | Z10: 14.767681 | AA10: 14.967077 | AB10: 15.158819 | AC10: 15.34264 | AD10: 15.515272 | AE10: 15.672087 | AF10: 15.811336 | AG10: 15.928084 | AH10: 16.020618 | AI10: 16.08662 | AJ10: 16.125515 | AK10: 16.140297 | AL10: 16.128704
B11: AIReF 2026 | M11: 12.953716 | N11: 13.054792 | O11: 13.254478 | P11: 13.343227 | Q11: 13.419087 | R11: 13.519808 | S11: 13.596648 | T11: 13.701217 | U11: 13.831612 | V11: 14.003178 | W11: 14.199524 | X11: 14.400431 | Y11: 14.60412 | Z11: 14.810245 | AA11: 15.022807 | AB11: 15.236914 | AC11: 15.440385 | AD11: 15.636377 | AE11: 15.805875 | AF11: 15.957269 | AG11: 16.089828 | AH11: 16.197861 | AI11: 16.285446 | AJ11: 16.347253 | AK11: 16.384862 | AL11: 16.398787
B12: AIReF + Población EUROPOP2025 | M12: =M11 -> 12.953716 | N12: =N11 -> 13.054792 | O12: =O11 -> 13.254478 | P12: =P11 -> 13.343227 | Q12: =Q11 -> 13.419087 | R12: =R11 -> 13.519808 | S12: 13.539784 | T12: 13.64287 | U12: 13.766345 | V12: 13.927143 | W12: 14.110997 | X12: 14.299807 | Y12: 14.492993 | Z12: 14.690922 | AA12: 14.897431 | AB12: 15.105875 | AC12: 15.304544 | AD12: 15.4983 | AE12: 15.668869 | AF12: 15.824351 | AG12: 15.963354 | AH12: 16.080247 | AI12: 16.178204 | AJ12: 16.252364 | AK12: 16.304465 | AL12: 16.334875

Sheet Gráfico 5
A1: Índice de gráficos
B3: GRÁFICO 5. DESCOMPOSICIÓN DEL CRECIMIENTO DEL GASTO EN PENSIONES
C6: 2025-2030 | D6: 2031-2035 | E6: 2036-2040 | F6: 2041-2045 | G6: 2046-2050 | H6: 2051-2055 | I6: 2056-2060 | J6: 2061-2065 | K6: 2066-2070
B7: Revalorización | C7: 0.025017061 | D7: 0.02 | E7: 0.02 | F7: 0.02 | G7: 0.02 | H7: 0.02 | I7: 0.02 | J7: 0.02 | K7: 0.02
B8: Número pensiones | C8: 0.018589173 | D8: 0.020749796 | E8: 0.020595156 | F8: 0.017412354 | G8: 0.011080865 | H8: 0.0047329049 | I8: 0.00077221784 | J8: -0.0011290226 | K8: -0.00068784577
B9: Efecto sustitución | C9: 0.0072822813 | D9: 0.0034676376 | E9: 0.0037874452 | F9: 0.0040261984 | G9: 0.0035851249 | H9: 0.0046779732 | I9: 0.0065773764 | J9: 0.0082753946 | K9: 0.0094821032
B10: Medidas | C10: 0.0041575076
B11: TOTAL | C11: =SUM(C7:C10) -> 0.055046023 | D11: =SUM(D7:D10) -> 0.044217433 | E11: =SUM(E7:E10) -> 0.044382601 | F11: =SUM(F7:F10) -> 0.041438553 | G11: =SUM(G7:G10) -> 0.034665989 | H11: =SUM(H7:H10) -> 0.029410878 | I11: =SUM(I7:I10) -> 0.027349594 | J11: =SUM(J7:J10) -> 0.027146372 | K11: =SUM(K7:K10) -> 0.028794257

Sheet Gráfico 6
A1: Índice de gráficos
B3: GRÁFICO 6. NÚMERO DE PENSIONES (MILLONES)
B5: %PIB | C5: 2025 | D5: 2030 | E5: 2035 | F5: 2040 | G5: 2045 | H5: 2050 | I5: 2055 | J5: 2060 | K5: 2065 | L5: 2070
B6: Seguridad Social | C6: 10.465964 | D6: 11.497554 | E6: 12.740954 | F6: 14.108128 | G6: 15.379862 | H6: 16.250902 | I6: 16.63904 | J6: 16.703351 | K6: 16.60927 | L6: 16.552217
B7: Clases Pasivas | C7: 0.72434517 | D7: 0.78378069 | E7: 0.80619622 | F7: 0.81640001 | G7: 0.79328719 | H7: 0.71243836 | I7: 0.59296495 | J7: 0.46741554 | K7: 0.35187657 | L7: 0.24319569
B8: Pensiones no contributivas | C8: 0.446119 | D8: 0.446119 | E8: 0.446119 | F8: 0.446119 | G8: 0.446119 | H8: 0.446119 | I8: 0.446119 | J8: 0.446119 | K8: 0.446119 | L8: 0.446119
B9: TOTAL | C9: =+C6+C7+C8 -> 11.636428 | D9: =+D6+D7+D8 -> 12.727453 | E9: =+E6+E7+E8 -> 13.993269 | F9: =+F6+F7+F8 -> 15.370647 | G9: =+G6+G7+G8 -> 16.619268 | H9: =+H6+H7+H8 -> 17.409459 | I9: =+I6+I7+I8 -> 17.678124 | J9: =+J6+J7+J8 -> 17.616886 | ... L9: =+L6+L7+L8 -> 17.241532

Sheet Gráfico 7
A1: Índice de gráficos
B3: GRÁFICO 7. TASA DE GENEROSIDAD (PENSIÓN MEDIA/SALARIO MEDIO)
C5: 2015 | D5: 2016 | E5: 2017 | F5: 2018 | G5: 2019 | H5: 2020 | I5: 2021 | J5: 2022 | K5: =J5+1 -> 2023 | L5: =K5+1 -> 2024 | M5: =L5+1 -> 2025 | N5: =M5+1 -> 2026 | O5: =N5+1 -> 2027 | P5: =O5+1 -> 2028 | Q5: =P5+1 -> 2029 | R5: =Q5+1 -> 2030 | ... BF5: =BE5+1 -> 2070
B6: Histórico | C6: 57.048702 | D6: 58.359414 | E6: 59.396877 | F6: 61.076121 | G6: 62.120227 | H6: 65.296382 | I6: 62.806077 | J6: 63.562997 | K6: 66.424094 | L6: 66.927519 | M6: 68.388093
B7: Opinión 2025 | K7: 65.614178 | L7: 65.455195 | M7: 66.36563 | N7: 66.774188 | O7: 66.881965 | P7: 66.984031 | Q7: 67.102167 | R7: 66.758824 | S7: 66.384857 | T7: 65.985611 | U7: 65.515583 | V7: 65.030192 | W7: 64.526633 | X7: 64.015243 | Y7: 63.501733 | Z7: 62.983462 | AA7: 62.452063 | AB7: 61.933325 | AC7: 61.411103 | AD7: 60.888421 | AE7: 60.353428 | AF7: 59.814127 | AG7: 59.275137 | AH7: 58.737826 | AI7: 58.208277 | AJ7: 57.689264 | AK7: 57.183102 | AL7: 56.695891 | AM7: 56.235775 | AN7: 55.813956 | AO7: 55.424607 | AP7: 55.07686 | AQ7: 54.761063 | AR7: 54.481502 | AS7: 54.233869 | AT7: 54.020392 | AU7: 53.835516 | AV7: 53.684994 | AW7: 53.565362 | AX7: 53.476141 | AY7: 53.416965 | AZ7: 53.388178 | BA7: 53.38569 | BB7: 53.407883 | BC7: 53.455438 | BD7: 53.530726 | BE7: 53.627895 | BF7: 53.744424
B8: AIReF 2026 | M8: 68.388093 | N8: 69.043999 | O8: 69.954661 | P8: 70.331816 | Q8: 70.402335 | R8: 70.539068 | S8: 69.975783 | T8: 69.376087 | U8: 68.744737 | V8: 68.316652 | W8: 67.830841 | X8: 67.339312 | Y8: 66.845035 | Z8: 66.362739 | AA8: 65.861767 | AB8: 65.354461 | AC8: 64.851195 | AD8: 64.341752 | AE8: 63.839358 | AF8: 63.327393 | AG8: 62.80463 | AH8: 62.277198 | AI8: 61.739184 | AJ8: 61.204541 | AK8: 60.68111 | AL8: 60.170599 | AM8: 59.687799 | AN8: 59.2371 | AO8: 58.827649 | AP8: 58.46529 | AQ8: 58.151943 | AR8: 57.878452 | AS8: 57.645331 | AT8: 57.445502 | AU8: 57.273231 | AV8: 57.13374 | AW8: 57.020922 | AX8: 56.931055 | AY8: 56.867006 | AZ8: 56.82464 | BA8: 56.808093 | BB8: 56.817477 | BC8: 56.8512 | BD8: 56.912658 | BE8: 57.000063 | BF8: 57.112685

Sheet Gráfico 8A
A1: Índice de gráficos
B2: GRÁFICO 8. PROYECCIONES DE PIB NOMINAL Y POBLACIÓN DEL AR2023 FRENTE A ACTUALES
B3: GRÁFICO 8A. PROYECCIONES DE PIB NOMINAL (MILES DE MILLONES DE EUROS)
C6: PIB AR2024 | D6: PIB AR2024 Actualizado | E6: PIB AIReF
B7: 2022 | C7: 1327108 | D7: 1375863 | E7: 1375863
B8: =+B7+1 -> 2023 | C8: 1412901.8 | D8: 1497761 | E8: 1497761
B9: =+B8+1 -> 2024 | C9: 1482982.2 | D9: 1594330 | E9: 1594330
B10: =+B9+1 -> 2025 | C10: 1545902 | D10: 1687152 | E10: 1687152
B11: =+B10+1 -> 2026 | C11: 1604572.7 | D11: 1751183.5 | E11: 1767851.4
B12: =+B11+1 -> 2027 | C12: 1658500.7 | D12: 1810039 | E12: 1849590.3
B13: =+B12+1 -> 2028 | C13: 1709511.5 | D13: 1865710.6 | E13: 1927977.6
B14: =+B13+1 -> 2029 | C14: 1760204.7 | D14: 1921035.7 | E14: 2003000.2
B15: =+B14+1 -> 2030 | C15: 1810531.2 | D15: 1975960.5 | E15: 2079175.6
G20: Fuente: | H20: INE, Eurostat y AIReF

Sheet Gráfico 8B
A1: Índice de gráficos
B2: GRÁFICO 8. PROYECCIONES DE PIB NOMINAL Y POBLACIÓN DEL AR2023 FRENTE A ACTUALES
B3: GRÁFICO 8B. PROYECCIONES DE POBLACIÓN (MILES DE RESIDENTES)
C6: EUROPOP2025 | D6: EUROPOP2023 | E6: AIReF 2026
B7: 2022 | C7: 47486.727 | D7: 47432.893 | E7: 47486.727
B8: =+B7+1 -> 2023 | C8: 48085.361 | D8: 47980.384 | E8: 48085.361
B9: =+B8+1 -> 2024 | C9: 48619.695 | D9: 48346.319 | E9: 48619.695
B10: =+B9+1 -> 2025 | C10: 49128.297 | D10: 48614.06 | E10: 49128.297
B11: =+B10+1 -> 2026 | C11: 49570.728 | D11: 48822.977 | E11: 49570.436
B12: =+B11+1 -> 2027 | C12: 49976.787 | D12: 48973.279 | E12: 50055.838
B13: =+B12+1 -> 2028 | C13: 50341.56 | D13: 49069.647 | E13: 50548.751
B14: =+B13+1 -> 2029 | C14: 50665.174 | D14: 49167.929 | E14: 51021.979
B15: =+B14+1 -> 2030 | C15: 50947.559 | D15: 49266.93 | E15: 51394.484
G20: Fuente: | H20: INE, Eurostat y AIReF

Sheet Gráfico 9
A1: Índice de gráficos
B3: GRÁFICO 9. INCIDENCIA DEL SMI (PORCENTAJE DE TRABAJADORES SOBRE TOTAL DE AFILIADOS AL RÉGIMEN GENERAL), 2018-2024
C5: Hasta el 100% del SMI | D5: hasta el 125% del SMI
B6: 2018 | C6: 0.030994667 | D6: 0.081908548
B7: 2019 | C7: 0.059527004 | D7: 0.19215197
B8: 2020 | C8: 0.06828052 | D8: 0.21391866
B9: 2021 | C9: 0.065684639 | D9: 0.21287178
B10: 2022 | C10: 0.066104887 | D10: 0.22752121
B11: 2023 | C11: 0.080186604 | D11: 0.25698935
B12: 2024 | C12: 0.091867206 | D12: 0.27072389
H24: Fuente: | I24: AIReF, a partir de la MCVL
H25: Nota: Incidencia calculada como media anual ponderada por personas-mes. Bases de cotización elevadas a jornada y mes completos a nivel episodio-personames. Se excluyen meses-persona coincidentes con prestación o suspensión temporal de empleo. Los niveles difieren ligeramente respecto al DT 9/25 por la mayor desagregación del panel y la depuración de prestaciones. Se han eliminado de la muestra las bases de cotización que superan la base máxima.

Sheet Gráfico 10
A1: Índice de gráficos
B3: GRÁFICO 10. DISTRIBUCIÓN DE LAS BASES DE COTIZACIÓN MENSUALES, 2018, 2023 Y 2024
C6: 2018 | D6: 2023 | E6: 2024
B7: [750,775) | C7: 0 | D7: 0 | E7: 0
B8: [775,800) | C8: 0 | D8: 0 | E8: 0
B9: [800,825) | C9: 0 | D9: 0 | E9: 0
B10: [825,850) | C10: 0 | D10: 0 | E10: 0
B11: [850,875) | C11: 0.019809072 | D11: 0 | E11: 0
B12: [875,900) | C12: 0.0073265123 | D12: 0 | E12: 0
B13: [900,925) | C13: 0.0073191927 | D13: 0 | E13: 0
B14: [925,950) | C14: 0.0070154293 | D14: 0 | E14: 0
B15: [950,975) | C15: 0.009109648 | D15: 0 | E15: 0
B16: [975,1000) | C16: 0.0089898912 | D16: 0 | E16: 0
B17: [1000,1025) | C17: 0.010064246 | D17: 0 | E17: 0
B18: [1025,1050) | C18: 0.010816538 | D18: 0 | E18: 0
... B28: [1275,1300) | C28: 0.022959957 | D28: 0.021614573 | E28: 0
B29: [1300,1325) | C29: 0.023844408 | D29: 0.031904304 | E29: 0.045928046 | H29: Fuente: | I29: AIReF, a partir de la MCVL
B30: [1325,1350) | C30: 0.02259845 | D30: 0.028209532 | E30: 0.022128775 | H30: Nota: Bases de cotización mensuales elevadas a jornada y mes completos a nivel episodiopersona-mes. Se excluyen los meses-persona en los que el episodio laboral coincide con prestación por desempleo o suspensión temporal de empleo.
B31: [1350,1375) | C31: 0.02314254 | D31: 0.02691803 | E31: 0.02954048
B32: [1375,1400) | C32: 0.022542943 | D32: 0.027484892 | E32: 0.024651597
B33: [1400,1425) | C33: 0.023593915 | D33: 0.024329128 | E33: 0.02988999
B34: [1425,1450) | C34: 0.024272401 | D34: 0.023945663 | E34: 0.025540319
B35: [1450,1475) | C35: 0.022331081 | D35: 0.024557662 | E35: 0.02893214
B36: [1475,1500) | C36: 0.022612276 | D36: 0.022903636 | E36: 0.024277688
B37: [1500,1525) | C37: 0.024416557 | D37: 0.025527509 | E37: 0.026294644
B38: [1525,1550) | C38: 0.022098684 | D38: 0.021507016 | E38: 0.024851463
B39: [1550,1575) | C39: 0.021417554 | D39: 0.021840871 | E39: 0.022569375
B40: [1575,1600) | C40: 0.021514539 | D40: 0.021774588 | E40: 0.022487029
B41: [1600,1625) | C41: 0.020565024 | D41: 0.023298285 | E41: 0.022192212
B42: [1625,1650) | C42: 0.018967725 | D42: 0.022741995 | E42: 0.020837273
... B121: [3600,3625) | C121: 0.0027997467 | D121: 0.0039875551 | E121: 0.0043909463

Sheet Gráfico 11A
A1: Índice de gráficos
B3: GRÁFICO 11. A. TASAS DE TRANSICIÓN ENTRE EMPLEO Y NO EMPLEO SEGÚN DURACIÓN DEL EPISODIO. SALIDA DEL NO EMPLEO AL EMPLEO | G3: TASAS DE TRANSICIÓN ENTRE EMPLEO Y NO EMPLEO SEGÚN DURACIÓN DEL EPISODIO
B6: Meses en desempleo/Inactividad | C6: Periodo 2022-2024 | D6: Periodo 2017-2019
B7: 1 | C7: 0.30236678 | D7: 0.30059372
B8: 2 | C8: 0.27054806 | D8: 0.25349386
B9: 3 | C9: 0.22271511 | D9: 0.20705873
B10: 4 | C10: 0.15822169 | D10: 0.14641678
B11: 5 | C11: 0.12593087 | D11: 0.1154989
B12: 6 | C12: 0.10772762 | D12: 0.10074916
B13: 7 | C13: 0.084505436 | D13: 0.080276388
B14: 8 | C14: 0.067045259 | D14: 0.06251878
B15: 9 | C15: 0.06522782 | D15: 0.06125401
B16: 10 | C16: 0.067417124 | D16: 0.0634241
B17: 11 | C17: 0.063048396 | D17: 0.056948304
B18: 12 | C18: 0.051166398 | D18: 0.047780653
G24: Fuente: | H24: AIReF, a partir de la MCVL
G25: Nota: Tasas calculadas con la MCVL-2025 a partir de ficheros de transiciones actualizados. Los niveles pueden diferir de los gráficos descriptivos del DT 8/25 por la incorporación de la nueva ola y por las mejoras en la reconstrucción de las trayectorias laborales, especialmente en la identificación de episodios consecutivos o solapados, el cálculo de su duración efectiva y la depuración de situaciones compatibles con empleo o prestación.

Sheet Gráfico 11B
A1: Índice de gráficos
B3: GRÁFICO 11. B. TASAS DE TRANSICIÓN ENTRE EMPLEO Y NO EMPLEO SEGÚN DURACIÓN DEL EPISODIO. SALIDA DEL EMPLEO AL NO EMPLEO
B6: Meses en empleo | C6: Periodo 2017-2019 | D6: Periodo 2022-2024
B7: 1 | C7: 0.088409297 | D7: 0.072527031
B8: 2 | C8: 0.10819855 | D8: 0.10124616
B9: 3 | C9: 0.086858093 | D9: 0.075834882
B10: 4 | C10: 0.077390015 | D10: 0.063921412
B11: 5 | C11: 0.050638705 | D11: 0.040444214
B12: 6 | C12: 0.055171047 | D12: 0.044198448
B13: 7 | C13: 0.051855785 | D13: 0.03672895
B14: 8 | C14: 0.036033535 | D14: 0.026299726
B15: 9 | C15: 0.034161842 | D15: 0.025240923
B16: 10 | C16: 0.032908813 | D16: 0.024424168
B17: 11 | C17: 0.025331876 | D17: 0.02023139
B18: 12 | C18: 0.046211894 | D18: 0.029099185
... B22: 16 | C22: 0.010609459 | D22: 0.011519804
B23: 17 | C23: 0.010020991 | D23: 0.010856257 | H23: Fuente: | I23: AIReF, a partir de la MCVL
B24: 18 | C24: 0.010364631 | D24: 0.01094447 | H24: Nota: Tasas calculadas con la MCVL-2025 a partir de ficheros de transiciones actualizados. Los niveles pueden diferir de los gráficos descriptivos del DT 8/25 por la incorporación de la nueva ola y por las mejoras en la reconstrucción de las trayectorias laborales, especialmente en la identificación de episodios consecutivos o solapados, el cálculo de su duración efectiva y la depuración de situaciones compatibles con empleo o prestación.
B25: 19 | C25: 0.010281816 | D25: 0.01021103
B26: 20 | C26: 0.010407033 | D26: 0.010565959
B27: 21 | C27: 0.0085530006 | D27: 0.0091798815
B28: 22 | C28: 0.0099510161 | D28: 0.010270682
B29: 23 | C29: 0.0081950782 | D29: 0.0089155009
B30: 24 | C30: 0.013406234 | D30: 0.01085512
B31: 25 | C31: 0.010984552 | D31: 0.0085096037
B32: 26 | C32: 0.007632157 | D32: 0.0077295519
B33: 27 | C33: 0.0076543229 | D33: 0.0073404449
B34: 28 | C34: 0.0068174047 | D34: 0.0070150062
B35: 29 | C35: 0.0068041621 | D35: 0.0063960239
B36: 30 | C36: 0.0062223348 | D36: 0.0058219002
... B42: 36 | C42: 0.0088129102 | D42: 0.0073730601

Sheet Gráfico RE_2.1.
A1: Índice de gráficos
B3: GRÁFICO RE_2.1. TASA DE PARCIALIDAD POR SEXO Y ORIGEN DE LOS INMIGRANTES (%)
C6: Hombres | D6: Mujeres
B7: ASIA | C7: 4.4480911 | D7: 14.473906
B8: EUROPA | C8: 4.9518406 | D8: 21.781389
B9: AMÉRICA | C9: 9.6416021 | D9: 29.666465
B10: ÁFRICA Y ORIENTE PRÓXIMO | C10: 6.6932471 | D10: 31.800084
H23: Fuente: | I23: AIReF a partir de microdatos EPA
H24: Nota: Porcentaje de ocupados a tiempo parcial sobre el total de ocupados.

Sheet Gráfico RE_2.2.
A1: Índice de gráficos
B3: GRÁFICO RE_2.2. ESTIMACIÓN FLUJOS PERSONAS REGULARIZABLES DA21

Sheet Gráfico RE_2.3.
A1: Índice de gráficos
B3: GRÁFICO RE_2.3. AFILIADOS EXTRANJEROS EN 2005: OBSERVADO VS. CONTRAFACTUAL (MILES)
B6: date | C6: excess
B7: 36526 | C7: 0.19531001
B8: 36557 | C8: 0.094582836
B9: 36586 | C9: 0.070296553
B10: 36617 | C10: 0.064414083
B11: 36647 | C11: 0.067743189
B12: 36678 | C12: 0.068582246
B13: 36708 | C13: 0.069028907
B14: 36739 | C14: 0.065372765
B15: 36770 | C15: 0.074980869
B16: 36800 | C16: 0.075144279
B17: 36831 | C17: 0.080167947
B18: 36861 | C18: -0.13964231
... B21: 36951 | C21: 3.2400268
B22: 36982 | C22: -3.0000776 | E22: Fuente: AIReF
B23: 37012 | C23: 4.7758464
B24: 37043 | C24: 0.13519262
B25: 37073 | C25: -11.767496
B26: 37104 | C26: 1.4263932
B27: 37135 | C27: 4.0799195
B28: 37165 | C28: -0.54389605
B29: 37196 | C29: 1.4290612
B30: 37226 | C30: -2.5241358
B31: 37257 | C31: 6.7409098
B32: 37288 | C32: 4.6987897
B33: 37316 | C33: 4.8093846
B34: 37347 | C34: 14.728478
... B61: 38169 | C61: -5.5321008
B62: 38200 | C62: -0.71878641 | E62: Fuente: AIReF
B63: 38231 | C63: 13.077975
B64: 38261 | C64: 4.9635517
B65: 38292 | C65: -11.629424
B66: 38322 | C66: 4.3205173
B67: 38353 | C67: -1.9350255
B68: 38384 | C68: 3.1232337
B69: 38412 | C69: 52.839895
B70: 38443 | C70: 121.51748
B71: 38473 | C71: 165.31255
B72: 38504 | C72: 179.06371
B73: 38534 | C73: 172.92401
B74: 38565 | C74: 169.36507
... B96: 39234 | C96: 102.54706

Sheet Gráfico RE_2.4.
A1: Índice de gráficos
B3: GRÁFICO RE_2.4. BASE MEDIA ANUAL DE COTIZACIÓN DE INMIGRANTES (MILES DE EUROS)
C6: Año 1 | D6: Año 2 | E6: Año 3
B7: Base | C7: 7.23 | D7: 12.31 | E7: 12.38
B8: Rango perfiles demográficos | C8: 3.26 | D8: 4.43 | E8: 6.6
B9: Media ponderada | C9: 8.5982939 | D9: 14.022461 | E9: 13.85721
H26: Fuente: AIReF, a partir de la MCVL-2025

Sheet Gráfico RE_2.5.
A1: Índice de gráficos
B3: GRÁFICO RE_2.5. DISTRIBUCIÓN DEL IMPACTO POTENCIAL DE COTIZACIONES (% PIB) CON DISTINTAS COMBINACIONES DE PARÁMETROS PARA EL PRIMER AÑO19

Sheet Gráfico 12
A1: Índice de gráficos
B3: GRÁFICO 12. FUENTES DE FINANCIACIÓN DEL SISTEMA PÚBLICO DE PENSIONES
D5: Rúbrica | E5: 2020 | F5: =+E5+1 -> 2021 | G5: =+F5+1 -> 2022 | H5: =+G5+1 -> 2023 | I5: =+H5+1 -> 2024 | J5: =+I5+1 -> 2025 | K5: =+J5+1 -> 2026 | L5: =+K5+1 -> 2027 | M5: =+L5+1 -> 2028 | ... BC5: =+BB5+1 -> 2070
B6: Pensiones CPE | C6: Ingreso | D6: Presupuesto del Estado | E6: 1.4646317 | F6: 1.3998675 | G6: 1.3512956 | H6: 1.3928761 | I6: 1.4018938 | J6: 1.3899685 | K6: 1.3967331 | L6: 1.4227349 | M6: 1.4352773 | N6: 1.4385958 | O6: 1.4337258 | P6: 1.4269953 | Q6: 1.4229951 | R6: 1.418984 | S6: 1.417409 | T6: 1.4162515 | U6: 1.4152825 | V6: 1.4145379 | W6: 1.4143539 | X6: 1.4135486 | Y6: 1.4111346 | Z6: 1.4070181 | AA6: 1.3998471 | AB6: 1.3872387 | AC6: 1.3695865 | AD6: 1.3481533 | AE6: 1.3216609 | AF6: 1.2913651 | AG6: 1.2564402 | AH6: 1.2180146 | AI6: 1.1754815 | AJ6: 1.1296479 | AK6: 1.0822855 | AL6: 1.0336789 | AM6: 0.9844413 | AN6: 0.93409571 | AO6: 0.88344461 | AP6: 0.83340464 | AQ6: 0.7848229 | AR6: 0.73781618 | AS6: 0.69282286 | AT6: 0.64929431 | AU6: 0.60737462 | AV6: 0.56693679 | AW6: 0.52803417 | AX6: 0.49107154 | AY6: 0.45476305 | AZ6: 0.41884081 | BA6: 0.38434649 | BB6: 0.35101577 | BC6: 0.31920127
C7: Gasto | D7: Prestaciones en efectivo AC | E7: 1.4646317 | F7: 1.3998675 | G7: 1.3512956 | H7: 1.3928761 | I7: 1.4018938 | J7: 1.3899685 | K7: 1.3967331 | L7: 1.4227349 | M7: 1.4352773 | N7: 1.4385958 | O7: 1.4337258 | P7: 1.4269953 | Q7: 1.4229951 | R7: 1.418984 | S7: 1.417409 | T7: 1.4162515 | U7: 1.4152825 | V7: 1.4145379 | W7: 1.4143539 | X7: 1.4135486 | Y7: 1.4111346 | Z7: 1.4070181 | AA7: 1.3998471 | AB7: 1.3872387 | AC7: 1.3695865 | AD7: 1.3481533 | AE7: 1.3216609 | AF7: 1.2913651 | AG7: 1.2564402 | AH7: 1.2180146 | AI7: 1.1754815 | AJ7: 1.1296479 | AK7: 1.0822855 | AL7: 1.0336789 | AM7: 0.9844413 | AN7: 0.93409571 | AO7: 0.88344461 | AP7: 0.83340464 | AQ7: 0.7848229 | AR7: 0.73781618 | AS7: 0.69282286 | AT7: 0.64929431 | AU7: 0.60737462 | AV7: 0.56693679 | AW7: 0.52803417 | AX7: 0.49107154 | AY7: 0.45476305 | AZ7: 0.41884081 | BA7: 0.38434649 | BB7: 0.35101577 | BC7: 0.31920127
D8: Saldo | E8: =+E6-E7 -> 0 | F8: =+F6-F7 -> 0 | G8: =+G6-G7 -> 0 | H8: =+H6-H7 -> 0 | I8: =+I6-I7 -> 0 | J8: =+J6-J7 -> 0 | K8: =+K6-K7 -> 0 | L8: =+L6-L7 -> 0 | ... BC8: =+BC6-BC7 -> 0
B9: Pensiones contributivas | C9: Ingreso | D9: Cotizaciones SSS dedicadas a pensiones | E9: 9.1977835 | F9: 9.2034777 | G9: 9.0448684 | H9: 9.2477131 | I9: 9.4876331 | J9: 9.6157574 | K9: 9.7046109 | L9: 9.8572704 | M9: 9.8819584 | N9: 9.9204971 | O9: 9.9262247 | P9: 10.062006 | Q9: 10.19443 | R9: 10.217476 | S9: 10.239645 | T9: 10.261624 | U9: 10.281157 | V9: 10.299946 | W9: 10.31802 | X9: 10.33578 | Y9: 10.35308 | Z9: 10.369896 | AA9: 10.386239 | AB9: 10.401532 | AC9: 10.416415 | AD9: 10.431141 | AE9: 10.44078 | AF9: 10.450117 | AG9: 10.459027 | AH9: 10.467371 | AI9: 10.475131 | AJ9: 10.465171 | AK9: 10.455623 | AL9: 10.446797 | AM9: 10.438016 | AN9: 10.42981 | AO9: 10.422043 | AP9: 10.41449 | AQ9: 10.40775 | AR9: 10.401647 | AS9: 10.395993 | AT9: 10.391221 | AU9: 10.38714 | AV9: 10.383495 | AW9: 10.380675 | AX9: 10.378173 | AY9: 10.376399 | AZ9: 10.375122 | BA9: 10.373982 | BB9: 10.373406 | BC9: 10.37318
C10: Ingreso | D10: Transferencias de AC | E10: 0.87487453 | F10: 1.6973494 | G10: 1.583694 | H10: 1.5538112 | I10: 1.6021737 | J10: 1.6729481 | K10: 1.6762143 | L10: 1.7049569 | M10: 1.7048885 | N10: 1.7048281 | O10: 1.7047712 | P10: 1.7047712 | Q10: 1.7047712 | R10: 1.7047712 | S10: 1.7047712 | T10: 1.7047712 | U10: 1.7047712 | V10: 1.7047712 | W10: 1.7047712 | X10: 1.7047712 | Y10: 1.7047712 | Z10: 1.7047712 | AA10: 1.7047712 | AB10: 1.7047712 | AC10: 1.7047712 | AD10: 1.7047712 | AE10: 1.7047712 | AF10: 1.7047712 | AG10: 1.7047712 | AH10: 1.7047712 | AI10: 1.7047712 | AJ10: 1.7047712 | AK10: 1.7047712 | AL10: 1.7047712 | AM10: 1.7047712 | AN10: 1.7047712 | AO10: 1.7047712 | AP10: 1.7047712 | AQ10: 1.7047712 | AR10: 1.7047712 | AS10: 1.7047712 | AT10: 1.7047712 | AU10: 1.7047712 | AV10: 1.7047712 | AW10: 1.7047712 | AX10: 1.7047712 | AY10: 1.7047712 | AZ10: 1.7047712 | BA10: 1.7047712 | BB10: 1.7047712 | BC10: 1.7047712
C12: Gasto | D12: Pensiones SS + complemento a mínimos | E12: 12.325973 | F12: 11.802027 | G12: 11.1183 | H12: 11.321278 | I12: 11.319716 | J12: 11.341479 | K12: 11.426846 | L12: 11.590858 | M12: 11.667065 | N12: 11.739606 | O12: 11.845197 | P12: 11.928768 | Q12: 12.037337 | R12: 12.171743 | S12: 12.344884 | T12: 12.542388 | U12: 12.744263 | V12: 12.948697 | W12: 13.155006 | X12: 13.368374 | Y12: 13.584894 | Z12: 13.792482 | AA12: 13.995644 | AB12: 14.177751 | AC12: 14.346798 | AD12: 14.50079 | AE12: 14.635315 | AF12: 14.753196 | AG12: 14.849927 | AH12: 14.925963 | AI12: 14.982421 | AJ12: 15.021443 | AK12: 15.045384 | AL12: 15.053828 | AM12: 15.04638 | AN12: 15.023052 | AO12: 14.992042 | AP12: 14.952787 | AQ12: 14.907449 | AR12: 14.862264 | AS12: 14.816138 | AT12: 14.776028 | AU12: 14.743204 | AV12: 14.71738 | AW12: 14.702883 | AX12: 14.698745 | AY12: 14.704872 | AZ12: 14.723131 | BA12: 14.75621 | BB12: 14.801487 | BC12: 14.857738
C13: Gasto | D13: No contributivas | E13: 0.2275377 | F13: 0.21044781 | G13: 0.21495045 | H13: 0.21073515 | I13: 0.21578824 | J13: 0.22226868 | K13: 0.23121352 | L13: 0.2408851 | M13: 0.2408851 | N13: 0.2408851 | O13: 0.2408851 | P13: 0.2408851 | Q13: 0.2408851 | R13: 0.2408851 | S13: 0.2408851 | T13: 0.2408851 | U13: 0.2408851 | V13: 0.2408851 | W13: 0.2408851 | X13: 0.2408851 | Y13: 0.2408851 | Z13: 0.2408851 | AA13: 0.2408851 | AB13: 0.2408851 | AC13: 0.2408851 | AD13: 0.2408851 | AE13: 0.2408851 | AF13: 0.2408851 | AG13: 0.2408851 | AH13: 0.2408851 | AI13: 0.2408851 | AJ13: 0.2408851 | AK13: 0.2408851 | AL13: 0.2408851 | AM13: 0.2408851 | AN13: 0.2408851 | AO13: 0.2408851 | AP13: 0.2408851 | AQ13: 0.2408851 | AR13: 0.2408851 | AS13: 0.2408851 | AT13: 0.2408851 | AU13: 0.2408851 | AV13: 0.2408851 | AW13: 0.2408851 | AX13: 0.2408851 | AY13: 0.2408851 | AZ13: 0.2408851 | BA13: 0.2408851 | BB13: 0.2408851 | BC13: 0.2408851
D14: Saldo | E14: =+E9+E10-E12-E13 -> -2.4808526 | F14: =+F9+F10-F12-F13 -> -1.1116475 | G14: =+G9+G10-G12-G13 -> -0.7046881 | H14: =+H9+H10-H12-H13 -> -0.73048915 | I14: =+I9+I10-I12-I13 -> -0.44569711 | J14: =+J9+J10-J12-J13 -> -0.27504212 | K14: =+K9+K10-K12-K13 -> -0.27723378 | L14: =+L9+L10-L12-L13 -> -0.26951559 | ... BC14: =+BC9+BC10-BC12-BC13 -> -3.0206727
B15: TOTAL | C15: Ingresos | E15: =+E6+E9+E10 -> 11.53729 | F15: =+F6+F9+F10 -> 12.300695 | G15: =+G6+G9+G10 -> 11.979858 | H15: =+H6+H9+H10 -> 12.1944 | I15: =+I6+I9+I10 -> 12.491701 | J15: =+J6+J9+J10 -> 12.678674 | K15: =+K6+K9+K10 -> 12.777558 | L15: =+L6+L9+L10 -> 12.984962 | ... BC15: =+BC6+BC9+BC10 -> 12.397152
C16: Gastos | E16: =+E7+E12+E13 -> 14.018142 | F16: =+F7+F12+F13 -> 13.412342 | G16: =+G7+G12+G13 -> 12.684546 | H16: =+H7+H12+H13 -> 12.92489 | I16: =+I7+I12+I13 -> 12.937398 | J16: =+J7+J12+J13 -> 12.953716 | K16: =+K7+K12+K13 -> 13.054792 | L16: =+L7+L12+L13 -> 13.254478 | ... BC16: =+BC7+BC12+BC13 -> 15.417825
C17: Saldo | E17: =+E15-E16 -> -2.4808526 | F17: =+F15-F16 -> -1.1116475 | G17: =+G15-G16 -> -0.7046881 | H17: =+H15-H16 -> -0.73048915 | I17: =+I15-I16 -> -0.44569711 | J17: =+J15-J16 -> -0.27504212 | K17: =+K15-K16 -> -0.27723378 | L17: =+L15-L16 -> -0.26951559 | ... BC17: =+BC15-BC16 -> -3.0206727
D18: Transferencias implícitas | E18: =-E17 -> 2.4808526 | F18: =-F17 -> 1.1116475 | G18: =-G17 -> 0.7046881 | H18: =-H17 -> 0.73048915 | I18: =-I17 -> 0.44569711 | J18: =-J17 -> 0.27504212 | K18: =-K17 -> 0.27723378 | L18: =-L17 -> 0.26951559 | ... BC18: =-BC17 -> 3.0206727

Sheet Gráfico 13A
A1: Índice de gráficos
B2: GRÁFICO 13. POBLACIÓN (MILES DE PERSONAS)
B3: GRÁFICO 13A. POBLACIÓN TOTAL
B19: Fuente: | C19: INE, Eurostat y AIReF
B20: Población total
C21: Histórico | D21: AIReF 2026 | E21: Bandas | G21: EUROPOP2025 | H21: AIReF 2025 | I21: EUROPOP2023
B22: 1990 | C22: 38853.227
B23: 1991 | C23: 38881.416
B24: 1992 | C24: 39051.336
B25: 1993 | C25: 39264.034
B26: 1994 | C26: 39458.489
B27: 1995 | C27: 39639.726
B28: 1996 | C28: 39808.374
B29: 1997 | C29: 39971.329
B30: 1998 | C30: 40143.449
B31: 1999 | C31: 40303.568
B32: 2000 | C32: 40470.182
B33: 2001 | C33: 40665.545
... B53: 2021 | C53: 47400.798
B54: 2022 | C54: 47486.727 | I54: 47432.893
B55: 2023 | C55: 48085.361 | I55: 47980.384
B56: 2024 | C56: 48619.695 | H56: 48619.695 | I56: 48346.319
B57: 2025 | C57: 49128.297 | D57: 49128.297 | E57: 49128.297 | F57: 49128.297 | G57: 49128.297 | H57: 49081.526 | I57: 48614.06
B58: 2026 | D58: 49570.436 | E58: 49632.468 | F58: 49507.656 | G58: 49570.728 | H58: 49371.252 | I58: 48822.977
B59: 2027 | D59: 50055.838 | E59: 50187.34 | F59: 49922.588 | G59: 49976.787 | H59: 49618.267 | I59: 48973.279
B60: 2028 | D60: 50548.751 | E60: 50756.721 | F60: 50336.295 | G60: 50341.56 | H60: 49811.212 | I60: 49069.647
B61: 2029 | D61: 51021.979 | E61: 51312.201 | F61: 50724.664 | G61: 50665.174 | H61: 49976.081 | I61: 49167.929
B62: 2030 | D62: 51394.484 | E62: 51770.831 | F62: 51006.683 | G62: 50947.559 | H62: 50119.31 | I62: 49266.93
B63: 2031 | D63: 51664.574 | E63: 52130.225 | F63: 51183.116 | G63: 51188.48 | H63: 50246.289 | I63: 49363.835
B64: 2032 | D64: 51876.404 | E64: 52433.272 | F64: 51297.52 | G64: 51388.67 | H64: 50363.793 | I64: 49460.401
B65: 2033 | D65: 52042.12 | E65: 52692.716 | F65: 51363.553 | G65: 51588.777 | H65: 50475.535 | I65: 49558.8
B66: 2034 | D66: 52162.939 | E66: 52908.896 | F66: 51383.414 | G66: 51784.85 | H66: 50584.666 | I66: 49656.906
B67: 2035 | D67: 52260.348 | E67: 53103.114 | F67: 51378.372 | G67: 51977.041 | H67: 50691.139 | I67: 49760.92
B68: 2036 | D68: 52333.543 | E68: 53274.398 | F68: 51347.896 | G68: 52165.359 | H68: 50796.355 | I68: 49863.657
B69: 2037 | D69: 52397.903 | E69: 53438.024 | F69: 51307.048 | G69: 52350.887 | H69: 50901.155 | I69: 49963.357
... B82: 2050 | D82: 52728.898 | E82: 55065.464 | F82: 50258.766 | G82: 53877.467 | H82: 52094.597 | I82: 50460.161

Sheet Gráfico 13B
A1: Índice de gráficos
B2: GRÁFICO 13. POBLACIÓN (MILES DE PERSONAS)
B3: GRÁFICO 13B. POBLACIÓN DE 15-74 AÑOS
B18: Fuente: | C18: INE, Eurostat y AIReF
B19: Población en edad de trabajar
C20: Histórico | D20: AIReF 2026 | E20: Bandas | G20: EUROPOP2025 | H20: AIReF 2025 | I20: EUROPOP2023
B21: 1990 | C21: 28828.563
B22: 1991 | C22: 29103.713
B23: 1992 | C23: 29482.022
B24: 1993 | C24: 29861.394
B25: 1994 | C25: 30225.709
B26: 1995 | C26: 30565.552
B27: 1996 | C27: 30848.249
B28: 1997 | C28: 31094.288
B29: 1998 | C29: 31304.887
B30: 1999 | C30: 31488.156
B31: 2000 | C31: 31650.055
B32: 2001 | C32: 31795.799
... B52: 2021 | C52: 36059.396
B53: 2022 | C53: 36196.474 | I53: 36069.646
B54: 2023 | C54: 36763.28 | I54: 36574.611
B55: 2024 | C55: 37266.661 | H55: 37266.661 | I55: 36928.514
B56: 2025 | C56: 37745.287 | D56: 37745.287 | E56: 37745.287 | F56: 37745.287 | G56: 37745.287 | H56: 37697.449 | I56: 37204.985
B57: 2026 | D57: 38177.326 | E57: 38210.985 | F57: 38143.34 | G57: 38185.648 | H57: 37998.549 | I57: 37444.61
B58: 2027 | D58: 38633.313 | E58: 38702.254 | F58: 38563.455 | G58: 38581.256 | H58: 38249.454 | I58: 37626.201
B59: 2028 | D59: 39064.036 | E59: 39169.915 | F59: 38956.211 | G59: 38913.643 | H59: 38421.766 | I59: 37721.644
B60: 2029 | D60: 39459.078 | E60: 39602.686 | F60: 39312.087 | G60: 39192.114 | H60: 38549.914 | I60: 37795.859
B61: 2030 | D61: 39782.755 | E61: 39964.574 | F61: 39595.747 | G61: 39448.752 | H61: 38669.71 | I61: 37878.077
B62: 2031 | D62: 39999.784 | E62: 40220.148 | F62: 39772.108 | G62: 39647.303 | H62: 38753.104 | I62: 37932.661
B63: 2032 | D63: 40150.978 | E63: 40410.276 | F63: 39881.966 | G63: 39791.371 | H63: 38808.706 | I63: 37962.593
B64: 2033 | D64: 40217.445 | E64: 40515.742 | F64: 39906.818 | G64: 39881.547 | H64: 38810.229 | I64: 37939.343
B65: 2034 | D65: 40220.334 | E65: 40557.766 | F65: 39867.755 | G65: 39933.183 | H65: 38778.97 | I65: 37880.087
B66: 2035 | D66: 40183.979 | E66: 40560.594 | F66: 39789.228 | G66: 39954.748 | H66: 38722.54 | I66: 37799.883
B67: 2036 | D67: 40104.576 | E67: 40520.304 | F67: 39667.585 | G67: 39942.102 | H67: 38637.724 | I67: 37687.162
B68: 2037 | D68: 40023.588 | E68: 40478.502 | F68: 39544.132 | G68: 39927.38 | H68: 38555.958 | I68: 37573.29
... B81: 2050 | D81: 37966.416 | E81: 38989.05 | F81: 36875.106 | G81: 38321.532 | H81: 36718.645 | I81: 34998.546

Sheet Gráfico 14A
A1: Índice de gráficos
B2: GRÁFICO 14. TASA DE DEPENDENCIA (% DE LA POBLACIÓN ENTRE 15 Y 74 AÑOS)
B3: GRÁFICO 14A. DESCOMPOSICIÓN DE LA TASA DE DEPENDENCIA
B18: Fuente: | C18: INE y AIReF
B19: Tasa de dependencia
C20: Total | D20: < 15 años | E20: > 74 años
B21: 2002 | C21: =+D21+E21 -> 28.054612 | D21: 18.577039 | E21: 9.4775731
B22: 2003 | C22: =+D22+E22 -> 28.177922 | D22: 18.549583 | E22: 9.6283393
B23: 2004 | C23: =+D23+E23 -> 28.420995 | D23: 18.603893 | E23: 9.8171022
B24: 2005 | C24: =+D24+E24 -> 28.617358 | D24: 18.601201 | E24: 10.016157
B25: 2006 | C25: =+D25+E25 -> 28.925609 | D25: 18.690769 | E25: 10.23484
B26: 2007 | C26: =+D26+E26 -> 29.296793 | D26: 18.840453 | E26: 10.456341
B27: 2008 | C27: =+D27+E27 -> 29.620278 | D27: 18.966299 | E27: 10.653979
B28: 2009 | C28: =+D28+E28 -> 30.173302 | D28: 19.242874 | E28: 10.930428
B29: 2010 | C29: =+D29+E29 -> 30.742178 | D29: 19.501071 | E29: 11.241106
B30: 2011 | C30: =+D30+E30 -> 31.297555 | D30: 19.732963 | E30: 11.564592
B31: 2012 | C31: =+D31+E31 -> 31.821817 | D31: 19.925909 | E31: 11.895908
B32: 2013 | C32: =+D32+E32 -> 32.114665 | D32: 20.025394 | E32: 12.089271
... B69: 2050 | C69: =+D69+E69 -> 38.883002 | D69: 14.428282 | E69: 24.454719

Sheet Gráfico 14B
A1: Índice de gráficos
B2: GRÁFICO 14. TASA DE DEPENDENCIA (% DE LA POBLACIÓN ENTRE 15 Y 74 AÑOS)
B3: GRÁFICO 14B. COMPRATIVA DE TASAS DE DEPENDENCIA
B20: Fuente: | C20: INE, Eurostat y AIReF
B21: Tasa de dependencia
C22: Total | G22: <15
C23: Histórico | D23: AIReF 2026 | E23: EUROPOP2025 | F23: AIReF 2025 | G23: Histórico | H23: AIReF 2026 | I23: EUROPOP2025 | J23: AIReF 2025
B24: 2002 | C24: 28.054612 | G24: 18.577039
B25: 2003 | C25: 28.177922 | G25: 18.549583
B26: 2004 | C26: 28.420995 | G26: 18.603893
B27: 2005 | C27: 28.617358 | G27: 18.601201
B28: 2006 | C28: 28.925609 | G28: 18.690769
B29: 2007 | C29: 29.296793 | G29: 18.840453
B30: 2008 | C30: 29.620278 | G30: 18.966299
B31: 2009 | C31: 30.173302 | G31: 19.242874
B32: 2010 | C32: 30.742178 | G32: 19.501071
B33: 2011 | C33: 31.297555 | G33: 19.732963
B34: 2012 | C34: 31.821817 | G34: 19.925909
B35: 2013 | C35: 32.114665 | G35: 20.025394
... B45: 2023 | C45: 30.797255 | G45: 17.781914
B46: 2024 | C46: 30.464318 | F46: 30.464318 | G46: 17.255039 | J46: 17.255039
B47: 2025 | C47: 30.157434 | D47: 30.157434 | E47: 30.157434 | F47: 30.198533 | G47: 16.807563 | H47: 16.807563 | I47: 16.807563 | J47: 16.797654
B48: 2026 | D48: 29.842607 | E48: 29.815076 | F48: 29.92931 | H48: 16.352661 | I48: 16.384064 | J48: 16.358357
B49: 2027 | D49: 29.566517 | E49: 29.536444 | F49: 29.722811 | H49: 15.934379 | I49: 15.978023 | J49: 15.960737
B50: 2028 | D50: 29.399714 | E50: 29.367379 | F50: 29.643212 | H50: 15.562771 | I50: 15.603276 | J50: 15.60977
B51: 2029 | D51: 29.303523 | E51: 29.273899 | F51: 29.639928 | H51: 15.265978 | I51: 15.294411 | J51: 15.335606
B52: 2030 | D52: 29.187845 | E52: 29.148722 | F52: 29.608704 | H52: 14.95114 | I52: 14.961312 | J52: 15.050077
B53: 2031 | D53: 29.162133 | E53: 29.109614 | F53: 29.657458 | H53: 14.657734 | I53: 14.651478 | J53: 14.794921
B54: 2032 | D54: 29.20334 | E54: 29.145261 | F54: 29.774471 | H54: 14.39446 | I54: 14.374227 | J54: 14.578881
B55: 2033 | D55: 29.401853 | E55: 29.355005 | F55: 30.057297 | H55: 14.192792 | I55: 14.17532 | J55: 14.438456
B56: 2034 | D56: 29.692952 | E56: 29.678744 | F56: 30.443552 | H56: 14.050342 | I56: 14.061416 | J56: 14.374919
B57: 2035 | D57: 30.052694 | E57: 30.089773 | F57: 30.908609 | H57: 13.951007 | I57: 14.0102 | J57: 14.366781
B58: 2036 | D58: 30.492698 | E58: 30.602438 | F58: 31.46829 | H58: 13.897833 | I58: 14.026302 | J58: 14.421037
B59: 2037 | D59: 30.917556 | E59: 31.115257 | F59: 32.018909 | H59: 13.849228 | I59: 14.063445 | J59: 14.488093
... B72: 2050 | D72: 38.883002 | E72: 40.593197 | F72: 41.875055 | H72: 14.428282 | I72: 15.733372 | J72: 16.893498

Sheet Gráfico 15
A1: Índice de gráficos
B3: GRÁFICO 15. CRECIMIENTO PROMEDIO DEL PIB POTENCIAL (%, 2022-2050)
C6: Enter labels below: | D6: Enter values below: | E6: Cumulative | F6: Start & End | G6: Before | H6: After | I6: Data label position
C7: Mix edad | D7: 0.17376152 | E7: 0.17376152 | F7: 0.17376152
C8: Intensidad | D8: 0.33018589 | E8: 0.50394741 | G8: 0.17376152 | H8: 0.50394741 | I8: 0.50394741
C9: Productividad | D9: 0.97191624 | E9: 1.4758637 | G9: 0.50394741 | H9: 1.4758637 | I9: 1.4758637
C10: PIB | D10: 1.4758637 | F10: 1.4758637
K35: Fuente: | L35: AIReF

Sheet Gráfico 16
B3: GRÁFICO 16. TASA DE PARTICIPACIÓN (% POBLACIÓN 15-74 AÑOS)
B5: YEAR | C5: Previsión | D5: Variable
B6: 1980 | C6: 0 | D6: 54.692333
B7: 1981 | C7: 0 | D7: 54.13728
B8: 1982 | C8: 0 | D8: 53.640218
B9: 1983 | C9: 0 | D9: 53.244388
B10: 1984 | C10: 0 | D10: 53.100922
B11: 1985 | C11: 0 | D11: 53.313571
B12: 1986 | C12: 0 | D12: 53.908011
B13: 1987 | C13: 0 | D13: 54.776777
B14: 1988 | C14: 0 | D14: 55.665027
B15: 1989 | C15: 0 | D15: 56.438607
B16: 1990 | C16: 0 | D16: 57.06653
B17: 1991 | C17: 0 | D17: 57.541136
... B23: 1997 | C23: 0 | D23: 59.086658
B24: 1998 | C24: 0 | D24: 59.479823 | F24: Fuente: | G24: AIReF
B25: 1999 | C25: 0 | D25: 59.971141
B26: 2000 | C26: 0 | D26: 60.558669
B27: 2001 | C27: 0 | D27: 61.218212
B28: 2002 | C28: 0 | D28: 61.991165
B29: 2003 | C29: 0 | D29: 62.851306
B30: 2004 | C30: 0 | D30: 63.765556
B31: 2005 | C31: 0 | D31: 64.708085
B32: 2006 | C32: 0 | D32: 65.666157
B33: 2007 | C33: 0 | D33: 66.588075
B34: 2008 | C34: 0 | D34: 67.408118
B35: 2009 | C35: 0 | D35: 68.044683
B36: 2010 | C36: 0 | D36: 68.462871
... B76: 2050 | C76: 1 | D76: 68.254319

Sheet Gráfico 17
B3: GRÁFICO 17. NAWRU (%)
B6: YEAR | C6: Variable | D6: Previsión
B7: 1980 | C7: 10.42395 | D7: 0
B8: 1981 | C8: 11.381134 | D8: 0
B9: 1982 | C9: 12.367829 | D9: 0
B10: 1983 | C10: 12.580955 | D10: 0
B11: 1984 | C11: 13.639915 | D11: 0
B12: 1985 | C12: 14.445715 | D12: 0
B13: 1986 | C13: 14.888036 | D13: 0
B14: 1987 | C14: 15.971059 | D14: 0
B15: 1988 | C15: 16.354711 | D15: 0
B16: 1989 | C16: 16.538768 | D16: 0
B17: 1990 | C17: 16.870927 | D17: 0
B18: 1991 | C18: 17.086501 | D18: 0
... B20: 1993 | C20: 17.926382 | D20: 0
B21: 1994 | C21: 17.793616 | D21: 0 | F21: Fuente: | G21: AIReF
B22: 1995 | C22: 17.325467 | D22: 0
B23: 1996 | C23: 17.027184 | D23: 0
B24: 1997 | C24: 16.552948 | D24: 0
B25: 1998 | C25: 16.011093 | D25: 0
B26: 1999 | C26: 15.246767 | D26: 0
B27: 2000 | C27: 14.80429 | D27: 0
B28: 2001 | C28: 13.900472 | D28: 0
B29: 2002 | C29: 13.905925 | D29: 0
B30: 2003 | C30: 13.680688 | D30: 0
B31: 2004 | C31: 13.588664 | D31: 0
B32: 2005 | C32: 13.38017 | D32: 0
B33: 2006 | C33: 13.511959 | D33: 0
... B77: 2050 | C77: 8.6235838 | D77: 1

Sheet Gráfico 18
A1: Índice de gráficos
B3: GRÁFICO 18. EVOLUCIÓN DE LA RECAUDACIÓN IMPOSITIVA ENTRE 1995 Y 2050 (% PIB)
C6: =+D6-1 -> 1995 | D6: =+E6-1 -> 1996 | E6: =+F6-1 -> 1997 | F6: =+G6-1 -> 1998 | G6: =+H6-1 -> 1999 | H6: =+I6-1 -> 2000 | I6: =+J6-1 -> 2001 | J6: =+K6-1 -> 2002 | ... V6: =+W6-1 -> 2014 | W6: 2015 | X6: =W6+1 -> 2016 | Y6: =X6+1 -> 2017 | Z6: =Y6+1 -> 2018 | AA6: =Z6+1 -> 2019 | AB6: =AA6+1 -> 2020 | AC6: =AB6+1 -> 2021 | AD6: =AC6+1 -> 2022 | AE6: =AD6+1 -> 2023 | ... BF6: =BE6+1 -> 2050
B7: Total impuestos | C7: 17.856957 | D7: 17.929776 | E7: 18.514332 | F7: 19.280459 | G7: 19.461562 | H7: 19.361859 | I7: 19.023323 | J7: 19.525052 | K7: 19.431989 | L7: 20.28969 | M7: 21.417249 | N7: 22.110043 | O7: 22.483633 | P7: 18.120571 | Q7: 15.690934 | R7: 17.367525 | S7: 17.235982 | T7: 18.06393 | U7: 18.796528 | V7: 19.139438 | W7: 19.222674 | X7: 19.108932 | Y7: 19.429003 | Z7: 20.028195 | AA7: 19.624554 | AB7: 20.037743 | AC7: 21.265361 | AD7: 21.549675 | AE7: 21.019976 | AF7: 21.387166 | AG7: 22.527709 | AH7: 22.767975 | AI7: 23.233499 | AJ7: 23.359285 | AK7: 23.626093 | AL7: 23.857901 | AM7: 23.924212 | AN7: 24.05547 | AO7: 24.096043 | AP7: 24.163656 | AQ7: 24.236818 | AR7: 24.313313 | AS7: 24.392177 | AT7: 24.472215 | AU7: 24.554403 | AV7: 24.640829 | AW7: 24.728718 | AX7: 24.81466 | AY7: 24.897328 | AZ7: 24.979114 | BA7: 25.056153 | BB7: 25.128061 | BC7: 25.197847 | BD7: 25.264328 | BE7: 25.322569 | BF7: 25.374769
B8: IRPF | C8: 7.465023 | D8: 7.2644689 | E8: 6.8960537 | F8: 6.9427133 | G8: 6.6809574 | H8: 6.3668961 | I8: 6.5672392 | J8: 6.7142638 | K8: 6.2817344 | L8: 6.2980242 | M8: 6.5903126 | N8: 7.017869 | O8: 7.5538662 | P8: 7.069308 | Q8: 6.6664174 | R8: 6.9773816 | S8: 7.2209693 | T8: 7.5060688 | U8: 7.6113248 | V8: 7.6931591 | W8: 7.3076187 | X8: 7.2329819 | Y8: 7.4130958 | Z8: 7.6919777 | AA8: 7.8991952 | AB8: 8.7636179 | AC8: 8.6321525 | AD8: 8.9688436 | AE8: 8.9714581 | AF8: 9.149486 | AG8: 9.5993378 | AH8: 9.8966233 | AI8: 10.189588 | AJ8: 10.376552 | AK8: 10.601592 | AL8: 10.829474 | AM8: 10.926574 | AN8: 11.07717 | AO8: 11.127224 | AP8: 11.180112 | AQ8: 11.237436 | AR8: 11.296254 | AS8: 11.356219 | AT8: 11.417226 | AU8: 11.479988 | AV8: 11.544026 | AW8: 11.607834 | AX8: 11.671529 | AY8: 11.732585 | AZ8: 11.792288 | BA8: 11.850468 | BB8: 11.906346 | BC8: 11.960465 | BD8: 12.012063 | BE8: 12.061151 | BF8: 12.107728
B9: Impuesto sobre Sociedades | C9: 1.6424657 | D9: 1.7941427 | E9: 2.4447877 | F9: 2.5291685 | G9: 2.6164845 | H9: 2.9168744 | I9: 2.6690384 | J9: 3.0036899 | K9: 2.9872832 | L9: 3.3506219 | M9: 3.8005232 | N9: 4.021312 | O9: 4.5897262 | P9: 2.7606754 | Q9: 2.21385 | R9: 1.8346075 | S9: 1.7757715 | T9: 2.1459627 | U9: 2.0026501 | V9: 1.9801742 | W9: 2.1856994 | X9: 2.1975713 | Y9: 2.2218348 | Z9: 2.4489473 | AA9: 2.0510325 | AB9: 1.954014 | AC9: 2.6168904 | AD9: 2.6621837 | AE9: 2.8212779 | AF9: 2.8642126 | AG9: 3.0563499 | AH9: 3.1913041 | AI9: 3.215065 | AJ9: 3.2220381 | AK9: 3.2921462 | AL9: 3.3317409 | AM9: 3.3504008 | AN9: 3.3682443 | AO9: 3.3853758 | AP9: 3.4011705 | AQ9: 3.4162634 | AR9: 3.431357 | AS9: 3.4465007 | AT9: 3.4618258 | AU9: 3.477074 | AV9: 3.4922959 | AW9: 3.5076085 | AX9: 3.5230879 | AY9: 3.5389638 | AZ9: 3.5549559 | BA9: 3.5710354 | BB9: 3.5872596 | BC9: 3.6034972 | BD9: 3.6198479 | BE9: 3.6363756 | BF9: 3.6530699
B10: IVA | C10: 4.976682 | D10: 5.1128059 | E10: 5.2937982 | F10: 5.5881999 | G10: 5.8873 | H10: 5.8323596 | I10: 5.725527 | J10: 5.5612568 | K10: 5.6902116 | L10: 5.966488 | M10: 6.2237827 | N10: 6.2131881 | O10: 5.8339044 | P10: 4.7174079 | Q10: 3.4389885 | R10: 5.1568506 | S10: 5.0858133 | T10: 5.336151 | U10: 5.9111205 | V10: 6.1688302 | W10: 6.3741362 | X10: 6.3895911 | Y10: 6.4613205 | Z10: 6.5363828 | AA10: 6.4519706 | AB10: 6.2582469 | AC10: 6.7623438 | AD10: 6.842251 | AE10: 6.4115703 | AF10: 6.4287193 | AG10: 6.7828506 | AH10: 6.7575895 | AI10: 6.8600924 | AJ10: 6.8434218 | AK10: 6.8390041 | AL10: 6.833211 | AM10: 6.8129429 | AN10: 6.7988559 | AO10: 6.7892567 | AP10: 6.7963704 | AQ10: 6.8002977 | AR10: 6.8053712 | AS10: 6.8118786 | AT10: 6.8183129 | AU10: 6.8245013 | AV10: 6.8328944 | AW10: 6.8423199 | AX10: 6.8500475 | AY10: 6.8564813 | AZ10: 6.8622855 | BA10: 6.865896 | BB10: 6.8667427 | BC10: 6.8667428 | BD10: 6.8657384 | BE10: 6.8603974 | BF10: 6.8515531
B11: IIEE | C11: 3.7727861 | D11: 3.758358 | E11: 3.8796922 | F11: 4.2203769 | G11: 4.2768199 | H11: 4.2457293 | I11: 4.0615181 | J11: 4.2458414 | K11: 4.4727594 | L11: 4.6745557 | M11: 4.8026303 | N11: 4.857674 | O11: 4.5061363 | P11: 3.5731794 | Q11: 3.3716783 | R11: 3.398685 | S11: 3.153428 | T11: 3.0757473 | U11: 3.2714329 | V11: 3.2972745 | W11: 3.3552201 | X11: 3.2887876 | Y11: 3.3327521 | Z11: 3.3508871 | AA11: 3.222356 | AB11: 3.0618643 | AC11: 3.2539738 | AD11: 3.0763964 | AE11: 2.8156695 | AF11: 2.944748 | AG11: 3.0891704 | AH11: 2.9224578 | AI11: 2.968754 | AJ11: 2.9172729 | AK11: 2.8933511 | AL11: 2.8634753 | AM11: 2.8342936 | AN11: 2.8112 | AO11: 2.7941866 | AP11: 2.7860035 | AQ11: 2.7828207 | AR11: 2.7803308 | AS11: 2.7775788 | AT11: 2.7748505 | AU11: 2.7728401 | AV11: 2.7716124 | AW11: 2.7709553 | AX11: 2.7699956 | AY11: 2.7692981 | AZ11: 2.7695846 | BA11: 2.7687543 | BB11: 2.7677133 | BC11: 2.7671417 | BD11: 2.7666787 | BE11: 2.7646449 | BF11: 2.7624181
B12: Cotizaciones | C12: 12.198972 | D12: 11.985617 | E12: 12.15384 | F12: 12.2176 | G12: 12.419531 | H12: 12.427086 | I12: 12.573307 | J12: 12.546027 | K12: 12.592457 | L12: 12.620937 | M12: 12.580484 | N12: 12.581501 | O12: 12.61163 | P12: 12.707687 | Q12: 12.92313 | R12: 12.769073 | S12: 12.733851 | T12: 12.590741 | U12: 12.432621 | V12: 12.413121 | W12: 12.097006 | X12: 12.07275 | Y12: 12.173255 | Z12: 12.328051 | AA12: 12.814447 | AB12: 14.361671 | AC12: 13.896448 | AD12: 13.088949 | AE12: 13.153167 | AF12: 13.192815 | AG12: 13.253815 | AH12: 13.39879 | AI12: 13.564775 | AJ12: 13.56455 | AK12: 13.586304 | AL12: 13.576358 | AM12: 13.744035 | AN12: 13.895872 | AO12: 13.903372 | AP12: 13.911602 | AQ12: 13.920973 | AR12: 13.92807 | AS12: 13.935101 | AT12: 13.942026 | AU12: 13.949425 | AV12: 13.957046 | AW12: 13.964787 | AX12: 13.97262 | AY12: 13.979715 | AZ12: 13.98696 | BA12: 13.994669 | BB12: 13.996223 | BC12: 13.997999 | BD12: 13.999796 | BE12: 14.001402 | BF12: 14.002773

Sheet Gráfico 19
A1: Índice de gráficos
B3: GRÁFICO 19. EVOLUCIÓN DE LOS RECURSOS HASTA 2050 (% PIB)
C5: 2015 | D5: =C5+1 -> 2016 | E5: =D5+1 -> 2017 | F5: =E5+1 -> 2018 | G5: =F5+1 -> 2019 | H5: =G5+1 -> 2020 | I5: =H5+1 -> 2021 | J5: =I5+1 -> 2022 | K5: =J5+1 -> 2023 | ... AL5: =AK5+1 -> 2050
B6: Histórico | C6: 38.417845 | D6: 37.87431 | E6: 37.948367 | F6: 38.95565 | G6: 38.95215 | H6: 41.468402 | I6: 42.591426 | J6: 41.300478 | K6: 41.33964 | L6: 41.51081 | M6: 42.134082
B7: Opinión 2025 | J7: 41.367647 | K7: 41.196297 | L7: 41.370886 | M7: 41.500683 | N7: 41.433807 | O7: 41.567789 | P7: 41.717595 | Q7: 41.938644 | R7: 42.234873 | S7: 42.437444 | T7: 42.627708 | U7: 42.709547 | V7: 42.791908 | W7: 42.872635 | X7: 42.952875 | Y7: 43.033693 | Z7: 43.123813 | AA7: 43.219331 | AB7: 43.304701 | AC7: 43.390401 | AD7: 43.476219 | AE7: 43.555488 | AF7: 43.636614 | AG7: 43.713276 | AH7: 43.779817 | AI7: 43.842841 | AJ7: 43.899836 | AK7: 43.952004 | AL7: 43.995011
B8: AIReF 2026 | M8: 42.134082 | N8: 42.462538 | O8: 42.975548 | P8: 42.941373 | Q8: 43.163115 | R8: 43.302211 | S8: 43.420369 | T8: 43.591675 | U8: 43.639748 | V8: 43.715591 | W8: 43.798124 | X8: 43.881716 | Y8: 43.967611 | Z8: 44.054574 | AA8: 44.144162 | AB8: 44.238208 | AC8: 44.333838 | AD8: 44.427613 | AE8: 44.517376 | AF8: 44.606407 | AG8: 44.691155 | AH8: 44.764617 | AI8: 44.836179 | AJ8: 44.904457 | AK8: 44.964303 | AL8: 45.017875

Sheet Gráfico 20
A1: Índice de gráficos
B3: GRÁFICO 20. EMPLEOS NO FINANCIEROS SIN PRTR (% PIB)
C5: 2015 | D5: =C5+1 -> 2016 | E5: =D5+1 -> 2017 | F5: =E5+1 -> 2018 | G5: =F5+1 -> 2019 | H5: =G5+1 -> 2020 | I5: =H5+1 -> 2021 | J5: =I5+1 -> 2022 | K5: =J5+1 -> 2023 | ... AL5: =AK5+1 -> 2050
B6: Histórico | C6: 43.683907 | D6: 42.09536 | E6: 41.016936 | F6: 41.508122 | G6: 42.016814 | H6: 51.377684 | I6: 49.242667 | J6: 45.887054 | K6: 44.679759 | L6: 45.47371 | M6: 44.5245
B7: AIReF 2026 | M7: 44.5245 | N7: 45.032432 | O7: 45.166551 | P7: 45.238487 | Q7: 45.452658 | R7: 45.688101 | S7: 45.906229 | T7: 46.127728 | U7: 46.345929 | V7: 46.626974 | W7: 46.941664 | X7: 47.258174 | Y7: 47.564259 | Z7: 47.879152 | AA7: 48.213252 | AB7: 48.565309 | AC7: 48.928973 | AD7: 49.283907 | AE7: 49.620082 | AF7: 49.946475 | AG7: 50.261869 | AH7: 50.560338 | AI7: 50.849516 | AJ7: 51.114759 | AK7: 51.359113 | AL7: 51.574935
B8: Opinión 2025 | K8: 44.711491 | L8: 44.414972 | M8: 44.19906 | N8: 44.123365 | O8: 44.304185 | P8: 44.515479 | Q8: 44.798935 | R8: 45.012912 | S8: 45.291402 | T8: 45.57186 | U8: 45.845101 | V8: 46.1182 | W8: 46.416327 | X8: 46.727116 | Y8: 47.036892 | Z8: 47.373285 | AA8: 47.718744 | AB8: 48.063252 | AC8: 48.420461 | AD8: 48.770367 | AE8: 49.117221 | AF8: 49.451576 | AG8: 49.768211 | AH8: 50.064879 | AI8: 50.340805 | AJ8: 50.589688 | AK8: 50.818021 | AL8: 51.014388

Sheet Gráfico 21
A1: Índice de gráficos
C4: Tipo de interés implícito | D4: Tipo interés nuevas emisiones
B5: 1995 | D5: 10.1 | G5: Gráfico 21 | H5: PROYECCIÓN TIPO MEDIO DE EMISIÓN Y TIPO IMPLÍCITO
B6: 1996 | C6: 8.6785561 | D6: 7.47
B7: 1997 | C7: 7.3577437 | D7: 5.38
B8: 1998 | C8: 6.7707299 | D8: 4.32
B9: 1999 | C9: 5.8620109 | D9: 3.77
B10: 2000 | C10: 5.6553486 | D10: 4.98
B11: 2001 | C11: 5.557228 | D11: 4.54
B12: 2002 | C12: 5.2026557 | D12: 4.171
B13: 2003 | C13: 4.8052125 | D13: 2.942
B14: 2004 | C14: 4.468421 | D14: 2.936
B15: 2005 | C15: 4.1552966 | D15: 2.801
B16: 2006 | C16: 4.1089858 | D16: 3.472
B17: 2007 | C17: 4.3375681 | D17: 4.198
... B19: 2009 | C19: 4.1657119 | D19: 2.148
B20: 2010 | C20: 3.5883637 | D20: 2.554 | G20: Fuente: | H20: AIReF
B21: 2011 | C21: 4.0917964 | D21: 3.897
B22: 2012 | C22: 4.2195395 | D22: 3.008
B23: 2013 | C23: 3.9396936 | D23: 2.452
B24: 2014 | C24: 3.5782622 | D24: 1.519
B25: 2015 | C25: 3.074923 | D25: 0.841
B26: 2016 | C26: 2.8027275 | D26: 0.611
B27: 2017 | C27: 2.5848095 | D27: 0.622
B28: 2018 | C28: 2.4990958 | D28: 0.646
B29: 2019 | C29: 2.3336385 | D29: 0.231
B30: 2020 | C30: 2.0522496 | D30: 0.178
B31: 2021 | C31: 1.9429566 | D31: -0.035
B32: 2022 | C32: 2.2229551 | D32: 1.345
... B60: 2050 | C60: 3.7646208 | D60: 3.7568125

Sheet Gráfico 22
A1: Índice de gráficos
C4: Intereses
B5: 1995 | C5: 4.9406964 | E5: Gráfico 22 | F5: INTERESES (%PIB)
B6: 1996 | C6: 5.0312304
B7: 1997 | C7: 4.536477
B8: 1998 | C8: 4.0659948
B9: 1999 | C9: 3.4115536
B10: 2000 | C10: 3.1633695
B11: 2001 | C11: 2.9695074
B12: 2002 | C12: 2.6291641
B13: 2003 | C13: 2.2996625
B14: 2004 | C14: 1.9887008
B15: 2005 | C15: 1.7455679
B16: 2006 | C16: 1.6087946
B17: 2007 | C17: 1.5785014
... B19: 2009 | C19: 1.7106404
B20: 2010 | C20: 1.8973304 | E20: Fuente: | F20: AIReF
B21: 2011 | C21: 2.4854729
B22: 2012 | C22: 3.0264565
B23: 2013 | C23: 3.5638794
B24: 2014 | C24: 3.5329934
B25: 2015 | C25: 3.069417
B26: 2016 | C26: 2.7806694
B27: 2017 | C27: 2.5309737
B28: 2018 | C28: 2.4411108
B29: 2019 | C29: 2.2517967
B30: 2020 | C30: 2.2251761
B31: 2021 | C31: 2.1182154
B32: 2022 | C32: 2.3094596
... B60: 2050 | C60: 4.3642818

Sheet Gráfico 23
A1: Índice de gráficos
B3: GRÁFICO 23. EVOLUCIÓN DEL GASTO EN SANIDAD (% PIB)
C5: 2015 | D5: =C5+1 -> 2016 | E5: =D5+1 -> 2017 | F5: =E5+1 -> 2018 | G5: =F5+1 -> 2019 | H5: =G5+1 -> 2020 | I5: =H5+1 -> 2021 | J5: =I5+1 -> 2022 | K5: =J5+1 -> 2023 | ... AL5: =AK5+1 -> 2050
B6: Histórico | C6: 6.1156532 | D6: 6.0298299 | E6: 5.9227845 | F6: 5.951285 | G6: 6.0553876 | H6: 7.5756234 | I6: 7.1665612 | J6: 6.7831608 | K6: 6.5847622 | L6: 6.4567561 | M6: 6.471819
B7: AIReF 2026 | M7: 6.471819 | N7: 6.4245231 | O7: 6.4922414 | P7: 6.4989002 | Q7: 6.5282741 | R7: 6.5642222 | S7: 6.604549 | T7: 6.6696653 | U7: 6.7460296 | V7: 6.8400906 | W7: 6.9315014 | X7: 7.013751 | Y7: 7.0880305 | Z7: 7.1583976 | AA7: 7.2309326 | AB7: 7.3044328 | AC7: 7.3786243 | AD7: 7.4503745 | AE7: 7.5178964 | AF7: 7.585609 | AG7: 7.651866 | AH7: 7.7166338 | AI7: 7.7792112 | AJ7: 7.8377095 | AK7: 7.8912856 | AL7: 7.9394281
B8: Opinión 2025 | M8: 6.4599617 | N8: 6.4551479 | O8: 6.473635 | P8: 6.5060996 | Q8: 6.5479922 | R8: 6.6109817 | S8: 6.6834192 | T8: 6.7645203 | U8: 6.8544761 | V8: 6.9380963 | W8: 7.0185358 | X8: 7.096436 | Y8: 7.1738368 | Z8: 7.2532871 | AA8: 7.3331751 | AB8: 7.4098218 | AC8: 7.4857143 | AD8: 7.5612726 | AE8: 7.6341428 | AF8: 7.704005 | AG8: 7.7687007 | AH8: 7.8284231 | AI8: 7.8825312 | AJ8: 7.9308269 | AK8: 7.9737978 | AL8: 8.0105771

Sheet Gráfico 24
A1: Índice de gráficos
B3: GRÁFICO 24. EVOLUCIÓN DEL GASTO EN CUIDADOS DE LARGA DURACIÓN (% PIB)
C5: 2015 | D5: =C5+1 -> 2016 | E5: =D5+1 -> 2017 | F5: =E5+1 -> 2018 | G5: =F5+1 -> 2019 | H5: =G5+1 -> 2020 | I5: =H5+1 -> 2021 | J5: =I5+1 -> 2022 | K5: =J5+1 -> 2023 | ... AL5: =AK5+1 -> 2050
B6: Histórico | C6: 0.69765954 | D6: 0.68751106 | E6: 0.69518262 | F6: 0.70550672 | G6: 0.71770915 | H6: 0.81336906 | I6: 0.77609659 | J6: 0.7579772 | K6: 0.72374698 | L6: 0.81173418 | M6: 0.82996582
B7: AIReF | M7: 0.82996582 | N7: 0.89712469 | O7: 0.90687537 | P7: 0.91956434 | Q7: 0.93497416 | R7: 0.9463415 | S7: 0.96917227 | T7: 0.99043814 | U7: 1.014414 | V7: 1.0430827 | W7: 1.0689803 | X7: 1.0985937 | Y7: 1.1247638 | Z7: 1.1544056 | AA7: 1.1885259 | AB7: 1.2206063 | AC7: 1.2517898 | AD7: 1.2819655 | AE7: 1.3146136 | AF7: 1.3491242 | AG7: 1.3832174 | AH7: 1.4168448 | AI7: 1.4511233 | AJ7: 1.488254 | AK7: 1.5249284 | AL7: 1.5624242
B8: Opinión 2025 | M8: 0.81873674 | N8: 0.82252935 | O8: 0.82001455 | P8: 0.83298448 | Q8: 0.8468645 | R8: 0.86750745 | S8: 0.89347338 | T8: 0.91441011 | U8: 0.93826039 | V8: 0.96412238 | W8: 0.98817436 | X8: 1.0154746 | Y8: 1.040039 | Z8: 1.0682802 | AA8: 1.0992762 | AB8: 1.1281554 | AC8: 1.1569584 | AD8: 1.1855339 | AE8: 1.2165069 | AF8: 1.2484764 | AG8: 1.280007 | AH8: 1.3113987 | AI8: 1.342869 | AJ8: 1.3767368 | AK8: 1.4106461 | AL8: 1.4452309

Sheet Gráfico 25
A1: Índice de gráficos
B3: GRÁFICO 25. EVOLUCIÓN DEL GASTO EN EDUCACIÓN (% PIB)
C5: 2015 | D5: =C5+1 -> 2016 | E5: =D5+1 -> 2017 | F5: =E5+1 -> 2018 | G5: =F5+1 -> 2019 | H5: =G5+1 -> 2020 | I5: =H5+1 -> 2021 | J5: =I5+1 -> 2022 | K5: =J5+1 -> 2023 | ... AL5: =AK5+1 -> 2050
B6: Histórico | C6: 4.0832959 | D6: 4.0364499 | E6: 3.9693203 | F6: 3.9400269 | G6: 3.9923108 | H6: 4.6052387 | I6: 4.5233651 | J6: 4.26416 | K6: 4.2089492 | L6: 4.1310143 | M6: 3.9823301
B7: AIReF | M7: 3.9823301 | N7: 3.9363503 | O7: 3.9972634 | P7: 3.987221 | Q7: 3.9807646 | R7: 3.9538204 | S7: 3.9300106 | T7: 3.8928868 | U7: 3.8440565 | V7: 3.7906063 | W7: 3.7375279 | X7: 3.6832638 | Y7: 3.6271055 | Z7: 3.5739194 | AA7: 3.5268185 | AB7: 3.4863204 | AC7: 3.4521213 | AD7: 3.4227081 | AE7: 3.3979361 | AF7: 3.3773125 | AG7: 3.360994 | AH7: 3.3492266 | AI7: 3.3412316 | AJ7: 3.3350103 | AK7: 3.3303737 | AL7: 3.3263002
B8: Opinión 2025 | K8: 4.2073677 | L8: 4.0631714 | M8: 4.0365117 | N8: 3.9798076 | O8: 3.9532092 | P8: 3.9383704 | Q8: 3.9210063 | R8: 3.9041296 | S8: 3.874634 | T8: 3.8322566 | U8: 3.7804871 | V8: 3.7255554 | W8: 3.6719779 | X8: 3.6204124 | Y8: 3.5724892 | Z8: 3.5306294 | AA8: 3.4940749 | AB8: 3.4634756 | AC8: 3.4386532 | AD8: 3.4211006 | AE8: 3.4107934 | AF8: 3.4049331 | AG8: 3.405154 | AH8: 3.4099506 | AI8: 3.419117 | AJ8: 3.4318147 | AK8: 3.4465239 | AL8: 3.4631029

Sheet Gráfico 26
A1: Índice de gráficos
B3: GRÁFICO 26. EVOLUCIÓN DEL GASTO EN PRESTACIONES POR DESEMPLEO (% PIB)
C5: 2015 | D5: =C5+1 -> 2016 | E5: =D5+1 -> 2017 | F5: =E5+1 -> 2018 | G5: =F5+1 -> 2019 | H5: =G5+1 -> 2020 | I5: =H5+1 -> 2021 | J5: =I5+1 -> 2022 | K5: =J5+1 -> 2023 | ... AL5: =AK5+1 -> 2050
B6: Histórico | C6: 1.9163619 | D6: 1.6566286 | E6: 1.4869269 | F6: 1.4272856 | G6: 1.4916528 | H6: 3.2086921 | I6: 2.077826 | J6: 1.4849589 | K6: 1.456908 | L6: 1.4512679 | M6: 1.4483579
B7: AIReF | M7: 1.4483579 | N7: 1.3751207 | O7: 1.317633 | P7: 1.2862749 | Q7: 1.2614562 | R7: 1.2423457 | S7: 1.249118 | T7: 1.256065 | U7: 1.2630579 | V7: 1.2718049 | W7: 1.280808 | X7: 1.2821566 | Y7: 1.2832965 | Z7: 1.2838907 | AA7: 1.2846301 | AB7: 1.2855116 | AC7: 1.2863107 | AD7: 1.2866895 | AE7: 1.2862122 | AF7: 1.2856645 | AG7: 1.2850904 | AH7: 1.2844997 | AI7: 1.2841626 | AJ7: 1.2838672 | AK7: 1.2833767 | AL7: 1.2826522
B8: Opinión 2025 | K8: 1.4563606 | L8: 1.4119643 | M8: 1.349457 | N8: 1.291675 | O8: 1.2458159 | P8: 1.1964489 | Q8: 1.1609552 | R8: 1.1615668 | S8: 1.1615962 | T8: 1.1612887 | U8: 1.1616548 | V8: 1.1618966 | W8: 1.1619272 | X8: 1.1615939 | Y8: 1.1609961 | Z8: 1.1605362 | AA8: 1.1600609 | AB8: 1.1589235 | AC8: 1.1575863 | AD8: 1.1562319 | AE8: 1.1545788 | AF8: 1.152904 | AG8: 1.1510859 | AH8: 1.1491467 | AI8: 1.1470647 | AJ8: 1.144791 | AK8: 1.1425259 | AL8: 1.1400898

Sheet Gráfico 27
A1: Índice de gráficos
B3: GRÁFICO 27. EVOLUCIÓN DE LA RATIO DE DEUDA (% PIB)
C6: Deuda sobre PIB
B7: 1995 | C7: 61.586474
B8: 1996 | C8: 65.441953
B9: 1997 | C9: 64.286299
B10: 1998 | C10: 62.354666
B11: 1999 | C11: 60.853144
B12: 2000 | C12: 57.840514
B13: 2001 | C13: 54.052229
B14: 2002 | C14: 51.236868
B15: 2003 | C15: 47.686949
B16: 2004 | C16: 45.332696
B17: 2005 | C17: 42.395191
B18: 2006 | C18: 39.019058
... B28: 2016 | C28: 102.02036
B29: 2017 | C29: 101.20718 | F29: Fuente: | G29: Banco España, INE y AIReF
B30: 2018 | C30: 99.790955
B31: 2019 | C31: 97.659249
B32: 2020 | C32: 119.27911
B33: 2021 | C33: 115.69678
B34: 2022 | C34: 109.32085
B35: 2023 | C35: 105.18212
B36: 2024 | C36: 101.64604
B37: 2025 | C37: 100.65629

Sheet Gráfico 28
A1: Índice de gráficos
B3: GRÁFICO 28. DEUDA (%PIB), PAÍSES DE LA UNIÓN EUROPEA CON MÁS DEL 80%
C7: Deuda en 2019 T4 | D7: Deuda en 2020 T4 | E7: Deuda en 2025 T4 | F7: Variación deuda entre 2019 T4 y 2025 T4 | G7: Reducción desde el máximo
B8: Grecia | C8: 183.2 | D8: 209.4 | E8: 146.1 | F8: -37.1 | G8: -63.3
B9: Italia | C9: 133.9 | D9: 154.4 | E9: 137.1 | F9: 3.2 | G9: -17.3
B10: Francia | C10: 98.2 | D10: 114.9 | E10: 116.2 | F10: 18 | G10: 1.3
B11: Bélgica | C11: 97.7 | D11: 111.4 | E11: 107.9 | F11: 10.2 | G11: -3.5
B12: España | C12: 97.7 | D12: 119.3 | E12: 100.7 | F12: 3 | G12: -18.6
B13: Portugal | C13: 116.1 | D13: 134.1 | E13: 89.7 | F13: -26.4 | G13: -44.4
B14: Finlandia | C14: 65.3 | D14: 75.3 | E14: 88.5 | F14: 23.2 | G14: 13.2
B15: Zona euro | C15: 83.6 | D15: 96.5 | E15: 87.9 | F15: 4.3 | G15: -8.6
B16: UE | C16: 77.5 | D16: 89.5 | E16: 81.7 | F16: 4.2 | G16: -7.8
B17: Austria | C17: 71 | D17: 83.2 | E17: 81.5 | F17: 10.5 | G17: -1.7
B18: Hungría | C18: 65 | D18: 78.7 | E18: 74.6 | F18: 9.6 | G18: -4.1
B19: Eslovenia | C19: 66 | D19: 80.2 | E19: 65.7 | F19: -0.3 | G19: -14.5
... B32: Irlanda | C32: 55.8 | D32: 56.9 | E32: 32.9 | F32: -22.9 | G32: -24
B33: Bulgaria | C33: 20.1 | D33: 24.5 | E33: 29.9 | F33: 9.8 | G33: 5.4 | I33: Fuente: | J33: Banco de España y Eurostat
B34: Dinamarca | C34: 38.3 | D34: 45.2 | E34: 27.9 | F34: -10.4 | G34: -17.3
B35: Luxemburgo | C35: 22.3 | D35: 24.5 | E35: 26.5 | F35: 4.2 | G35: 2
B36: Estonia | C36: 9 | D36: 19.1 | E36: 24.1 | F36: 15.1 | G36: 5

Sheet Gráfico 29
A1: Índice de gráficos
B3: GRÁFICO 29. DEUDA PÚBLICA (%PIB)
C6: Deuda Pública
B7: 1995 | C7: 61.586474
B8: 1996 | C8: 65.441953
B9: 1997 | C9: 64.286299
B10: 1998 | C10: 62.354666
B11: 1999 | C11: 60.853144
B12: 2000 | C12: 57.840514
B13: 2001 | C13: 54.052229
B14: 2002 | C14: 51.236868
B15: 2003 | C15: 47.686949
B16: 2004 | C16: 45.332696
B17: 2005 | C17: 42.395191
B18: 2006 | C18: 39.019058
... B24: 2012 | C24: 89.560379
B25: 2013 | C25: 100.01494 | F25: Fuente: | G25: AIReF
B26: 2014 | C26: 104.44838
B27: 2015 | C27: 102.48521
B28: 2016 | C28: 102.02036
B29: 2017 | C29: 101.20718
B30: 2018 | C30: 99.790955
B31: 2019 | C31: 97.659249
B32: 2020 | C32: 119.27911
B33: 2021 | C33: 115.69678
B34: 2022 | C34: 109.32085
B35: 2023 | C35: 105.18212
B36: 2024 | C36: 101.64604
B37: 2025 | C37: 100.65629
... B62: 2050 | C62: 123.34752

Sheet Gráfico 30
A1: Índice de gráficos
B3: GRÁFICO 30. DIFERENCIA CON OPINIÓN DE 2025 EN LA RATIO DE DEUDA EN 2050 (P.P)
B7: Diferencia de la ratio a en 2050 | C7: -6.4416255
B8: Mejor punto de partida 2025 | C8: 0.13134696
B9: Gasto intereses | C9: -5.2257679
B10: Crecimiento Real | C10: 1.0117904
B11: Inflación | C11: 1.1818039
B12: Déficit primario | C12: -5.3134502
B13: Aj. stock flujo | C13: 1.8150755
F26: Fuente: | G26: AIReF

Sheet Gráfico 31.A.
A1: Índice de gráficos
B3: GRÁFICO 31. A. CONTRIBUCIONES A LA VARIACIÓN DE LA DEUDA (P.P), POR AÑOS
C6: Var. Deuda | D6: Gasto intereses | E6: Crecimiento | F6: Crecimiento Real | G6: Inflación | H6: Déficit primario | I6: Aj. stock flujo | K6: Diferencial interés-crecimiento | L6: Déficit primario y stock-flujo
B7: 2021 | C7: -3.5823302 | D7: 2.1182154 | E7: -10.258895 | F7: -7.379103 | G7: -2.8797918 | H7: 4.5329971 | I7: 0.025352213 | K7: -8.1406795 | L7: 4.5583493
B8: 2022 | C8: -6.3759297 | D8: 2.3094596 | E8: -11.805358 | F8: -6.7735563 | G8: -5.0318013 | H8: 2.2771163 | I8: 0.84285209 | K8: -9.495898 | L8: 3.1199683
B9: 2023 | C9: -4.1387288 | D9: 2.3736097 | E9: -8.8972757 | F9: -2.5484835 | G9: -6.3487922 | H9: 0.96650934 | I9: 1.4184279 | K9: -6.523666 | L9: 2.3849372
B10: 2024 | C10: -3.5360778 | D10: 2.4331851 | E10: -6.3709094 | F10: -3.4634798 | G10: -2.9074295 | H10: 0.78239762 | I10: -0.38075116 | K10: -3.9377243 | L10: 0.40164646
B11: 2025 | C11: -0.9897518 | D11: 2.3894705 | E11: -5.5922577 | F11: -2.7530279 | G11: -2.8392297 | H11: 0.00094834372 | I11: 2.212087 | K11: -3.2027871 | L11: 2.2130353
B12: 2026 | C12: -0.86082994 | D12: 2.4641361 | E12: -4.594788 | F12: -2.1739882 | G12: -2.4207998 | H12: 0.10576208 | I12: 1.1640599 | K12: -2.1306519 | L12: 1.269822
B13: 2027 | C13: -1.6250837 | D13: 2.5432794 | E13: -4.4102603 | F13: -1.8935045 | G13: -2.5167557 | H13: -0.35227309 | I13: 0.59417026 | K13: -1.8669809 | L13: 0.24189717
B14: 2028 | C14: -1.3405959 | D14: 2.6574124 | E14: -3.991388 | F14: -1.80211 | G14: -2.189278 | H14: -0.36029472 | I14: 0.35367441 | K14: -1.3339756 | L14: -0.0066203142
B15: 2029 | C15: -0.94598025 | D15: 2.706432 | E15: -3.6267685 | F15: -1.652262 | G15: -1.9745065 | H15: -0.41688485 | I15: 0.39124106 | K15: -0.92033647 | L15: -0.025643784
B16: 2030 | C16: -0.85209902 | D16: 2.8060376 | E16: -3.5129278 | F16: -1.6152638 | G16: -1.897664 | H16: -0.484525 | I16: 0.33931613 | K16: -0.70689015 | L16: -0.14520887
B17: 2031 | C17: -1.0421782 | D17: 2.9281522 | E17: -3.4859759 | F17: -1.6388353 | G17: -1.8471406 | H17: -0.48435452 | I17: 0 | K17: -0.55782372 | L17: -0.48435452
B18: 2032 | C18: -0.79114352 | D18: 2.9846119 | E18: -3.2785145 | F18: -1.4499385 | G18: -1.828576 | H18: -0.49724088 | I18: 0 | K18: -0.29390264 | L18: -0.49724088
... B25: 2039 | C25: 1.2527025 | D25: 3.3006527 | E25: -2.7583915 | F25: -0.89242032 | G25: -1.8659712 | H25: 0.71044133 | I25: 0 | K25: 0.54226116 | L25: 0.71044133
B26: 2040 | C26: 1.4931534 | D26: 3.3687809 | E26: -2.7774808 | F26: -0.88689206 | G26: -1.8905887 | H26: 0.90185331 | I26: 0 | K26: 0.59130006 | L26: 0.90185331 | O26: Fuente: | P26: AIReF
B27: 2041 | C27: 1.7157567 | D27: 3.4527948 | E27: -2.8247294 | F27: -0.90504286 | G27: -1.9196866 | H27: 1.0876913 | I27: 0 | K27: 0.62806538 | L27: 1.0876913
B28: 2042 | C28: 1.9115508 | D28: 3.5349176 | E28: -2.8926348 | F28: -0.93964856 | G28: -1.9529862 | H28: 1.2692679 | I28: 0 | K28: 0.64228286 | L28: 1.2692679
B29: 2043 | C29: 2.0431739 | D29: 3.6225275 | E29: -3.0101048 | F29: -1.0204371 | G29: -1.9896677 | H29: 1.4307512 | I29: 0 | K29: 0.61242268 | L29: 1.4307512
B30: 2044 | C30: 2.2150506 | D30: 3.7125415 | E30: -3.0789931 | F30: -1.0495514 | G30: -2.0294417 | H30: 1.5815022 | I30: 0 | K30: 0.63354847 | L30: 1.5815022
B31: 2045 | C31: 2.3811033 | D31: 3.8079941 | E31: -3.1475295 | F31: -1.0749065 | G31: -2.072623 | H31: 1.7206386 | I31: 0 | K31: 0.66046466 | L31: 1.7206386
B32: 2046 | C32: 2.5256019 | D32: 3.9085372 | E32: -3.2323987 | F32: -1.1134692 | G32: -2.1189295 | H32: 1.8494634 | I32: 0 | K32: 0.67613848 | L32: 1.8494634
B33: 2047 | C33: 2.6851045 | D33: 4.0177408 | E33: -3.2953226 | F33: -1.1270055 | G33: -2.1683171 | H33: 1.9626863 | I33: 0 | K33: 0.72241825 | L33: 1.9626863
B34: 2048 | C34: 2.7996628 | D34: 4.1284773 | E34: -3.3831136 | F34: -1.1624989 | G34: -2.2206148 | H34: 2.0542991 | I34: 0 | K34: 0.74536363 | L34: 2.0542991
B35: 2049 | C35: 2.8847352 | D35: 4.2464988 | E35: -3.4880247 | F35: -1.2130147 | G35: -2.27501 | H35: 2.1262611 | I35: 0 | K35: 0.75847415 | L35: 2.1262611
B36: 2050 | C36: 2.9469111 | D36: 4.3642818 | E36: -3.5938988 | F36: -1.2628185 | G36: -2.3310803 | H36: 2.176528 | I36: 0 | K36: 0.77038307 | L36: 2.176528

Sheet Gráfico 31.B.
A1: Índice de gráficos
B3: GRÁFICO 31. B. CONTRIBUCIONES A LA VARIACIÓN DE LA DEUDA (P.P), POR PERIODOS
C5: Var. Deuda | D5: Gasto intereses | E5: Crecimiento real | F5: Inflación | G5: Déficit primario | H5: Aj. stock flujo | J5: Diferencial interés-crecimiento | K5: Déficit primario y stock-flujo
B6: 2021-2030 | C6: -24.247407 | D6: 24.801238 | E6: -32.054779 | F6: -31.006049 | G6: 7.051753 | H6: 6.9604298 | J6: -38.25959 | K6: 14.012183
B7: 2031-2040 | C7: 3.3293167 | D7: 31.271576 | E7: -10.737506 | F7: -18.359474 | G7: 1.1547207 | H7: 0 | J7: 2.174596 | K7: 1.1547207
B8: 2041-2050 | C8: 24.108651 | D8: 38.796311 | E8: -10.868393 | F8: -21.078357 | G8: 17.259089 | H8: 0 | J8: 6.8495616 | K8: 17.259089
B9: 2051-2060 | C9: 28.025429 | D9: 49.905895 | E9: -16.34764 | F9: -26.412785 | G9: 20.879959 | H9: 0 | J9: 7.1454704 | K9: 20.879959
B10: 2061-2070 | C10: 27.531865 | D10: 60.218272 | E10: -15.772181 | F10: -31.711246 | G10: 14.797021 | H10: 0 | J10: 12.734844 | K10: 14.797021
B12: 2025-2035 | C12: -7.4998127 | D12: 28.218122 | E12: -15.42767 | F12: -20.107953 | G12: -3.024774 | H12: 2.8424618 | J12: -7.3175005 | K12: -0.18231223
B13: 2036-2050 | C13: 29.313191 | D13: 55.027063 | E13: -15.315358 | F13: -30.328882 | G13: 19.930368 | H13: 0 | J13: 9.3828231 | K13: 19.930368
N22: Fuente: | O22: AIReF

Sheet Gráfico 32
A1: Índice de gráficos
B3: GRÁFICO 32. SALDO PÚBLICO (%PIB)
C6: Saldo primario | D6: Saldo total
B7: 1995 | C7: -1.8526525 | D7: -6.793349
B8: 1996 | C8: -0.8346525 | D8: -5.8658829
B9: 1997 | C9: 0.67730181 | D9: -3.8591752
B10: 1998 | C10: 1.4390911 | D10: -2.6269037
B11: 1999 | C11: 2.1713858 | D11: -1.2401679
B12: 2000 | C12: 2.0021033 | D12: -1.1612662
B13: 2001 | C13: 2.5145586 | D13: -0.4549488
B14: 2002 | C14: 2.3149235 | D14: -0.31424059
B15: 2003 | C15: 1.9247947 | D15: -0.37486779
B16: 2004 | C16: 1.8792897 | D16: -0.1094111
B17: 2005 | C17: 2.9761174 | D17: 1.2305494
B18: 2006 | C18: 3.7304373 | D18: 2.1216427
... B21: 2009 | C21: -9.526743 | D21: -11.237383
B22: 2010 | C22: -7.5900645 | D22: -9.4873949 | G22: Fuente: | H22: AIReF
B23: 2011 | C23: -7.2062993 | D23: -9.6917722
B24: 2012 | C24: -8.4695028 | D24: -11.495959
B25: 2013 | C25: -3.924528 | D25: -7.4884074
B26: 2014 | C26: -2.5034915 | D26: -6.0364849
B27: 2015 | C27: -2.1966458 | D27: -5.2660627
B28: 2016 | C28: -1.4403807 | D28: -4.2210501
B29: 2017 | C29: -0.53759581 | D29: -3.0685695
B30: 2018 | C30: -0.11136078 | D30: -2.5524715
B31: 2019 | C31: -0.81286741 | D31: -3.0646641
B32: 2020 | C32: -7.6841059 | D32: -9.909282
B33: 2021 | C33: -4.5329971 | D33: -6.6512124
B34: 2022 | C34: -2.2771163 | D34: -4.5865758
... B62: 2050 | C62: -2.1465477 | D62: -6.5427269

Sheet Gráfico 33
A1: Índice de gráficos
B3: GRÁFICO 33. DIFERENCIAL INTERÉS-CRECIMIENTO, (PUNTOS PIB)
C5: Diferencial interés-crecimiento
B6: 1996 | C6: 1.4178842
B7: 1997 | C7: 0.75034129
B8: 1998 | C8: -0.16777177
B9: 1999 | C9: -0.74544508
B10: 2000 | C10: -1.7538864
B11: 2001 | C11: -1.4359594
B12: 2002 | C12: -0.88802581
B13: 2003 | C13: -1.0795402
B14: 2004 | C14: -1.1925767
B15: 2005 | C15: -1.5788649
B16: 2006 | C16: -1.6333126
B17: 2007 | C17: -1.0491647
... B21: 2011 | C21: 2.9622709
B22: 2012 | C22: 5.2228521 | F22: Fuente: | G22: AIReF
B23: 2013 | C23: 4.4643277
B24: 2014 | C24: 2.2529512
B25: 2015 | C25: -1.5580246
B26: 2016 | C26: -0.49156133
B27: 2017 | C27: -1.5721662
B28: 2018 | C28: -1.0863085
B29: 2019 | C29: -1.0462056
B30: 2020 | C30: 12.992122
B31: 2021 | C31: -8.1406795
B32: 2022 | C32: -9.495898
B33: 2023 | C33: -6.523666
B34: 2024 | C34: -3.9377243
... B80: 2070 | C80: 1.7052354

Sheet Gráfico 34 
A1: Índice de gráficos
B3: GRÁFICO 34. NECESIDADES BRUTAS DE FINANCIACIÓN (% PIB)
C6: Nec. Financiación | D6: Amortizaciones | E6: Amortizaciones c/p | F6: Amortizaciones l/p | G6: Saldo primario | H6: Intereses | I6: Ajuste stock-flujo
B7: 2025 | C7: 16.748241 | D7: 13.639934 | E7: 4.6375774 | F7: 9.0023561 | G7: 0.19758609 | H7: 2.4489458 | I7: 0.37067894
B8: =B7+1 -> 2026 | C8: 16.861322 | D8: 13.794115 | E8: 4.6899989 | F8: 9.1041156 | G8: 0.12118131 | H8: 2.5246176 | I8: 0.421409
B9: =B8+1 -> 2027 | C9: 17.420618 | D9: 14.498233 | E9: 4.9293994 | F9: 9.5688341 | G9: 0.06577533 | H9: 2.6317796 | I9: 0.22482967
B10: =B9+1 -> 2028 | C10: 17.106496 | D10: 14.158148 | E10: 4.8137703 | F10: 9.3443776 | G10: -0.026820163 | H10: 2.7631874 | I10: 0.2119807
B11: =B10+1 -> 2029 | C11: 18.409973 | D11: 15.38918 | E11: 5.2323211 | F11: 10.156859 | G11: -0.053630488 | H11: 2.8158778 | I11: 0.25854647
B12: =B11+1 -> 2030 | C12: 16.350576 | D12: 13.589803 | E12: 4.620533 | F12: 8.9692699 | G12: -0.17683032 | H12: 2.9229733 | I12: 0.014630607
B13: =B12+1 -> 2031 | C13: 16.350525 | D13: 13.492551 | E13: 4.5874673 | F13: 8.9050836 | G13: -0.18572341 | H13: 3.0276687 | I13: 0.016028797
B14: =B13+1 -> 2032 | C14: 17.297846 | D14: 14.333327 | E14: 4.873331 | F14: 9.4599955 | G14: -0.1781747 | H14: 3.1038454 | I14: 0.038848833
B15: =B14+1 -> 2033 | C15: 18.166894 | D15: 15.012744 | E15: 5.1043331 | F15: 9.9084113 | G15: -0.034859421 | H15: 3.1456198 | I15: 0.043389488
B16: =B15+1 -> 2034 | C16: 16.442425 | D16: 13.107093 | E16: 4.4564115 | F16: 8.6506812 | G16: 0.10692875 | H16: 3.1882694 | I16: 0.040134005
B17: =B16+1 -> 2035 | C17: 17.700156 | D17: 14.1758 | E17: 4.8197722 | F17: 9.3560283 | G17: 0.25455102 | H17: 3.2517006 | I17: 0.018103769
B18: =B17+1 -> 2036 | C18: 16.970237 | D18: 13.215569 | E18: 4.4932935 | F18: 8.7222756 | G18: 0.41037765 | H18: 3.3203688 | I18: 0.02392123
B19: =B18+1 -> 2037 | C19: 18.849802 | D19: 14.878304 | E19: 5.0586233 | F19: 9.8196805 | G19: 0.56621922 | H19: 3.3878137 | I19: 0.017465613
B20: =B19+1 -> 2038 | C20: 17.771406 | D20: 13.563277 | E20: 4.6115142 | F20: 8.9517629 | G20: 0.73274613 | H20: 3.4622779 | I20: 0.013105062 | K20: Fuente: | L20: AIReF
B21: =B20+1 -> 2039 | C21: 19.029892 | D21: 14.582454 | E21: 4.9580344 | F21: 9.6244197 | G21: 0.9056288 | H21: 3.5344863 | I21: 0.0073223682
B22: =B21+1 -> 2040 | C22: 20.720923 | D22: 16.028062 | E22: 5.449541 | F22: 10.578521 | G22: 1.0817035 | H22: 3.6134628 | I22: -0.0023052236
B23: =B22+1 -> 2041 | C23: 20.843659 | D23: 15.884103 | E23: 5.4005949 | F23: 10.483508 | G23: 1.2550824 | H23: 3.708315 | I23: -0.0038407129
B24: =B23+1 -> 2042 | C24: 20.976832 | D24: 15.767068 | E24: 5.3608031 | F24: 10.406265 | G24: 1.4246499 | H24: 3.800363 | I24: -0.015249109
B25: =B24+1 -> 2043 | C25: 21.935421 | D25: 16.462124 | E25: 5.5971222 | F25: 10.865002 | G25: 1.5923719 | H25: 3.8985179 | I25: -0.017592352
B26: =B25+1 -> 2044 | C26: 22.107466 | D26: 16.389448 | E26: 5.5724122 | F26: 10.817035 | G26: 1.7437555 | H26: 3.9993278 | I26: -0.02506478
B27: =B26+1 -> 2045 | C27: 22.07629 | D27: 16.124409 | E27: 5.4822989 | F27: 10.64211 | G27: 1.8779927 | H27: 4.1045855 | I27: -0.030696847
B28: =B27+1 -> 2046 | C28: 23.258962 | D28: 17.084647 | E28: 5.80878 | F28: 11.275867 | G28: 1.9979767 | H28: 4.2147482 | I28: -0.038410427
B29: =B28+1 -> 2047 | C29: 23.549975 | D29: 17.165454 | E29: 5.8362543 | F29: 11.329199 | G29: 2.0939739 | H29: 4.3320099 | I29: -0.041462915
B30: =B29+1 -> 2048 | C30: 24.338097 | D30: 17.768989 | E30: 6.0414561 | F30: 11.727532 | G30: 2.1690967 | H30: 4.4494096 | I30: -0.049397563
B31: =B30+1 -> 2049 | C31: 24.509662 | D31: 17.76619 | E31: 6.0405047 | F31: 11.725686 | G31: 2.221726 | H31: 4.5736369 | I31: -0.051891684
B32: =B31+1 -> 2050 | C32: 25.811651 | D32: 18.908633 | E32: 6.4289353 | F32: 12.479698 | G32: 2.2533455 | H32: 4.6960902 | I32: -0.046417748
... B52: =B51+1 -> 2070 | C52: 33.759816 | D52: 26.142711 | E52: 8.8885217 | F52: 17.254189 | G52: 0.91383118 | H52: 6.7505396 | I52: -0.047265308

Sheet Gráfico 35
A1: Índice de gráficos
B3: GRÁFICO 35. INTERVALO DE DEUDA (%PIB), ESCENARIOS DE EVOLUCIÓN DEL PIB
C5: Inercial | D5: +0.5 | E5: -0.5 | F5: +0.5 | G5: -0.5 | H5: +0.5 | I5: -0.5 | J5: +0.5 | K5: -0.5
B6: 2019 | C6: 97.659249 | D6: 97.659249 | E6: 97.659249 | F6: 0 | G6: 0 | H6: 0 | I6: 0 | J6: 0 | K6: 0
B7: =B6+1 -> 2020 | C7: 119.27911 | D7: 119.27911 | E7: 119.27911 | F7: 0 | G7: 0 | H7: 0 | I7: 0 | J7: 0 | K7: 0
B8: =B7+1 -> 2021 | C8: 115.69678 | D8: 115.69678 | E8: 115.69678 | F8: 0 | G8: 0 | H8: 0 | I8: 0 | J8: 0 | K8: 0
B9: =B8+1 -> 2022 | C9: 109.32085 | D9: 109.32085 | E9: 109.32085 | F9: 0 | G9: 0 | H9: 0 | I9: 0 | J9: 0 | K9: 0
B10: =B9+1 -> 2023 | C10: 105.18212 | D10: 105.18212 | E10: 105.18212 | F10: 0 | G10: 0 | H10: 0 | I10: 0 | J10: 0 | K10: 0
B11: =B10+1 -> 2024 | C11: 101.64604 | D11: 101.64604 | E11: 101.64604 | F11: 0 | G11: 0 | H11: 0 | I11: 0 | J11: 0 | K11: 0
B12: =B11+1 -> 2025 | C12: 100.65629 | D12: 100.65629 | E12: 100.65629 | F12: 0 | G12: 0 | H12: 0 | I12: 0 | J12: 0 | K12: 0
B13: =B12+1 -> 2026 | C13: 99.795458 | D13: 100.2854 | E13: 99.31029 | F13: 0.10012579 | G13: -0.10012579 | H13: 0.48993707 | I13: -0.48516814 | J13: 0.00099011387 | K13: -0.00099008085
B14: =B13+1 -> 2027 | C14: 98.170375 | D14: 99.142036 | E14: 97.212883 | F14: 0.29864233 | G14: -0.29864233 | H14: 0.97166093 | I14: -0.95749208 | J14: 0.018478039 | K14: -0.018472097
B15: =B14+1 -> 2028 | C15: 96.829779 | D15: 98.276025 | E15: 95.411618 | F15: 0.59549637 | G15: -0.59549637 | H15: 1.4462468 | I15: -1.418161 | J15: 0.062779994 | K15: -0.062687154
B16: =B15+1 -> 2029 | C16: 95.883798 | D16: 97.805309 | E16: 94.008881 | F16: 0.99188523 | G16: -0.99188523 | H16: 1.9215105 | I16: -1.8749172 | J16: 0.14213497 | K16: -0.14165969
B17: =B16+1 -> 2030 | C17: 95.094625 | D17: 97.49102 | E17: 92.767875 | F17: 1.4877669 | G17: -1.4877669 | H17: 2.3963946 | I17: -2.3267505 | J17: 0.26929781 | K17: -0.26774365
B18: =B17+1 -> 2031 | C18: 94.122068 | D18: 96.981128 | E18: 91.359809 | F18: 1.9823651 | G18: -1.9823651 | H18: 2.8590599 | I18: -2.7622589 | J18: 0.44806007 | K18: -0.44408475
... B22: =B21+1 -> 2035 | C22: 93.581086 | D22: 98.371701 | E22: 89.044164 | F22: 4.0104147 | G22: -4.0104147 | H22: 4.7906149 | I22: -4.536922 | J22: 1.524134 | K22: -1.4889078
B23: =B22+1 -> 2036 | C23: 94.27301 | D23: 99.574921 | E23: 89.276877 | F23: 4.5331702 | G23: -4.5331702 | H23: 5.3019109 | I23: -4.9961323 | J23: 1.8766602 | K23: -1.8263583 | N23: Fuente: | O23: AIReF
B24: =B23+1 -> 2037 | C24: 95.166814 | D24: 100.98997 | E24: 89.706729 | F24: 5.0599802 | G24: -5.0599802 | H24: 5.8231546 | I24: -5.4600847 | J24: 2.2526725 | K24: -2.1837815
B25: =B24+1 -> 2038 | C25: 96.240468 | D25: 102.59449 | E25: 90.312032 | F25: 5.5897176 | G25: -5.5897176 | H25: 6.3540235 | I25: -5.9284356 | J25: 2.6572731 | K25: -2.5660402
B26: =B25+1 -> 2039 | C26: 97.552165 | D26: 104.45077 | E26: 91.147232 | F26: 6.1251469 | G26: -6.1251469 | H26: 6.8986093 | I26: -6.4049325 | J26: 3.08033 | K26: -2.9626559
B27: =B26+1 -> 2040 | C27: 99.099388 | D27: 106.55719 | E27: 92.209068 | F27: 6.6661175 | G27: -6.6661175 | H27: 7.4577995 | I27: -6.8903199 | J27: 3.5257123 | K27: -3.3773036
B28: =B27+1 -> 2041 | C28: 100.86349 | D28: 108.8963 | E28: 93.477831 | F28: 7.2115017 | G28: -7.2115017 | H28: 8.0328193 | I28: -7.3856544 | J28: 3.9944991 | K28: -3.8108904
B29: =B28+1 -> 2042 | C29: 102.81703 | D29: 111.43905 | E29: 94.927687 | F29: 7.7602608 | G29: -7.7602608 | H29: 8.6220195 | I29: -7.8893471 | J29: 4.4874135 | K29: -4.2639277
B30: =B29+1 -> 2043 | C30: 104.89507 | D30: 114.11815 | E30: 96.495826 | F30: 8.3088421 | G30: -8.3088421 | H30: 9.2230791 | I30: -8.3992484 | J30: 4.9997268 | K30: -4.7315656
B31: =B30+1 -> 2044 | C31: 107.13771 | D31: 116.97865 | E31: 98.217923 | F31: 8.8611303 | G31: -8.8611303 | H31: 9.8409379 | I31: -8.9197909 | J31: 5.5334983 | K31: -5.2155418
B32: =B31+1 -> 2045 | C32: 109.53859 | D32: 120.01587 | E32: 100.08618 | F32: 9.4175807 | G32: -9.4175807 | H32: 10.477283 | I32: -9.4524088 | J32: 6.0891828 | K32: -5.7160763
B33: =B32+1 -> 2046 | C33: 112.07563 | D33: 123.2074 | E33: 102.07893 | F33: 9.9771912 | G33: -9.9771912 | H33: 11.131774 | I33: -9.9966977 | J33: 6.6631632 | K33: -6.2293798
B34: =B33+1 -> 2047 | C34: 114.76356 | D34: 126.57261 | E34: 104.20686 | F34: 10.542346 | G34: -10.542346 | H34: 11.80905 | I34: -10.556693 | J34: 7.2617658 | K34: -6.7614748
B35: =B34+1 -> 2048 | C35: 117.55688 | D35: 130.06387 | E35: 106.42653 | F35: 11.111258 | G35: -11.111258 | H35: 12.506981 | I35: -11.130354 | J35: 7.8807388 | K35: -7.3079397
... B37: =B36+1 -> 2050 | C37: 123.34752 | D37: 137.31268 | E37: 111.02907 | F37: 12.256506 | G37: -12.256506 | H37: 13.96516 | I37: -12.318454 | J37: 9.1869731 | K37: -8.4505228
F38: 135.60403 | G38: 111.09102 | H38: 137.31268 | I38: 111.02907 | J38: 132.5345 | K38: 114.897
G39: 24.513012 | I39: 26.283613 | K39: 17.637496

Sheet Gráfico 36
A1: Índice de gráficos
B3: GRÁFICO 36. CONTRIBUCIONES A LA VARIACIÓN DEL SALDO PRIMARIO DE LOS COMPONENTES DEL ENVEJECIMIENTO (PUNTOS DE PIB)
C6: Envejecimiento | D6: Educación | E6: Sanidad | F6: Cuidados LD | G6: Pensiones
B7: 2025 | C7: 0 | D7: 0 | E7: 0 | F7: 0 | G7: 0
B8: 2026 | C8: 0 | D8: 0 | E8: 0 | F8: 0 | G8: 0
B9: 2027 | C9: -0.17221669 | D9: -0.059374966 | E9: -0.069388978 | F9: -0.0097523525 | G9: -0.033700397
B10: 2028 | C10: -0.26712122 | D10: -0.046338602 | E10: -0.075660969 | F10: -0.022446422 | G10: -0.12267522
B11: 2029 | C11: -0.35659646 | D11: -0.038158405 | E11: -0.10379147 | F11: -0.037865862 | G11: -0.17678072
B12: 2030 | C12: -0.4843313 | D12: -0.0094454162 | E12: -0.13819229 | F12: -0.049246872 | G12: -0.28744672
B13: 2031 | C13: -0.4285401 | D13: 0.015521618 | E13: -0.17709445 | F13: -0.071565171 | G13: -0.1954021
B14: 2032 | C14: -0.42806383 | D14: 0.052367844 | E14: -0.24061569 | F14: -0.092625428 | G14: -0.14719056
B15: 2033 | C15: -0.6011085 | D15: 0.099598103 | E15: -0.31504005 | F15: -0.11632731 | G15: -0.26933925
B16: 2034 | C16: -0.8345493 | D16: 0.1498541 | E16: -0.40701871 | F16: -0.14465217 | G16: -0.43273252
B17: 2035 | C17: -1.0878333 | D17: 0.19870014 | E17: -0.49631057 | F17: -0.17011305 | G17: -0.6201098
B18: 2036 | C18: -1.3421397 | D18: 0.24768373 | E18: -0.57625981 | F18: -0.19916927 | G18: -0.81439433
... B24: 2042 | C24: -2.9254049 | D24: 0.45339423 | E24: -0.99240142 | F24: -0.3774701 | G24: -2.0089276
B25: 2043 | C25: -3.1705902 | D25: 0.46552122 | E25: -1.0553869 | F25: -0.40893339 | G25: -2.1717911 | I25: Fuente: | J25: AIReF
B26: 2044 | C26: -3.4043166 | D26: 0.47255667 | E26: -1.1182924 | F26: -0.44212711 | G26: -2.3164537
B27: 2045 | C27: -3.621784 | D27: 0.4743834 | E27: -1.1795794 | F27: -0.47478776 | G27: -2.4418003
B28: 2046 | C28: -3.8239 | D28: 0.47087924 | E28: -1.2391348 | F28: -0.50685979 | G28: -2.5487847
B29: 2047 | C29: -4.008121 | D29: 0.46289319 | E29: -1.2963457 | F29: -0.53948455 | G29: -2.635184
B30: 2048 | C30: -4.1674656 | D30: 0.45256967 | E30: -1.3493912 | F30: -0.5748023 | G30: -2.6958417
B31: 2049 | C31: -4.2991861 | D31: 0.44030806 | E31: -1.3974485 | F31: -0.60953573 | G31: -2.73251
B32: 2050 | C32: -4.4034706 | D32: 0.42731546 | E32: -1.4401131 | F32: -0.64494919 | G32: -2.7457238

Sheet Gráfico 37
A1: Índice de gráficos
C4: Envejecimiento | D4: Educación | E4: Sanidad | F4: Cuidados LD | G4: Pensiones
B5: 2025 | C5: 0 | D5: 0 | E5: 0 | F5: 0 | G5: 0
B6: 2026 | C6: 0 | D6: 0 | E6: 0 | F6: 0 | G6: 0
B7: 2027 | C7: 0.17245063 | D7: 0.059455621 | E7: 0.069483235 | F7: 0.0097656 | G7: 0.033746176 | I7: Gráfico 37 | J7: CONTRIBUCIONES A LA VARIACIÓN DE LA DEUDA DE LOS COMPONENTES DEL ENVEJECIMIENTO
B8: 2028 | C8: 0.43788448 | D8: 0.10514058 | E8: 0.14441411 | F8: 0.032127969 | G8: 0.15620182
B9: 2029 | C9: 0.79198805 | D9: 0.14261235 | E9: 0.24735626 | F9: 0.069832313 | G9: 0.33218713
B10: 2030 | C10: 1.2732702 | D10: 0.15132384 | E10: 0.38455597 | F10: 0.11883049 | G10: 0.61855988
B11: 2031 | C11: 1.6973346 | D11: 0.13505624 | E11: 0.56038103 | F11: 0.19005414 | G11: 0.81184321
B12: 2032 | C12: 2.1232464 | D12: 0.082192703 | E12: 0.80054187 | F12: 0.28258124 | G12: 0.95793058
B13: 2033 | C13: 2.7259255 | D13: -0.017829078 | E13: 1.1165272 | F13: 0.39928711 | G13: 1.2279403
B14: 2034 | C14: 3.5714162 | D14: -0.16837509 | E14: 1.528398 | F14: 0.5456974 | G14: 1.6656959
B15: 2035 | C15: 4.6803591 | D15: -0.36879706 | E15: 2.034056 | F15: 0.71915125 | G15: 2.2959489
B16: 2036 | C16: 6.0522243 | D16: -0.61963156 | E16: 2.6234301 | F16: 0.92295575 | G16: 3.12547
B17: 2037 | C17: 7.6791891 | D17: -0.92200626 | E17: 3.2888806 | F17: 1.1538092 | G17: 4.1585055
B18: 2038 | C18: 9.5671033 | D18: -1.2719353 | E18: 4.026002 | F18: 1.4150496 | G18: 5.3979871
B19: 2039 | C19: 11.741402 | D19: -1.6630932 | E19: 4.8388752 | F19: 1.7119175 | G19: 6.8537027
... B23: 2043 | C23: 23.330517 | D23: -3.4982733 | E23: 8.8432629 | F23: 3.2285393 | G23: 14.756988
B24: 2044 | C24: 26.891951 | D24: -3.9944942 | E24: 10.020417 | F24: 3.6922798 | G24: 17.173749 | I24: Fuente: | J24: AIReF
B25: 2045 | C25: 30.69574 | D25: -4.4958981 | E25: 11.267119 | F25: 4.1919488 | G25: 19.73257
B26: 2046 | C26: 34.724978 | D26: -4.996723 | E26: 12.580932 | F26: 4.7267621 | G26: 22.414007
B27: 2047 | C27: 38.971229 | D27: -5.4936483 | E27: 13.962883 | F27: 5.2986023 | G27: 25.203391
B28: 2048 | C28: 43.40506 | D28: -5.9834464 | E28: 15.407087 | F28: 5.9096083 | G28: 28.071811
B29: 2049 | C29: 47.99479 | D29: -6.463413 | E29: 16.907096 | F29: 6.5587455 | G29: 30.992362
B30: 2050 | C30: 52.713883 | D30: -6.9327793 | E30: 18.457878 | F30: 7.2469332 | G30: 33.941852

Sheet Anexo I. Gr 1A
A1: Índice de gráficos
B2: ANEXO I. GRÁFICO 1. TENDENCIAS RECIENTES EN LA FECUNDIDAD DE MADRES ESPAÑOLAS Y EXTRANJERAS
B3: ANEXO I. GRÁFICO 1A. NÚMERO DE HIJOS POR MUJER. SEGÚN NACIONALIDAD DE LA MADRE
B18: Fuente: | C18: INE
B19: Número de hijos por mujer
C20: Española | D20: Extranjera | E20: Ambas nacionalidades
B21: 2002 | C21: 1.21 | D21: 1.86 | E21: 1.25
B22: 2003 | C22: 1.25 | D22: 1.77 | E22: 1.3
B23: 2004 | C23: 1.27 | D23: 1.75 | E23: 1.32
B24: 2005 | C24: 1.28 | D24: 1.66 | E24: 1.33
B25: 2006 | C25: 1.31 | D25: 1.69 | E25: 1.36
B26: 2007 | C26: 1.31 | D26: 1.72 | E26: 1.38
B27: 2008 | C27: 1.36 | D27: 1.83 | E27: 1.44
B28: 2009 | C28: 1.31 | D28: 1.68 | E28: 1.38
B29: 2010 | C29: 1.3 | D29: 1.68 | E29: 1.37
B30: 2011 | C30: 1.29 | D30: 1.58 | E30: 1.34
B31: 2012 | C31: 1.27 | D31: 1.56 | E31: 1.32
B32: 2013 | C32: 1.23 | D32: 1.52 | E32: 1.27
... B43: 2024 | C43: 1.07 | D43: 1.27 | E43: 1.1

Sheet Anexo I. Gr 1B
A1: Índice de gráficos
B2: ANEXO I. GRÁFICO 1. TENDENCIAS RECIENTES EN LA FECUNDIDAD DE MADRES ESPAÑOLAS Y EXTRANJERAS
B3: ANEXO I. GRÁFICO 1B. DIFERENCIAL EN EL NÚMERO DE HIJOS POR MUJER ENTRE MADRES DE NACIONALIDAD EXTRANJERA Y ESPAÑOLA
B18: Fuente: | C18: INE
B19: Diferencial en el número de hijos por mujer
C20: Diferencial | D20: Mínimo
B21: 2002 | C21: 0.65 | D21: 0.19
B22: 2003 | C22: 0.52 | D22: 0.19
B23: 2004 | C23: 0.48 | D23: 0.19
B24: 2005 | C24: 0.38 | D24: 0.19
B25: 2006 | C25: 0.38 | D25: 0.19
B26: 2007 | C26: 0.41 | D26: 0.19
B27: 2008 | C27: 0.47 | D27: 0.19
B28: 2009 | C28: 0.37 | D28: 0.19
B29: 2010 | C29: 0.38 | D29: 0.19
B30: 2011 | C30: 0.29 | D30: 0.19
B31: 2012 | C31: 0.29 | D31: 0.19
B32: 2013 | C32: 0.29 | D32: 0.19
... B43: 2024 | C43: 0.2 | D43: 0.19

Sheet Anexo I. Gr 2A
A1: Índice de gráficos
B2: ANEXO I. GRÁFICO 2. ÍNDICE COYUNTURAL DE FECUNDIDAD EN EL ENTORNO INTERNACIONAL
B3: ANEXO I. GRÁFICO 2A. EVOLUCIÓN DEL NÚMERO DE HIJOS POR MUJER. ESPAÑA EN EL CONTEXTO MUNDIAL Y DE PAÍSES EMISORES
B18: Fuente: | C18: ONU e INE para España a partir de 1975
B19: Número de hijos por mujer
D20: Mundial | F20: Países emisores
C21: España | D21: Máximo | E21: Mínimo | F21: Máximo | G21: Mínimo
B22: 1950 | C22: 2.469118 | D22: 8.111024 | E22: 0.990647 | F22: 7.42222 | G22: 2.686794
B23: =+B22+1 -> 1951 | C23: 2.456483 | D23: 8.114649 | E23: 0.989839 | F23: 7.444508 | G23: 2.695786
B24: =+B23+1 -> 1952 | C24: 2.538107 | D24: 8.135796 | E24: 0.989149 | F24: 7.495599 | G24: 2.71435
B25: =+B24+1 -> 1953 | C25: 2.499262 | D25: 8.155979 | E25: 0.988508 | F25: 7.535505 | G25: 2.734095
B26: =+B25+1 -> 1954 | C26: 2.437395 | D26: 8.174661 | E26: 0.987544 | F26: 7.564822 | G26: 2.754953
B27: =+B26+1 -> 1955 | C27: 2.506372 | D27: 8.1719 | E27: 0.987211 | F27: 7.581888 | G27: 2.751664
B28: =+B27+1 -> 1956 | C28: 2.539436 | D28: 8.190222 | E28: 0.986902 | F28: 7.588395 | G28: 2.786247
B29: =+B28+1 -> 1957 | C29: 2.687474 | D29: 8.217448 | E29: 0.986692 | F29: 7.582134 | G29: 2.796626
B30: =+B29+1 -> 1958 | C30: 2.727427 | D30: 8.233275 | E30: 0.986447 | F30: 7.562365 | G30: 2.809843
B31: =+B30+1 -> 1959 | C31: 2.753066 | D31: 8.25341 | E31: 0.986147 | F31: 7.528826 | G31: 2.810834
B32: =+B31+1 -> 1960 | C32: 2.80662 | D32: 8.250273 | E32: 0.985876 | F32: 7.484525 | G32: 2.821619
B33: =+B32+1 -> 1961 | C33: 2.776659 | D33: 8.248659 | E33: 0.985712 | F33: 7.54535 | G33: 2.839899
B34: =+B33+1 -> 1962 | C34: 2.802751 | D34: 8.2423 | E34: 0.985554 | F34: 7.588497 | G34: 2.859643
... B95: =+B94+1 -> 2023 | C95: 1.212696 | D95: 6.10421 | E95: 0.661504 | F95: 2.765094 | G95: 1.166721

Sheet Anexo I. Gr 2B
A1: Índice de gráficos
B2: ANEXO I. GRÁFICO 2. ENTORNO INTERNACIONAL
B3: ANEXO I. GRÁFICO 2B. EVOLUCIÓN DEL NÚMERO DE HIJOS POR MUJER. ESPAÑA EN EL CONTEXTO EUROPEO
B18: Fuente: | C18: Eurostat
B19: Número de hijos por mujer
C20: España | D20: Máximo UE | E20: Mínimo UE
B21: 1950 | C21: 2.469118 | D21: 4.225773 | E21: 1.95945
B22: 1951 | C22: 2.456483 | D22: 4.20965 | E22: 1.98802
B23: 1952 | C23: 2.538107 | D23: 4.173269 | E23: 1.941458
B24: 1953 | C24: 2.499262 | D24: 4.128584 | E24: 1.845813
B25: 1954 | C25: 2.437395 | D25: 4.075607 | E25: 1.919467
B26: 1955 | C26: 2.506372 | D26: 4.034717 | E26: 1.880733
B27: 1956 | C27: 2.539436 | D27: 4.110364 | E27: 1.836111
B28: 1957 | C28: 2.687474 | D28: 4.171941 | E28: 1.866993
B29: 1958 | C29: 2.727427 | D29: 4.070917 | E29: 1.91625
B30: 1959 | C30: 2.753066 | D30: 4.212141 | E30: 1.921284
B31: 1960 | C31: 2.80662 | D31: 4.258389 | E31: 1.940566
B32: 1961 | C32: 2.776659 | D32: 3.912293 | E32: 1.935205
... B95: 2024 | C95: 1.1 | D95: 1.72 | E95: 1.01

Sheet Anexo I. Gr 3A
A1: Índice de gráficos
B2: ANEXO I. GRÁFICO 3. DESCOMPOSICIÓN DEL ÍNDICE COYUNTURAL DE FECUNDIDAD
B3: ANEXO I. GRÁFICO 3A. PROPORCIÓN DE MUJERES QUE TIENEN HIJOS
B18: Fuente: | C18: INE y AIReF
B19: Proporción de entrada a la maternidad
C20: Española | D20: Extranjera | E20: Ambas nacionalidades
B21: 2010 | C21: 0.71519819 | D21: 0.88929972 | E21: 0.74106042
B22: 2011 | C22: 0.7119903 | D22: 0.8310956 | E22: 0.7265866
B23: 2012 | C23: 0.70259524 | D23: 0.80556263 | E23: 0.71273237
B24: 2013 | C24: 0.6873884 | D24: 0.79010354 | E24: 0.6963048
B25: 2014 | C25: 0.70379982 | D25: 0.81402115 | E25: 0.71206912
B26: 2015 | C26: 0.69869186 | D26: 0.82506163 | E26: 0.70826619
B27: 2016 | C27: 0.68534342 | D27: 0.82815521 | E27: 0.69656904
B28: 2017 | C28: 0.66041471 | D28: 0.80941509 | E28: 0.6726986
B29: 2018 | C29: 0.62393262 | D29: 0.76987569 | E29: 0.63773325
B30: 2019 | C30: 0.61369897 | D30: 0.74653773 | E30: 0.62687536
B31: 2020 | C31: 0.60423043 | D31: 0.72029981 | E31: 0.61521834
B32: 2021 | C32: 0.61038002 | D32: 0.624625 | E32: 0.60288054
... B35: 2024 | C35: 0.57047236 | D35: 0.61179214 | E35: 0.56697069

Sheet Anexo I. Gr 3B
A1: Índice de gráficos
B2: ANEXO I. GRÁFICO 3. DESCOMPOSICIÓN DEL ÍNDICE COYUNTURAL DE FECUNDIDAD
B3: ANEXO I. GRÁFICO 3B. NÚMERO DE HIJOS POR MUJER DE AQUELLAS QUE ACCEDEN A LA MATERNIDAD
B18: Fuente: | C18: INE y AIReF
B19: Proporción de entrada a la maternidad
C20: Española | D20: Extranjera | E20: Ambas nacionalidades
B21: 2010 | C21: 1.820168 | D21: 1.8798151 | E21: 1.8460871
B22: 2011 | C22: 1.8166009 | D22: 1.8934266 | E22: 1.8461412
B23: 2012 | C23: 1.814388 | D23: 1.928769 | E23: 1.8519435
B24: 2013 | C24: 1.7896344 | D24: 1.917505 | E24: 1.8270373
B25: 2014 | C25: 1.8100854 | D25: 1.9524516 | E25: 1.8491801
B26: 2015 | C26: 1.8362383 | D26: 1.9871441 | E26: 1.8769382
B27: 2016 | C27: 1.8669659 | D27: 2.0336887 | E27: 1.9126629
B28: 2017 | C28: 1.8892801 | D28: 2.0648929 | E28: 1.9386746
B29: 2018 | C29: 1.915115 | D29: 2.0987901 | E29: 1.9684296
B30: 2019 | C30: 1.8979578 | D30: 2.1028887 | E30: 1.9586752
B31: 2020 | C31: 1.8646028 | D31: 2.0271227 | E31: 1.9164366
B32: 2021 | C32: 1.8904845 | D32: 2.15383 | E32: 1.9567758
... B35: 2024 | C35: 1.8755312 | D35: 2.0734238 | E35: 1.9430681

Sheet Anexo I. Gr 4A
A1: Índice de gráficos
B2: ANEXO I. GRÁFICO 4. ÍNDICE DE FECUNDIDAD POR COHORTE (CCF) EN EL ENTORNO INTERNACIONAL
B3: ANEXO I. GRÁFICO 4A. EVOLUCIÓN DEL NÚMERO DE HIJOS DE CADA GENERACIÓN DE MUJERES. ESPAÑA EN EL CONTEXTO MUNDIAL Y DE PAÍSES EMISORES
B18: Fuente: | C18: ONU INE para España a partir de las generaciones nacidas en 1960
B19: Número de hijos por mujer
D20: Mundial | F20: Países emisores
C21: España | D21: Máximo | E21: Mínimo | F21: Máximo | G21: Mínimo
B22: =1935+30 -> 1965 | C22: 2.6842136 | D22: 8.4755674 | E22: 1.7250026 | F22: 7.6168093 | G22: 2.768171
B23: =B22+1 -> 1966 | C23: 2.6715722 | D23: 8.4932592 | E23: 1.6975381 | F23: 7.624824 | G23: 2.7786657
B24: =B23+1 -> 1967 | C24: 2.6557592 | D24: 8.5015721 | E24: 1.6843548 | F24: 7.6295078 | G24: 2.7877136
B25: =B24+1 -> 1968 | C25: 2.6365638 | D25: 8.5054263 | E25: 1.6797804 | F25: 7.6276561 | G25: 2.7940822
B26: =B25+1 -> 1969 | C26: 2.6082536 | D26: 8.5064173 | E26: 1.7096299 | F26: 7.6200884 | G26: 2.7983602
B27: =B26+1 -> 1970 | C27: 2.5748504 | D27: 8.503666 | E27: 1.7653545 | F27: 7.6043327 | G27: 2.7999332
B28: =B27+1 -> 1971 | C28: 2.5263902 | D28: 8.4946794 | E28: 1.7690651 | F28: 7.5751449 | G28: 2.7985294
B29: =B28+1 -> 1972 | C29: 2.4978853 | D29: 8.4769867 | E29: 1.7163323 | F29: 7.526771 | G29: 2.7947663
B30: =B29+1 -> 1973 | C30: 2.4780779 | D30: 8.4497929 | E30: 1.7373063 | F30: 7.4568004 | G30: 2.7903212
B31: =B30+1 -> 1974 | C31: 2.4440917 | D31: 8.4143612 | E31: 1.7583822 | F31: 7.3645159 | G31: 2.7861175
B32: =B31+1 -> 1975 | C32: 2.4190484 | D32: 8.3731053 | E32: 1.6824432 | F32: 7.2525567 | G32: 2.7825026
B33: =B32+1 -> 1976 | C33: 2.3711459 | D33: 8.3262334 | E33: 1.6814005 | F33: 7.1282063 | G33: 2.7789694
B34: =B33+1 -> 1977 | C34: 2.3086451 | D34: 8.2741493 | E34: 1.6301649 | F34: 7.0005095 | G34: 2.7741317
... B61: =B60+1 -> 2004 | C61: 1.3817009 | D61: 7.6554511 | E61: 1.0751815 | F61: 4.1413124 | G61: 1.6903081

Sheet Anexo I. Gr 4B
A1: Índice de gráficos
B2: ANEXO I. GRÁFICO 4. ÍNDICE DE FECUNDIDAD POR COHORTE (CCF) EN EL ENTORNO INTERNACIONAL
B3: ANEXO I. GRÁFICO 4B. EVOLUCIÓN DEL NÚMERO DE HIJOS DE CADA GENERACIÓN DE MUJERES. ESPAÑA EN EL CONTEXTO EUROPEO
B18: Fuente: | C18: Eurostat
AN19: Rango UE CCF
B20: Número de hijos por mujer
C21: España | D21: Máximo UE | E21: Mínimo UE
B22: =1946+30 -> 1976 | C22: #N/A | D22: 2.4029 | E22: 1.81995
B23: =B22+1 -> 1977 | C23: #N/A | D23: 2.37907 | E23: 1.86945
B24: =B23+1 -> 1978 | C24: #N/A | D24: 2.36975 | E24: 1.80267
B25: =B24+1 -> 1979 | C25: #N/A | D25: 2.30889 | E25: 1.83821
B26: =B25+1 -> 1980 | C26: #N/A | D26: 2.34767 | E26: 1.84263
B27: =B26+1 -> 1981 | C27: #N/A | D27: 2.29778 | E27: 1.81895
B28: =B27+1 -> 1982 | C28: #N/A | D28: 2.27647 | E28: 1.81363
B29: =B28+1 -> 1983 | C29: #N/A | D29: 2.25849 | E29: 1.67881
B30: =B29+1 -> 1984 | C30: #N/A | D30: 2.21462 | E30: 1.68528
B31: =B30+1 -> 1985 | C31: #N/A | D31: 2.23123 | E31: 1.67424
B32: =B31+1 -> 1986 | C32: #N/A | D32: 2.20784 | E32: 1.70486
B33: =B32+1 -> 1987 | C33: 1.87082 | D33: 2.21594 | E33: 1.71784
B34: =B33+1 -> 1988 | C34: 1.85022 | D34: 2.20544 | E34: 1.67594
B35: =B34+1 -> 1989 | C35: 1.80698 | D35: 2.1645 | E35: 1.69676
B36: =B35+1 -> 1990 | C36: 1.777 | D36: 2.17306 | E36: 1.69304
B37: =B36+1 -> 1991 | C37: 1.71769 | D37: 2.18284 | E37: 1.64474
B38: =B37+1 -> 1992 | C38: 1.70042 | D38: 2.16636 | E38: 1.61777
B39: =B38+1 -> 1993 | C39: 1.66542 | D39: 2.10978 | E39: 1.5947
B40: =B39+1 -> 1994 | C40: 1.65038 | D40: 2.10087 | E40: 1.56965
B41: =B40+1 -> 1995 | C41: 1.61369 | D41: 2.05451 | E41: 1.55011
B42: =B41+1 -> 1996 | C42: 1.58558 | D42: 2.02858 | E42: 1.51966
B43: =B42+1 -> 1997 | C43: 1.56556 | D43: 2.02434 | E43: 1.50857
B44: =B43+1 -> 1998 | C44: 1.55726 | D44: 1.99347 | E44: 1.51225
... B50: =B49+1 -> 2004 | C50: 1.38834 | D50: 1.95899 | E50: 1.38834

Sheet Anexo I. Gr 5
A1: Índice de gráficos
B3: ANEXO I. GRÁFICO 5. EVOLUCIÓN ED LAS PROYECCIONES DEL NÚMERO DE HIJOS POR MUJER DE LA AIREF
B19: Fuente: | C19: INE y AIReF
B20: Número de hijos por mujer
C21: Observado | D21: AIReF 2025 | E21: AIReF 2023 | F21: AIReF 2020 | G21: AIReF 2018
B22: 2004 | C22: 1.32
B23: 2005 | C23: 1.33
B24: 2006 | C24: 1.36
B25: 2007 | C25: 1.38
B26: 2008 | C26: 1.44
B27: 2009 | C27: 1.38
B28: 2010 | C28: 1.37
B29: 2011 | C29: 1.34
B30: 2012 | C30: 1.32
B31: 2013 | C31: 1.27
B32: 2014 | C32: 1.32
B33: 2015 | C33: 1.33
B34: 2016 | C34: 1.33
B35: 2017 | C35: 1.31 | G35: 1.31
B36: 2018 | C36: 1.26 | G36: 1.4010493
B37: 2019 | C37: 1.23 | F37: 1.23 | G37: 1.4203964
B38: 2020 | C38: 1.18 | F38: 1.2330142 | G38: 1.4426631
B39: 2021 | C39: 1.18 | E39: 1.18 | F39: 1.228445 | G39: 1.4647831
B40: 2022 | C40: 1.16 | E40: 1.1903159 | F40: 1.2263316 | G40: 1.490189
B41: 2023 | C41: 1.12 | D41: 1.12 | E41: 1.197795 | F41: 1.221625 | G41: 1.5168607
B42: 2024 | C42: 1.1008797 | D42: 1.1189156 | E42: 1.2080819 | F42: 1.2203832 | G42: 1.5436873
B43: 2025 | C43: 1.105 | D43: 1.1276932 | E43: 1.2106042 | F43: 1.2226198 | G43: 1.5744187
B44: 2026 | D44: 1.1400335 | E44: 1.2139333 | F44: 1.2241548 | G44: 1.5917013
B45: 2027 | D45: 1.1497046 | E45: 1.2186676 | F45: 1.2315971 | G45: 1.6062029
B46: 2028 | D46: 1.1589152 | E46: 1.2212971 | F46: 1.2391705 | G46: 1.6224447
B47: 2029 | D47: 1.1689641 | E47: 1.231971 | F47: 1.2485652 | G47: 1.6374226
B48: 2030 | D48: 1.1747067 | E48: 1.2429833 | F48: 1.253719 | G48: 1.6500085
B49: 2031 | D49: 1.180894 | E49: 1.2564334 | F49: 1.2589682 | G49: 1.6632398
B50: 2032 | D50: 1.1897786 | E50: 1.2592052 | F50: 1.2649158 | G50: 1.67321
B51: 2033 | D51: 1.1978938 | E51: 1.2664147 | F51: 1.2710708 | G51: 1.6858698
B52: 2034 | D52: 1.2029178 | E52: 1.2735324 | F52: 1.2778007 | G52: 1.6990484
B53: 2035 | D53: 1.2078317 | E53: 1.2813458 | F53: 1.2854856 | G53: 1.7077474
B54: 2036 | D54: 1.2152601 | E54: 1.2888003 | F54: 1.2933566 | G54: 1.7185246
B55: 2037 | D55: 1.2209727 | E55: 1.2951041 | F55: 1.3046959 | G55: 1.7290467
... B58: 2040 | D58: 1.2432503 | E58: 1.3208659 | F58: 1.334046 | G58: 1.7613114

Sheet Anexo I. Gr 6A
A1: Índice de gráficos
B2: ANEXO I. GRÁFICO 6. PROYECCIONES DEL NÚMERO DE HIJOS POR MUJER. SEGÚN NACIONALIDAD
B3: ANEXO I. GRÁFICO 6A. NÚMERO DE HIJOS POR MUJER. MADRES DE NACIONALIDAD ESPAÑOLA
B18: Fuente: | C18: INE y AIReF
B19: Madres de nacionalidad española
C20: Histórico | D20: AIReF 2026 | E20: Bandas
B21: 2002 | C21: 1.20843
B22: 2003 | C22: 1.25163
B23: 2004 | C23: 1.26642
B24: 2005 | C24: 1.28281
B25: 2006 | C25: 1.31147
B26: 2007 | C26: 1.30722
B27: 2008 | C27: 1.3596
B28: 2009 | C28: 1.30985
B29: 2010 | C29: 1.30215
B30: 2011 | C30: 1.29411
B31: 2012 | C31: 1.27438
B32: 2013 | C32: 1.231
... B42: 2023 | C42: 1.08955
B43: 2024 | C43: 1.07088 | D43: 1.07088 | E43: 1.07088 | F43: 1.07088
B44: 2025 | D44: 1.0678129 | E44: 1.0920033 | F44: 1.0439972
B45: 2026 | D45: 1.0589504 | E45: 1.0849467 | F45: 1.0332232
B46: 2027 | D46: 1.0498235 | E46: 1.0759412 | F46: 1.0228627
B47: 2028 | D47: 1.0364208 | E47: 1.062627 | F47: 1.0133658
B48: 2029 | D48: 1.0254125 | E48: 1.0518025 | F48: 0.99987702
B49: 2030 | D49: 1.0159733 | E49: 1.0413817 | F49: 0.99170408
B50: 2031 | D50: 1.0074323 | E50: 1.031786 | F50: 0.98139142
B51: 2032 | D51: 1.0009994 | E51: 1.0245537 | F51: 0.97263229
B52: 2033 | D52: 0.98901688 | E52: 1.0149572 | F52: 0.96497372
B53: 2034 | D53: 0.98459326 | E53: 1.0094415 | F53: 0.95847113
B54: 2035 | D54: 0.97748528 | E54: 1.0023943 | F54: 0.95253658
B55: 2036 | D55: 0.96946252 | E55: 0.99663809 | F55: 0.94390084
... B69: 2050 | D69: 0.9286196 | E69: 0.95528643 | F69: 0.90390528

Sheet Anexo I. Gr 6B
A1: Índice de gráficos
B2: ANEXO I. GRÁFICO 6. PROYECCIONES DEL NÚMERO DE HIJOS POR MUJER. SEGÚN NACIONALIDAD
B3: ANEXO I. GRÁFICO 6B. NÚMERO DE HIJOS POR MUJER. MADRES DE NACIONALIDAD EXTRANJERA
B18: Fuente: | C18: INE y AIReF
B19: Madres de nacionaldiad extranjera
C20: Histórico | D20: AIReF 2026 | E20: Bandas
B21: 2002 | C21: 1.85808
B22: 2003 | C22: 1.76916
B23: 2004 | C23: 1.75304
B24: 2005 | C24: 1.66305
B25: 2006 | C25: 1.68814
B26: 2007 | C26: 1.72028
B27: 2008 | C27: 1.82606
B28: 2009 | C28: 1.68358
B29: 2010 | C29: 1.67769
B30: 2011 | C30: 1.5798
B31: 2012 | C31: 1.56165
B32: 2013 | C32: 1.52445
... B42: 2023 | C42: 1.28182
B43: 2024 | C43: 1.27034 | D43: 1.27034 | E43: 1.27034 | F43: 1.27034
B44: 2025 | D44: 1.2811014 | E44: 1.3342374 | F44: 1.2296858
B45: 2026 | D45: 1.3042199 | E45: 1.3733518 | F45: 1.2413351
B46: 2027 | D46: 1.3273522 | E46: 1.403597 | F46: 1.2494794
B47: 2028 | D47: 1.3483378 | E47: 1.4292349 | F47: 1.267935
B48: 2029 | D48: 1.3677347 | E48: 1.4481184 | F48: 1.281138
B49: 2030 | D49: 1.3748777 | E49: 1.4593561 | F49: 1.290682
B50: 2031 | D50: 1.3824844 | E50: 1.4616614 | F50: 1.2935803
B51: 2032 | D51: 1.3763625 | E51: 1.463157 | F51: 1.2955729
B52: 2033 | D52: 1.3739899 | E52: 1.453844 | F52: 1.2890827
B53: 2034 | D53: 1.3681619 | E53: 1.4518511 | F53: 1.2896779
B54: 2035 | D54: 1.3597925 | E54: 1.4460058 | F54: 1.2774362
B55: 2036 | D55: 1.3553981 | E55: 1.4388238 | F55: 1.2673969
... B69: 2050 | D69: 1.2722918 | E69: 1.3556033 | F69: 1.1837724

Sheet Anexo I. Gr 7A
A1: Índice de gráficos
B2: ANEXO I. GRÁFICO 7. PROYECCIONES DEL NÚMERO DE HIJOS POR MUJER Y DEL DIFERENCIAL ENTRE MADRES DE NACIONALIDAD EXTRANJERA Y ESPAÑOLA
B3: ANEXO I. GRÁFICO 7A. NÚMERO DE HIJOS POR MUJER
B18: Fuente: | C18: INE, Eurostat y AIReF
B19: Madres de nacionalidad española
C20: Histórico | D20: AIReF 2026 | E20: Bandas | G20: EUROPOP2025 | H20: AIReF25
B21: 1990 | C21: 1.35899
B22: 1991 | C22: 1.32632
B23: 1992 | C23: 1.31016
B24: 1993 | C24: 1.25605
B25: 1994 | C25: 1.18853
B26: 1995 | C26: 1.15523
B27: 1996 | C27: 1.13831
B28: 1997 | C28: 1.14794
B29: 1998 | C29: 1.1266
B30: 1999 | C30: 1.16492
B31: 2000 | C31: 1.21207
B32: 2001 | C32: 1.2353
... B53: 2022 | C53: 1.15725
B54: 2023 | C54: 1.11856 | H54: 1.11856
B55: 2024 | C55: 1.10269 | D55: 1.10269 | E55: 1.10269 | F55: 1.10269 | G55: 1.10269 | H55: 1.1189156
B56: 2025 | D56: 1.1036938 | E56: 1.1347988 | F56: 1.0737864 | G56: 1.10738 | H56: 1.1276932
B57: 2026 | D57: 1.1027277 | E57: 1.1401015 | F57: 1.0686904 | G57: 1.1141 | H57: 1.1400335
B58: 2027 | D58: 1.1019548 | E58: 1.1420734 | F58: 1.0630775 | G58: 1.11831 | H58: 1.1497046
B59: 2028 | D59: 1.0977075 | E59: 1.1398838 | F59: 1.0607933 | G59: 1.12252 | H59: 1.1589152
B60: 2029 | D60: 1.0946914 | E60: 1.137641 | F60: 1.0543123 | G60: 1.12671 | H60: 1.1689641
B61: 2030 | D61: 1.0890768 | E61: 1.1327364 | F61: 1.0501587 | G61: 1.13097 | H61: 1.1747067
B62: 2031 | D62: 1.0839463 | E62: 1.1252349 | F62: 1.0421505 | G62: 1.13519 | H62: 1.180894
B63: 2032 | D63: 1.0768202 | E63: 1.1192906 | F63: 1.0352775 | G63: 1.13937 | H63: 1.1897786
B64: 2033 | D64: 1.0668778 | E64: 1.108938 | F64: 1.0272142 | G64: 1.14358 | H64: 1.1978938
B65: 2034 | D65: 1.0616963 | E65: 1.103707 | F65: 1.0220202 | G65: 1.14782 | H65: 1.2029178
B66: 2035 | D66: 1.0542644 | E66: 1.0966449 | F66: 1.0143567 | G66: 1.15201 | H66: 1.2078317
B67: 2036 | D67: 1.0474915 | E67: 1.0906746 | F67: 1.0056799 | G67: 1.15628 | H67: 1.2152601
... B81: 2050 | D81: 1.0166261 | E81: 1.0600712 | F81: 0.97362689 | G81: 1.21568 | H81: 1.3061325

Sheet Anexo I. Gr 7B
A1: Índice de gráficos
B2: ANEXO I. GRÁFICO 7. PROYECCIONES DEL NÚMERO DE HIJOS POR MUJER Y DEL DIFERENCIAL ENTRE MADRES DE NACIONALIDAD EXTRANJERA Y ESPAÑOLA
B3: ANEXO I. GRÁFICO 7B. DIFERENCIAL EN EL NÚMERO DE HIJOS POR MUJER DE MADRES DE NACIONALIDAD EXTRANJERA Y ESPAÑOLA
B18: Fuente: | C18: INE y AIReF
B19: Diferencial según nacionalidad
C20: Histórico | D20: AIReF 2026
B21: 2002 | C21: ='Anexo I. Gr 6B'!C21-'Anexo I. Gr 6A'!C21 -> 0.64965
B22: 2003 | C22: ='Anexo I. Gr 6B'!C22-'Anexo I. Gr 6A'!C22 -> 0.51753
B23: 2004 | C23: ='Anexo I. Gr 6B'!C23-'Anexo I. Gr 6A'!C23 -> 0.48662
B24: 2005 | C24: ='Anexo I. Gr 6B'!C24-'Anexo I. Gr 6A'!C24 -> 0.38024
B25: 2006 | C25: ='Anexo I. Gr 6B'!C25-'Anexo I. Gr 6A'!C25 -> 0.37667
B26: 2007 | C26: ='Anexo I. Gr 6B'!C26-'Anexo I. Gr 6A'!C26 -> 0.41306
B27: 2008 | C27: ='Anexo I. Gr 6B'!C27-'Anexo I. Gr 6A'!C27 -> 0.46646
B28: 2009 | C28: ='Anexo I. Gr 6B'!C28-'Anexo I. Gr 6A'!C28 -> 0.37373
B29: 2010 | C29: ='Anexo I. Gr 6B'!C29-'Anexo I. Gr 6A'!C29 -> 0.37554
B30: 2011 | C30: ='Anexo I. Gr 6B'!C30-'Anexo I. Gr 6A'!C30 -> 0.28569
B31: 2012 | C31: ='Anexo I. Gr 6B'!C31-'Anexo I. Gr 6A'!C31 -> 0.28727
B32: 2013 | C32: ='Anexo I. Gr 6B'!C32-'Anexo I. Gr 6A'!C32 -> 0.29345
... B42: 2023 | C42: ='Anexo I. Gr 6B'!C42-'Anexo I. Gr 6A'!C42 -> 0.19227
B43: 2024 | C43: ='Anexo I. Gr 6B'!C43-'Anexo I. Gr 6A'!C43 -> 0.19946 | D43: ='Anexo I. Gr 6B'!D43-'Anexo I. Gr 6A'!$D$43 -> 0.19946
B44: 2025 | D44: ='Anexo I. Gr 6B'!D44-'Anexo I. Gr 6A'!$D$43 -> 0.21022135
B45: 2026 | D45: ='Anexo I. Gr 6B'!D45-'Anexo I. Gr 6A'!$D$43 -> 0.23333991
B46: 2027 | D46: ='Anexo I. Gr 6B'!D46-'Anexo I. Gr 6A'!$D$43 -> 0.25647217
B47: 2028 | D47: ='Anexo I. Gr 6B'!D47-'Anexo I. Gr 6A'!$D$43 -> 0.27745782
B48: 2029 | D48: ='Anexo I. Gr 6B'!D48-'Anexo I. Gr 6A'!$D$43 -> 0.29685472
B49: 2030 | D49: ='Anexo I. Gr 6B'!D49-'Anexo I. Gr 6A'!$D$43 -> 0.30399765
B50: 2031 | D50: ='Anexo I. Gr 6B'!D50-'Anexo I. Gr 6A'!$D$43 -> 0.3116044
B51: 2032 | D51: ='Anexo I. Gr 6B'!D51-'Anexo I. Gr 6A'!$D$43 -> 0.30548245
B52: 2033 | D52: ='Anexo I. Gr 6B'!D52-'Anexo I. Gr 6A'!$D$43 -> 0.30310991
B53: 2034 | D53: ='Anexo I. Gr 6B'!D53-'Anexo I. Gr 6A'!$D$43 -> 0.29728187
B54: 2035 | D54: ='Anexo I. Gr 6B'!D54-'Anexo I. Gr 6A'!$D$43 -> 0.28891249
B55: 2036 | D55: ='Anexo I. Gr 6B'!D55-'Anexo I. Gr 6A'!$D$43 -> 0.28451806
... B69: 2050 | D69: ='Anexo I. Gr 6B'!D69-'Anexo I. Gr 6A'!$D$43 -> 0.20141185

Sheet Anexo I. Gr 8A
A1: Índice de gráficos
B2: ANEXO I. GRÁFICO 8. IMPLICACIONES DE LAS PROYECCIONES EN TÉRMINOS DE LA PROPORCIÓN MUJERES QUE ACCEDEN A LA MATERNIDAD Y DE LA COHORTE
B3: ANEXO I. GRÁFICO 8A. PROPORCIÓN DE MUJERES QUE TIENEN HIJOS
B18: Fuente: | C18: INE y AIReF
B19: Proporción de entrada a la maternidad
C20: Española | E20: Extranjera
C21: observado | D21: proyectado | E21: observado | F21: proyectado
B22: 2010 | C22: 0.71519819 | E22: 0.88929972
B23: 2011 | C23: 0.7119903 | E23: 0.8310956
B24: 2012 | C24: 0.70259524 | E24: 0.80556263
B25: 2013 | C25: 0.6873884 | E25: 0.79010354
B26: 2014 | C26: 0.70379982 | E26: 0.81402115
B27: 2015 | C27: 0.69869186 | E27: 0.82506163
B28: 2016 | C28: 0.68534342 | E28: 0.82815521
B29: 2017 | C29: 0.66041471 | E29: 0.80941509
B30: 2018 | C30: 0.62393262 | E30: 0.76987569
B31: 2019 | C31: 0.61369897 | E31: 0.74653773
B32: 2020 | C32: 0.60423043 | E32: 0.72029981
B33: 2021 | C33: 0.61038002 | E33: 0.624625
... B35: 2023 | C35: 0.57946108 | E35: 0.60198172
B36: 2024 | C36: 0.57047236 | D36: =C36 -> 0.57047236 | E36: 0.61179214 | F36: =E36 -> 0.61179214
B37: 2025 | D37: ='Anexo I. Gr 6A'!D44/AVERAGE('Anexo I. Gr 3B'!C$31:C$35) -> 0.56928305 | F37: ='Anexo I. Gr 6B'!D44/AVERAGE('Anexo I. Gr 3B'!D$31:D$35) -> 0.60976009
B38: 2026 | D38: ='Anexo I. Gr 6A'!D45/AVERAGE('Anexo I. Gr 3B'!C$31:C$35) -> 0.56455816 | F38: ='Anexo I. Gr 6B'!D45/AVERAGE('Anexo I. Gr 3B'!D$31:D$35) -> 0.62076373
B39: 2027 | D39: ='Anexo I. Gr 6A'!D46/AVERAGE('Anexo I. Gr 3B'!C$31:C$35) -> 0.55969234 | F39: ='Anexo I. Gr 6B'!D46/AVERAGE('Anexo I. Gr 3B'!D$31:D$35) -> 0.63177389
B40: 2028 | D40: ='Anexo I. Gr 6A'!D47/AVERAGE('Anexo I. Gr 3B'!C$31:C$35) -> 0.55254695 | F40: ='Anexo I. Gr 6B'!D47/AVERAGE('Anexo I. Gr 3B'!D$31:D$35) -> 0.64176234
B41: 2029 | D41: ='Anexo I. Gr 6A'!D48/AVERAGE('Anexo I. Gr 3B'!C$31:C$35) -> 0.54667811 | F41: ='Anexo I. Gr 6B'!D48/AVERAGE('Anexo I. Gr 3B'!D$31:D$35) -> 0.65099459
B42: 2030 | D42: ='Anexo I. Gr 6A'!D49/AVERAGE('Anexo I. Gr 3B'!C$31:C$35) -> 0.54164581 | F42: ='Anexo I. Gr 6B'!D49/AVERAGE('Anexo I. Gr 3B'!D$31:D$35) -> 0.65439438
B43: 2031 | D43: ='Anexo I. Gr 6A'!D50/AVERAGE('Anexo I. Gr 3B'!C$31:C$35) -> 0.53709236 | F43: ='Anexo I. Gr 6B'!D50/AVERAGE('Anexo I. Gr 3B'!D$31:D$35) -> 0.65801493
B44: 2032 | D44: ='Anexo I. Gr 6A'!D51/AVERAGE('Anexo I. Gr 3B'!C$31:C$35) -> 0.53366279 | F44: ='Anexo I. Gr 6B'!D51/AVERAGE('Anexo I. Gr 3B'!D$31:D$35) -> 0.6551011
B45: 2033 | D45: ='Anexo I. Gr 6A'!D52/AVERAGE('Anexo I. Gr 3B'!C$31:C$35) -> 0.52727452 | F45: ='Anexo I. Gr 6B'!D52/AVERAGE('Anexo I. Gr 3B'!D$31:D$35) -> 0.65397184
B46: 2034 | D46: ='Anexo I. Gr 6A'!D53/AVERAGE('Anexo I. Gr 3B'!C$31:C$35) -> 0.52491616 | F46: ='Anexo I. Gr 6B'!D53/AVERAGE('Anexo I. Gr 3B'!D$31:D$35) -> 0.6511979
B47: 2035 | D47: ='Anexo I. Gr 6A'!D54/AVERAGE('Anexo I. Gr 3B'!C$31:C$35) -> 0.52112668 | F47: ='Anexo I. Gr 6B'!D54/AVERAGE('Anexo I. Gr 3B'!D$31:D$35) -> 0.64721436
B48: 2036 | D48: ='Anexo I. Gr 6A'!D55/AVERAGE('Anexo I. Gr 3B'!C$31:C$35) -> 0.51684951 | F48: ='Anexo I. Gr 6B'!D55/AVERAGE('Anexo I. Gr 3B'!D$31:D$35) -> 0.64512277
... B62: 2050 | D62: ='Anexo I. Gr 6A'!D69/AVERAGE('Anexo I. Gr 3B'!C$31:C$35) -> 0.49507493 | F62: ='Anexo I. Gr 6B'!D69/AVERAGE('Anexo I. Gr 3B'!D$31:D$35) -> 0.60556707

Sheet Anexo I. Gr 8B
A1: Índice de gráficos
B2: ANEXO I. GRÁFICO 8. IMPLICACIONES DE LAS PROYECCIONES EN TÉRMINOS DE LA PROPORCIÓN MUJERES QUE ACCEDEN A LA MATERNIDAD Y DE LA COHORTE
B3: ANEXO I. GRÁFICO 8B. ÍNDICE COYUNTURAL DE FECUNDIDAD Y FECUNDIDAD DE LA COHORTE COMPLETA
B18: Fuente: | C18: INE y AIReF
B19: Número de hijos por mujer (por periodo y por cohorte)
C20: CCF observado | D20: CCF proyectado | E20: ICF observado | F20: ICF proyectado
B21: =1960+30 -> 1990 | C21: 1.78 | E21: 1.36 | F21: #N/A
B22: =B21+1 -> 1991 | C22: 1.72 | E22: 1.33 | F22: #N/A
B23: =B22+1 -> 1992 | C23: 1.7 | E23: 1.31 | F23: #N/A
B24: =B23+1 -> 1993 | C24: 1.66 | E24: 1.26 | F24: #N/A
B25: =B24+1 -> 1994 | C25: 1.65 | E25: 1.19 | F25: #N/A
B26: =B25+1 -> 1995 | C26: 1.61 | E26: 1.16 | F26: #N/A
B27: =B26+1 -> 1996 | C27: 1.59 | E27: 1.14 | F27: #N/A
B28: =B27+1 -> 1997 | C28: 1.57 | E28: 1.15 | F28: #N/A
B29: =B28+1 -> 1998 | C29: 1.56 | E29: 1.13 | F29: #N/A
B30: =B29+1 -> 1999 | C30: 1.5 | E30: 1.16 | F30: #N/A
B31: =B30+1 -> 2000 | C31: 1.49 | E31: 1.21 | F31: #N/A
B32: =B31+1 -> 2001 | C32: 1.46 | E32: 1.24 | F32: #N/A
B33: =B32+1 -> 2002 | C33: 1.44 | E33: 1.25 | F33: #N/A
... B36: =B35+1 -> 2005 | C36: 1.38 | E36: 1.33 | F36: #N/A
B37: =B36+1 -> 2006 | D37: 1.37 | E37: 1.36 | F37: #N/A
B38: =B37+1 -> 2007 | D38: 1.36 | E38: 1.38 | F38: #N/A
B39: =B38+1 -> 2008 | D39: 1.37 | E39: 1.44 | F39: #N/A
B40: =B39+1 -> 2009 | D40: 1.36 | E40: 1.38 | F40: #N/A
B41: =B40+1 -> 2010 | D41: 1.38 | E41: 1.37 | F41: #N/A
B42: =B41+1 -> 2011 | D42: 1.38 | E42: 1.34 | F42: #N/A
B43: =B42+1 -> 2012 | D43: 1.39 | E43: 1.32 | F43: #N/A
B44: =B43+1 -> 2013 | D44: 1.38 | E44: 1.27 | F44: #N/A
B45: =B44+1 -> 2014 | D45: 1.37 | E45: 1.32 | F45: #N/A
B46: =B45+1 -> 2015 | D46: 1.37 | E46: 1.33 | F46: #N/A
B47: =B46+1 -> 2016 | D47: 1.35 | E47: 1.33 | F47: #N/A
B48: =B47+1 -> 2017 | D48: 1.35 | E48: 1.31 | F48: #N/A
... B54: =B53+1 -> 2023 | D54: 1.19 | E54: 1.12 | F54: #N/A
B55: =B54+1 -> 2024 | D55: 1.17 | E55: 1.1 | F55: 1.1
B56: =B55+1 -> 2025 | D56: 1.16 | E56: #N/A | F56: 1.1
B57: =B56+1 -> 2026 | D57: 1.15 | E57: #N/A | F57: 1.1
B58: =B57+1 -> 2027 | D58: 1.14 | E58: #N/A | F58: 1.1
B59: =B58+1 -> 2028 | D59: 1.14 | E59: #N/A | F59: 1.1
B60: =B59+1 -> 2029 | D60: 1.13 | E60: #N/A | F60: 1.09
B61: =B60+1 -> 2030 | D61: 1.12 | E61: #N/A | F61: 1.09
B62: =B61+1 -> 2031 | D62: 1.11 | E62: #N/A | F62: 1.08
B63: =B62+1 -> 2032 | D63: 1.1 | E63: #N/A | F63: 1.08
B64: =B63+1 -> 2033 | D64: 1.09 | E64: #N/A | F64: 1.07
B65: =B64+1 -> 2034 | D65: 1.09 | E65: #N/A | F65: 1.06
B66: =B65+1 -> 2035 | D66: 1.08 | E66: #N/A | F66: 1.05
B67: =B66+1 -> 2036 | D67: 1.07 | E67: #N/A | F67: 1.05
... B71: =B70+1 -> 2040 | D71: 1.05 | E71: #N/A | F71: 1.03

Sheet Anexo I. Gr 9A
A1: Índice de gráficos
B2: ANEXO I. GRÁFICO 9. ESPERANZA DE VIDA. SEGÚN SEXO (AÑOS)
B3: ANEXO I. GRÁFICO 9A. ESPERANZA DE VIDA AL NACER. SEGÚN SEXO
B18: Fuente: | C18: INE y AIReF
B19: Niveles
C20: Hombres | D20: Mujeres | E20: Diferencial
B21: 1991 | C21: 73.487287 | D21: 80.649806 | E21: =D21-C21 -> 7.162519
B22: 1992 | C22: 73.888807 | D22: 81.144618 | E22: =D22-C22 -> 7.255811
B23: 1993 | C23: 74.089323 | D23: 81.226085 | E23: =D23-C23 -> 7.136762
B24: 1994 | C24: 74.466313 | D24: 81.59828 | E24: =D24-C24 -> 7.131967
B25: 1995 | C25: 74.532792 | D25: 81.721377 | E25: =D25-C25 -> 7.188585
B26: 1996 | C26: 74.659576 | D26: 81.882296 | E26: =D26-C26 -> 7.22272
B27: 1997 | C27: 75.287185 | D27: 82.225998 | E27: =D27-C27 -> 6.938813
B28: 1998 | C28: 75.417725 | D28: 82.311221 | E28: =D28-C28 -> 6.893496
B29: 1999 | C29: 75.425013 | D29: 82.3248 | E29: =D29-C29 -> 6.899787
B30: 2000 | C30: 75.926322 | D30: 82.732117 | E30: =D30-C30 -> 6.805795
B31: 2001 | C31: 76.268321 | D31: 83.053229 | E31: =D31-C31 -> 6.784908
B32: 2002 | C32: 76.378391 | D32: 83.135444 | E32: =D32-C32 -> 6.757053
... B54: 2024 | C54: 81.384766 | D54: 86.528421 | E54: =D54-C54 -> 5.143655

Sheet Anexo I. Gr 9B
A1: Índice de gráficos
B2: ANEXO I. GRÁFICO 9. ESPERANZA DE VIDA. SEGÚN SEXO (AÑOS)
B3: ANEXO I. GRÁFICO 9B. ESPERANZA DE VIDA AL LOS 65 AÑOS. SEGÚN SEXO
B18: Fuente: | C18: INE y AIReF
B19: Esperanza de vida a los 65 años
C20: Hombres | D20: Mujeres | E20: Diferencial
B21: 1991 | C21: 15.574615 | D21: 19.22954 | E21: =D21-C21 -> 3.654925
B22: 1992 | C22: 15.881408 | D22: 19.621545 | E22: =D22-C22 -> 3.740137
B23: 1993 | C23: 15.844071 | D23: 19.62543 | E23: =D23-C23 -> 3.781359
B24: 1994 | C24: 16.087008 | D24: 19.899046 | E24: =D24-C24 -> 3.812038
B25: 1995 | C25: 16.096 | D25: 19.977443 | E25: =D25-C25 -> 3.881443
B26: 1996 | C26: 16.158537 | D26: 20.079974 | E26: =D26-C26 -> 3.921437
B27: 1997 | C27: 16.299746 | D27: 20.262486 | E27: =D27-C27 -> 3.96274
B28: 1998 | C28: 16.215089 | D28: 20.218052 | E28: =D28-C28 -> 4.002963
B29: 1999 | C29: 16.166991 | D29: 20.195169 | E29: =D29-C29 -> 4.028178
B30: 2000 | C30: 16.607801 | D30: 20.564943 | E30: =D30-C30 -> 3.957142
B31: 2001 | C31: 16.814853 | D31: 20.827024 | E31: =D31-C31 -> 4.012171
B32: 2002 | C32: 16.859732 | D32: 20.871898 | E32: =D32-C32 -> 4.012166
... B54: 2024 | C54: 19.868122 | D54: 23.64142 | E54: =D54-C54 -> 3.773298

Sheet Anexo I. Gr 10A
A1: Índice de gráficos
B2: ANEXO I. GRÁFICO 10. EVOLUCIÓN DE LA ESPERANZA DE VIDA AL NACER. SEGÚN SEXO EN ENTORNO INTERNACIONAL
B3: ANEXO I. GRÁFICO 10A. HOMBRES
B18: Fuente: | C18: Eurostat
B19: Hombres
C20: Austria | D20: Bélgica | E20: Suiza | F20: Dinamarca | G20: Grecia | H20: Finlandia | I20: Italia | J20: P. Bajos | K20: Noruega | L20: Portugal | M20: Suecia | N20: España
B21: 1960 | D21: 66.8 | E21: 68.7 | K21: 71.6 | L21: 61.1
B22: 1961 | D22: 67.6 | E22: 68.9 | G22: 70.2 | K22: 71.4 | L22: 59.9
B23: 1962 | D23: 67.4 | E23: 68.4 | G23: 69.9 | K23: 71.2 | L23: 61.2
B24: 1963 | D24: 67.1 | E24: 68.3 | G24: 70.2 | K24: 71.1 | L24: 61.8
B25: 1964 | D25: 67.8 | E25: 69.2 | G25: 69.9 | K25: 71.5 | L25: 62
B26: 1965 | D26: 67.6 | E26: 69.5 | G26: 70.5 | K26: 71.3 | L26: 62.6
B27: 1966 | D27: 67.8 | E27: 69.6 | G27: 70.5 | K27: 71.6 | L27: 62
B28: 1967 | D28: 67.9 | E28: 69.7 | G28: 70.4 | K28: 71.5 | L28: 62.8
B29: 1968 | D29: 67.6 | E29: 69.8 | G29: 70.6 | K29: 71.4 | L29: 63.3 | M29: 71.7
B30: 1969 | D30: 67.6 | E30: 69.7 | G30: 71 | K30: 71 | L30: 62.8 | M30: 71.7
B31: 1970 | C31: 66.5 | D31: 67.9 | E31: 70 | G31: 71.6 | K31: 71.2 | L31: 63.6 | M31: 72.3
B32: 1971 | C32: 66.7 | D32: 67.9 | E32: 70.2 | G32: 72.2 | K32: 71.3 | L32: 63.1 | M32: 72
B33: 1972 | C33: 67 | D33: 68.2 | E33: 70.6 | G33: 71.7 | K33: 71.5 | L33: 65.2 | M33: 72
B34: 1973 | C34: 67.6 | D34: 68.4 | E34: 71 | G34: 72 | K34: 71.5 | L34: 64.4 | M34: 72.2
B35: 1974 | C35: 67.5 | D35: 68.8 | E35: 71.2 | F35: 71 | G35: 72.4 | K35: 71.9 | L35: 64.8 | M35: 72.2
B36: 1975 | C36: 67.7 | D36: 68.8 | E36: 71.5 | F36: 71.3 | G36: 72.2 | K36: 71.9 | L36: 64.6 | M36: 72.2 | N36: 70.5
B37: 1976 | C37: 68.2 | D37: 68.9 | E37: 71.6 | F37: 70.9 | G37: 72.3 | K37: 72.2 | L37: 65.3 | M37: 72.2 | N37: 70.8
B38: 1977 | C38: 68.5 | D38: 69.5 | E38: 72 | F38: 71.8 | G38: 72.4 | K38: 72.5 | L38: 66.4 | M38: 72.4 | N38: 71.2
B39: 1978 | C39: 68.5 | D39: 69.4 | E39: 71.9 | F39: 71.5 | G39: 72.9 | K39: 72.6 | L39: 67.1 | M39: 72.5 | N39: 71.3
B40: 1979 | C40: 68.8 | D40: 69.9 | E40: 72.3 | F40: 71.2 | G40: 73.2 | K40: 72.4 | L40: 67.9 | M40: 72.5 | N40: 71.8
B41: 1980 | C41: 69 | D41: 69.9 | E41: 72.3 | F41: 71.2 | G41: 73 | H41: 69.2 | K41: 72.4 | L41: 67.9 | M41: 72.8 | N41: 72.3
B42: 1981 | C42: 69.3 | D42: 70.3 | E42: 72.5 | F42: 71.3 | G42: 73.4 | H42: 69.6 | K42: 72.7 | L42: 68.2 | M42: 73.1 | N42: 72.5
B43: 1982 | C43: 69.4 | D43: 70.6 | E43: 72.8 | F43: 71.6 | G43: 73.6 | H43: 70.3 | K43: 72.7 | L43: 69 | M43: 73.5 | N43: 73.1
B44: 1983 | C44: 69.5 | D44: 70.6 | E44: 72.7 | F44: 71.5 | G44: 73.4 | H44: 70.3 | K44: 72.8 | L44: 69 | M44: 73.6 | N44: 72.9
B45: 1984 | C45: 70.1 | D45: 71 | E45: 73.4 | F45: 71.7 | G45: 73.8 | H45: 70.5 | K45: 73 | L45: 69.2 | M45: 73.9 | N45: 73.1
B46: 1985 | C46: 70.4 | D46: 71.1 | E46: 73.5 | F46: 71.5 | G46: 73.5 | H46: 70.2 | I46: 72.3 | J46: 73.1 | K46: 72.6 | L46: 69.4 | M46: 73.8 | N46: 73.1
B47: 1986 | C47: 71 | D47: 71.4 | E47: 73.7 | F47: 71.8 | G47: 74.1 | H47: 70.6 | I47: 72.6 | J47: 73.1 | K47: 72.9 | L47: 69.9 | M47: 74 | N47: 73.4
B48: 1987 | C48: 71.5 | D48: 72 | E48: 74 | F48: 71.8 | G48: 73.9 | H48: 70.7 | I48: 73 | J48: 73.5 | K48: 72.8 | L48: 70.3 | M48: 74.2 | N48: 73.5
B49: 1988 | C49: 71.9 | D49: 72.2 | E49: 73.9 | F49: 72.1 | G49: 74.3 | H49: 70.7 | I49: 73.2 | J49: 73.7 | K49: 73.1 | L49: 70.3 | M49: 74.1 | N49: 73.5
B50: 1989 | C50: 71.9 | D50: 72.3 | E50: 74.1 | F50: 72 | G50: 74.5 | H50: 70.9 | I50: 73.6 | J50: 73.7 | K50: 73.3 | L50: 70.9 | M50: 74.8 | N50: 73.4
B51: 1990 | C51: 72.3 | D51: 72.7 | E51: 74 | F51: 72 | G51: 74.7 | H51: 71 | I51: 73.8 | J51: 73.8 | K51: 73.4 | L51: 70.6 | M51: 74.8 | N51: 73.3
B52: 1991 | C52: 72.3 | D52: 72.9 | E52: 74.2 | F52: 72.5 | G52: 74.8 | H52: 71.4 | I52: 73.8 | J52: 74.1 | K52: 74 | L52: 70.5 | M52: 75 | N52: 73.4
B53: 1992 | C53: 72.5 | D53: 73 | E53: 74.5 | F53: 72.6 | G53: 74.7 | H53: 71.7 | I53: 74.2 | J53: 74.3 | K53: 74.2 | L53: 71 | M53: 75.4 | N53: 73.8
B54: 1993 | C54: 72.8 | D54: 73 | E54: 75 | F54: 72.6 | G54: 75.1 | H54: 72.1 | I54: 74.6 | J54: 74 | K54: 74.2 | L54: 71 | M54: 75.5 | N54: 74
B55: 1994 | C55: 73.2 | D55: 73.4 | E55: 75.2 | F55: 72.8 | G55: 75.3 | H55: 72.8 | I55: 74.8 | J55: 74.6 | K55: 74.9 | L55: 72 | M55: 76.1 | N55: 74.4
B56: 1995 | C56: 73.4 | D56: 73.5 | E56: 75.4 | F56: 72.7 | G56: 75.2 | H56: 72.8 | I56: 75 | J56: 74.6 | K56: 74.8 | L56: 71.7 | M56: 76.2 | N56: 74.4
B57: 1996 | C57: 73.7 | D57: 73.9 | E57: 76 | F57: 73.1 | G57: 75.3 | H57: 73.1 | I57: 75.4 | J57: 74.7 | K57: 75.4 | L57: 71.6 | M57: 76.6 | N57: 74.5
... B85: 2024 | C85: 80 | D85: 80.5 | E85: 82.7 | F85: 80.4 | G85: 79.3 | H85: 79.8 | I85: 82 | J85: 80.6 | K85: 81.7 | L85: 79.8 | M85: 82.6 | N85: 81.3

Sheet Anexo I. Gr 10B
A1: Índice de gráficos
B2: ANEXO I. GRÁFICO 10. EVOLUCIÓN DE LA ESPERANZA DE VIDA AL NACER. SEGÚN SEXO EN ENTORNO INTERNACIONAL
B3: ANEXO I. GRÁFICO 10B. MUJERES
B18: Fuente: | C18: Eurostat
B19: Mujeres
C20: Austria | D20: Bélgica | E20: Suiza | F20: Dinamarca | G20: Grecia | H20: Finlandia | I20: Italia | J20: P. Bajos | K20: Noruega | L20: Portugal | M20: Suecia | N20: España
B21: 1960 | D21: 72.8 | E21: 74.1 | K21: 76 | L21: 66.7
B22: 1961 | D22: 73.6 | E22: 74.6 | G22: 73.8 | K22: 76.2 | L22: 65.4
B23: 1962 | D23: 73.2 | E23: 74.1 | G23: 73.4 | K23: 76.2 | L23: 67
B24: 1963 | D24: 73.1 | E24: 74.3 | G24: 73.7 | K24: 75.7 | L24: 67.6
B25: 1964 | D25: 73.9 | E25: 75.2 | G25: 73.8 | K25: 76.3 | L25: 67.8
B26: 1965 | D26: 73.8 | E26: 75.1 | G26: 74.3 | K26: 76.7 | L26: 68.9
B27: 1966 | D27: 73.8 | E27: 75.3 | G27: 74.7 | K27: 76.9 | L27: 68.4
B28: 1967 | D28: 74.2 | E28: 75.8 | G28: 74.2 | K28: 77.1 | L28: 69.2
B29: 1968 | D29: 73.9 | E29: 75.6 | G29: 74.2 | K29: 77 | L29: 69.4 | M29: 76.4
B30: 1969 | D30: 74.1 | E30: 75.7 | G30: 75 | K30: 76.9 | L30: 69 | M30: 76.7
B31: 1970 | C31: 73.5 | D31: 74.2 | E31: 76.2 | G31: 76 | K31: 77.5 | L31: 69.7 | M31: 77.3
B32: 1971 | C32: 73.7 | D32: 74.4 | E32: 76.3 | G32: 76.2 | K32: 77.5 | L32: 69.7 | M32: 77.5
B33: 1972 | C33: 74.1 | D33: 74.8 | E33: 76.9 | G33: 75.9 | K33: 77.7 | L33: 71.5 | M33: 77.6
B34: 1973 | C34: 74.6 | D34: 75 | E34: 77.1 | G34: 76.2 | K34: 77.9 | L34: 70.6 | M34: 77.8
B35: 1974 | C35: 74.7 | D35: 75.3 | E35: 77.6 | F35: 76.9 | G35: 76.8 | K35: 78.2 | L35: 71.4 | M35: 78
B36: 1975 | C36: 74.7 | D36: 75.3 | E36: 78.1 | F36: 77.1 | G36: 76.7 | K36: 78.3 | L36: 72.1 | M36: 78.1 | N36: 76.3
B37: 1976 | C37: 75.1 | D37: 75.5 | E37: 78.2 | F37: 76.8 | G37: 76.7 | K37: 78.4 | L37: 72.6 | M37: 78 | N37: 76.6
B38: 1977 | C38: 75.5 | D38: 76.2 | E38: 78.8 | F38: 77.9 | G38: 77 | K38: 78.9 | L38: 73.7 | M38: 78.7 | N38: 77.1
B39: 1978 | C39: 75.7 | D39: 76.1 | E39: 78.8 | F39: 77.6 | G39: 77.5 | K39: 78.9 | L39: 73.9 | M39: 78.8 | N39: 77.4
B40: 1979 | C40: 76 | D40: 76.6 | E40: 79 | F40: 77.5 | G40: 77.8 | K40: 79.1 | L40: 74.7 | M40: 78.8 | N40: 78
B41: 1980 | C41: 76.1 | D41: 76.7 | E41: 79 | F41: 77.3 | G41: 77.5 | H41: 78 | K41: 79.3 | L41: 74.9 | M41: 79 | N41: 78.5
B42: 1981 | C42: 76.5 | D42: 77.1 | E42: 79.3 | F42: 77.5 | G42: 77.9 | H42: 78.2 | K42: 79.4 | L42: 75.2 | M42: 79.3 | N42: 78.8
B43: 1982 | C43: 76.7 | D43: 77.3 | E43: 79.6 | F43: 77.8 | G43: 78.2 | H43: 78.8 | K43: 79.7 | L43: 76 | M43: 79.5 | N43: 79.4
B44: 1983 | C44: 76.7 | D44: 77.3 | E44: 79.7 | F44: 77.7 | G44: 78 | H44: 78.5 | K44: 79.7 | L44: 75.8 | M44: 79.8 | N44: 79.1
B45: 1984 | C45: 77.3 | D45: 78 | E45: 80.3 | F45: 77.8 | G45: 78.6 | H45: 79 | K45: 79.8 | L45: 76.2 | M45: 80.1 | N45: 79.7
B46: 1985 | C46: 77.4 | D46: 78.1 | E46: 80.4 | F46: 77.6 | G46: 78.4 | H46: 78.7 | I46: 78.8 | J46: 79.8 | K46: 79.5 | L46: 76.5 | M46: 79.8 | N46: 79.6
B47: 1986 | C47: 77.8 | D47: 78.2 | E47: 80.5 | F47: 77.7 | G47: 78.8 | H47: 78.9 | I47: 79.1 | J47: 79.7 | K47: 80 | L47: 76.8 | M47: 80.2 | N47: 79.9
B48: 1987 | C48: 78.2 | D48: 78.9 | E48: 80.9 | F48: 77.9 | G48: 78.6 | H48: 78.8 | I48: 79.6 | J48: 80.3 | K48: 79.7 | L48: 77.2 | M48: 80.3 | N48: 80.2
B49: 1988 | C49: 78.7 | D49: 79.1 | E49: 81 | F49: 77.8 | G49: 79.3 | H49: 78.8 | I49: 79.7 | J49: 80.4 | K49: 79.7 | L49: 77.3 | M49: 80 | N49: 80.3
B50: 1989 | C50: 78.8 | D50: 79.1 | E50: 81.2 | F50: 77.9 | G50: 79.5 | H50: 79 | I50: 80.2 | J50: 80.1 | K50: 80 | L50: 77.9 | M50: 80.7 | N50: 80.5
B51: 1990 | C51: 79 | D51: 79.5 | E51: 80.9 | F51: 77.8 | G51: 79.5 | H51: 79 | I51: 80.3 | J51: 80.2 | K51: 79.9 | L51: 77.5 | M51: 80.5 | N51: 80.6
B52: 1991 | C52: 79.1 | D52: 79.7 | E52: 81.4 | F52: 78.1 | G52: 79.8 | H52: 79.5 | I52: 80.4 | J52: 80.3 | K52: 80.2 | L52: 77.7 | M52: 80.7 | N52: 80.7
B53: 1992 | C53: 79.3 | D53: 79.9 | E53: 81.6 | F53: 78 | G53: 79.7 | H53: 79.6 | I53: 80.8 | J53: 80.4 | K53: 80.5 | L53: 78.4 | M53: 81 | N53: 81.3
B54: 1993 | C54: 79.5 | D54: 79.9 | E54: 81.7 | F54: 77.8 | G54: 80.1 | H54: 79.5 | I54: 81 | J54: 80.1 | K54: 80.3 | L54: 78.1 | M54: 80.9 | N54: 81.3
B55: 1994 | C55: 79.8 | D55: 80.2 | E55: 82 | F55: 78.2 | G55: 80.3 | H55: 80.3 | I55: 81.2 | J55: 80.4 | K55: 80.8 | L55: 79 | M55: 81.6 | N55: 81.7
B56: 1995 | C56: 80.1 | D56: 80.4 | E56: 81.9 | F56: 77.9 | G56: 80.4 | H56: 80.4 | I56: 81.5 | J56: 80.5 | K56: 80.9 | L56: 79 | M56: 81.7 | N56: 81.8
B57: 1996 | C57: 80.2 | D57: 80.7 | E57: 82.2 | F57: 78.3 | G57: 80.6 | H57: 80.7 | I57: 81.8 | J57: 80.5 | K57: 81.2 | L57: 79 | M57: 81.7 | N57: 82
... B85: 2024 | C85: 84.5 | D85: 84.6 | E85: 86.2 | F85: 84.2 | G85: 84.5 | H85: 85 | I85: 86 | J85: 83.4 | K85: 84.9 | L85: 85.4 | M85: 85.6 | N85: 86.6

Sheet Anexo I. Gr 11A
A1: Índice de gráficos
B2: ANEXO I. GRÁFICO 11. PROYECCIONES DE LA ESPERANZA DE VIDA. SEGÚN SEXO (AÑOS)
B3: ANEXO I. GRÁFIO 11A. ESPERANZA DE VIDA AL NACER
B18: Fuente: | C18: INE y AIReF
B19: Esperanza de vida al nacer
C20: Hombres | D20: Mujeres | E20: Diferencial
B21: 1991 | C21: 73.487287 | D21: 80.649806 | E21: =D21-C21 -> 7.162519
B22: 1992 | C22: 73.888807 | D22: 81.144618 | E22: =D22-C22 -> 7.255811
B23: 1993 | C23: 74.089323 | D23: 81.226085 | E23: =D23-C23 -> 7.136762
B24: 1994 | C24: 74.466313 | D24: 81.59828 | E24: =D24-C24 -> 7.131967
B25: 1995 | C25: 74.532792 | D25: 81.721377 | E25: =D25-C25 -> 7.188585
B26: 1996 | C26: 74.659576 | D26: 81.882296 | E26: =D26-C26 -> 7.22272
B27: 1997 | C27: 75.287185 | D27: 82.225998 | E27: =D27-C27 -> 6.938813
B28: 1998 | C28: 75.417725 | D28: 82.311221 | E28: =D28-C28 -> 6.893496
B29: 1999 | C29: 75.425013 | D29: 82.3248 | E29: =D29-C29 -> 6.899787
B30: 2000 | C30: 75.926322 | D30: 82.732117 | E30: =D30-C30 -> 6.805795
B31: 2001 | C31: 76.268321 | D31: 83.053229 | E31: =D31-C31 -> 6.784908
B32: 2002 | C32: 76.378391 | D32: 83.135444 | E32: =D32-C32 -> 6.757053
... B80: 2050 | C80: 84.848582 | D80: 89.353308 | E80: =D80-C80 -> 4.5047264

Sheet Anexo I. Gr 11B
A1: Índice de gráficos
B2: ANEXO I. GRÁFICO 11. PROYECCIONES DE LA ESPERANZA DE VIDA. SEGÚN SEXO (AÑOS)
B3: ANEXO I. GRÁFICO 11 B. ESPERANZA DE VIDA A LOS 65 AÑOS
B18: Fuente: | C18: INE y AIReF
B19: Esperanza de vida a los 65 años
C20: Hombres | D20: Mujeres | E20: Diferencial
B21: 1991 | C21: 15.574615 | D21: 19.22954 | E21: =D21-C21 -> 3.654925
B22: 1992 | C22: 15.881408 | D22: 19.621545 | E22: =D22-C22 -> 3.740137
B23: 1993 | C23: 15.844071 | D23: 19.62543 | E23: =D23-C23 -> 3.781359
B24: 1994 | C24: 16.087008 | D24: 19.899046 | E24: =D24-C24 -> 3.812038
B25: 1995 | C25: 16.096 | D25: 19.977443 | E25: =D25-C25 -> 3.881443
B26: 1996 | C26: 16.158537 | D26: 20.079974 | E26: =D26-C26 -> 3.921437
B27: 1997 | C27: 16.299746 | D27: 20.262486 | E27: =D27-C27 -> 3.96274
B28: 1998 | C28: 16.215089 | D28: 20.218052 | E28: =D28-C28 -> 4.002963
B29: 1999 | C29: 16.166991 | D29: 20.195169 | E29: =D29-C29 -> 4.028178
B30: 2000 | C30: 16.607801 | D30: 20.564943 | E30: =D30-C30 -> 3.957142
B31: 2001 | C31: 16.814853 | D31: 20.827024 | E31: =D31-C31 -> 4.012171
B32: 2002 | C32: 16.859732 | D32: 20.871898 | E32: =D32-C32 -> 4.012166
... B80: 2050 | C80: 22.249156 | D80: 26.067206 | E80: =D80-C80 -> 3.8180499

Sheet Anexo I. Gr 12A
A1: Índice de gráficos
B2: ANEXO I. GRÁFICO 12. PROYECCIONES DE ESPERANZA DE VIDA (AÑOS)
B3: ANEXO I. GRÁFICO 12A. ESPERANZA DE VIDA AL NACER
B18: Fuente: | C18: INE, Eurostat y AIReF
B19: Esperanza de vida al nacer
C20: Histórico | D20: AIReF 2026 | E20: Bandas | G20: EUROPOP2025 | H20: AIReF 2025
B21: 1991 | C21: 77.065475
B22: 1992 | C22: 77.514166
B23: 1993 | C23: 77.65726
B24: 1994 | C24: 78.034754
B25: 1995 | C25: 78.123066
B26: 1996 | C26: 78.262819
B27: 1997 | C27: 78.763737
B28: 1998 | C28: 78.867464
B29: 1999 | C29: 78.870477
B30: 2000 | C30: 79.336624
B31: 2001 | C31: 79.670455
B32: 2002 | C32: 79.761154
... B52: 2022 | C52: 83.080876
B53: 2023 | C53: 83.774459 | H53: 83.774459
B54: 2024 | C54: 84.009718 | D54: 84.009718 | E54: 84.009718 | F54: 84.009718 | G54: 84.009718 | H54: 83.852185
B55: 2025 | D55: 84.098444 | E55: 84.570122 | F55: 83.617597 | G55: 84.099183 | H55: 84.05097
B56: 2026 | D56: 84.257946 | E56: 84.88755 | F56: 83.611604 | G56: 84.201064 | H56: 84.152773
B57: 2027 | D57: 84.417941 | E57: 85.242962 | F57: 83.562698 | G57: 84.302634 | H57: 84.318907
B58: 2028 | D58: 84.539546 | E58: 85.537548 | F58: 83.497243 | G58: 84.352903 | H58: 84.424991
B59: 2029 | D59: 84.660324 | E59: 85.800252 | F59: 83.462463 | G59: 84.453988 | H59: 84.571187
B60: 2030 | D60: 84.7803 | E60: 86.042472 | F60: 83.446824 | G60: 84.554876 | H60: 84.68061
B61: 2031 | D61: 84.899532 | E61: 86.26994 | F61: 83.444714 | G61: 84.65558 | H61: 84.814952
B62: 2032 | D62: 85.018038 | E62: 86.486051 | F62: 83.452863 | G62: 84.756137 | H62: 84.926573
B63: 2033 | D63: 85.135814 | E63: 86.692934 | F63: 83.469031 | G63: 84.85675 | H63: 85.053518
B64: 2034 | D64: 85.252871 | E64: 86.892108 | F64: 83.49171 | G64: 84.957374 | H64: 85.166291
B65: 2035 | D65: 85.36922 | E65: 87.084694 | F65: 83.51981 | G65: 85.106855 | H65: 85.288365
B66: 2036 | D66: 85.484869 | E66: 87.271536 | F66: 83.552496 | G66: 85.156314 | H66: 85.401485
... B80: 2050 | D80: 87.035478 | E80: 89.509319 | F80: 84.270886 | G80: 86.562169 | H80: 86.963127

Sheet Anexo I. Gr 12B
A1: Índice de gráficos
B2: ANEXO I. GRÁFICO 12. PROYECCIONES DE ESPERANZA DE VIDA (AÑOS)
B3: ANEXO I. GRÁFICO 12B. ESPERANZA DE VIDA A LOS 65 AÑOS
B18: Fuente: | C18: INE, Eurostat y AIReF
B19: Esperanza de vida a los 65 años
C20: Histórico | D20: AIReF 2026 | E20: Bandas | G20: EUROPOP2025 | H20: AIReF 2025
B21: 1991 | C21: 17.569268
B22: 1992 | C22: 17.92122
B23: 1993 | C23: 17.899794
B24: 1994 | C24: 18.158921
B25: 1995 | C25: 18.198943
B26: 1996 | C26: 18.276793
B27: 1997 | C27: 18.438283
B28: 1998 | C28: 18.36648
B29: 1999 | C29: 18.324048
B30: 2000 | C30: 18.736215
B31: 2001 | C31: 18.971467
B32: 2002 | C32: 19.010215
... B52: 2022 | C52: 21.110134
B53: 2023 | C53: 21.684928 | H53: 21.684928
B54: 2024 | C54: 21.867925 | D54: 21.867925 | E54: 21.867925 | F54: 21.867925 | G54: 21.867925 | H54: 21.840987
B55: 2025 | D55: 22.033417 | E55: 22.385078 | F55: 21.680631 | G55: 22.041302 | H55: 21.996125
B56: 2026 | D56: 22.147679 | E56: 22.617573 | F56: 21.675881 | G56: 22.138589 | H56: 22.065489
B57: 2027 | D57: 22.272181 | E57: 22.884934 | F57: 21.655802 | G57: 22.135946 | H57: 22.189934
B58: 2028 | D58: 22.356842 | E58: 23.10523 | F58: 21.602483 | G58: 22.233214 | H58: 22.259912
B59: 2029 | D59: 22.442922 | E59: 23.303825 | F59: 21.573642 | G59: 22.33009 | H59: 22.367275
B60: 2030 | D60: 22.531295 | E60: 23.490055 | F60: 21.56159 | G60: 22.370957 | H60: 22.445602
B61: 2031 | D61: 22.615197 | E61: 23.661836 | F61: 21.554884 | G61: 22.468328 | H61: 22.542048
B62: 2032 | D62: 22.699113 | E62: 23.825859 | F62: 21.555877 | G62: 22.521422 | H62: 22.619778
B63: 2033 | D63: 22.784308 | E63: 23.984879 | F63: 21.564336 | G63: 22.56308 | H63: 22.712748
B64: 2034 | D64: 22.867672 | E64: 24.137142 | F64: 21.5758 | G64: 22.660832 | H64: 22.791698
B65: 2035 | D65: 22.950454 | E65: 24.284609 | F65: 21.590806 | G65: 22.758689 | H65: 22.879256
B66: 2036 | D66: 23.033346 | E66: 24.428503 | F66: 21.609536 | G66: 22.856533 | H66: 22.959721
... B80: 2050 | D80: 24.240248 | E80: 26.254423 | F80: 22.144744 | G80: 23.839705 | H80: 24.177556

Sheet Anexo I. Gr 13A
A1: Índice de gráficos
B2: ANEXO I. GRÁFICO 13. FLUJOS MIGRATORIOS OBSERVADOS (MILES DE PERSONAS)
B3: ANEXO I. GRÁFICO 13A. FLUJOS DE INMIGRACIÓN Y EMIGRACIÓN
B18: Fuente: | C18: INE y elaboración AIReF
B19: Flujos migratorios
C20: Inmigración | D20: Emigración
B21: 2003 | C21: =C22/(1+0.456481776983468) -> 789156.37 | D21: 126781.37
B22: 2004 | C22: =C23/(1+0.050723018109416) -> 1149391.9 | D22: 484575.87
B23: 2005 | C23: =C24/(1+0.169001395832522) -> 1207692.5 | D23: 572012.49
B24: 2006 | C24: =C25/(1+0.139647782466189) -> 1411794.2 | D24: 748432.21
B25: 2007 | C25: =C26/(1-0.374835379737985) -> 1608948.1 | D25: 831354.14
B26: 2008 | C26: =C27/(1-0.344049316111198) -> 1005857.5 | D26: 571001.45
B27: 2009 | C27: =C28/(1-0.0820916982005939) -> 659792.88 | D27: 521226.88
B28: 2010 | C28: =C29/(1+0.0294729196238468) -> 605629.37 | D28: 528280.37
B29: 2011 | C29: =C30/(1-0.181186798982051) -> 623479.03 | D29: 555080.03
B30: 2012 | C30: =C31/(1-0.0765719247238977) -> 510512.86 | D30: 666476.86
B31: 2013 | C31: =C32/(1+0.0879076261165643) -> 471421.91 | D31: 723623.91
B32: 2014 | C32: =C33/(1+0.120018071460842) -> 512863.49 | D32: 614650.49
B33: 2015 | C33: =C34/(1+0.212306424174398) -> 574416.38 | D33: 578976.38
B34: 2016 | C34: =C35/(1+0.283027966447015) -> 696368.66 | D34: 617831.66
B35: 2017 | C35: =C36/(1+0.209632196522667) -> 893460.47 | D35: 714441.47
B36: 2018 | C36: =C37/(1+0.165913709211352) -> 1080758.6 | D36: 751933.55
B37: 2019 | C37: =C38/(1-0.376508367977827) -> 1260071.2 | D37: 802886.21
B38: 2020 | C38: =C39/(1+0.13023222017533) -> 785643.86 | D38: 550434.86
B39: 2021 | C39: 887960 | D39: 696866
B40: 2022 | C40: 1258894 | D40: 531889
B41: 2023 | C41: 1250991 | D41: 608695
B42: 2024 | C42: 1288562 | D42: 662294

Sheet Anexo I. Gr 13B
A1: Índice de gráficos
B2: ANEXO I. GRÁFICO 13. FLUJOS MIGRATORIOS OBSERVADOS (MILES DE PERSONAS)
B3: ANEXO I. GRÁFICO 13B. FLUJO NETO DE INMIGRACIÓN
B18: Fuente: | C18: INE y elaboración AIReF
B19: Inmigación neta
B20: 2003 | C20: 662375
B21: 2004 | C21: 664816
B22: 2005 | C22: 635680
B23: 2006 | C23: 663362
B24: 2007 | C24: 777594
B25: 2008 | C25: 434856
B26: 2009 | C26: 138566
B27: 2010 | C27: 77349
B28: 2011 | C28: 68399
B29: 2012 | C29: -155964
B30: 2013 | C30: -252202
B31: 2014 | C31: -101787
... B41: 2024 | C41: 626268

Sheet Anexo I. Gr 14
A1: Índice de gráficos
B3: ANEXO I. GRÁFICO 14. PERFIL ETARIO DE LOS FLUJOS DE INMIGRACIÓN
B18: Fuente: | C18: INE
B19: Distribución por edad de los flujos de inmigración
C20: 2008 | D20: 2009 | E20: 2010 | F20: 2011 | G20: 2012 | H20: 2013 | I20: 2014 | J20: 2015 | K20: 2016 | L20: 2017 | M20: 2018 | N20: 2019 | O20: 2020 | P20: 2021 | Q20: 2022 | R20: 2023 | S20: 2024
B21: 0 años | C21: 0.0093210522 | D21: 0.011537982 | E21: 0.01288314 | F21: 0.012433517 | G21: 0.013293691 | H21: 0.014730814 | I21: 0.013576512 | J21: 0.01403918 | K21: 0.012774053 | L21: 0.010495516 | M21: 0.0083503707 | N21: 0.0072846711 | O21: 0.0070589291 | P21: 0.0073764584 | Q21: 0.0073508969 | R21: 0.0062846176 | S21: 0.0060408424
B22: 1 año | C22: 0.009760063 | D22: 0.011512534 | E22: 0.012068067 | F22: 0.011908385 | G22: 0.011504535 | H22: 0.012319605 | I22: 0.01263038 | J22: 0.013682574 | K22: 0.013617941 | L22: 0.013169665 | M22: 0.011469914 | N22: 0.010561241 | O22: 0.0098863476 | P22: 0.0085814676 | Q22: 0.0094535362 | R22: 0.008723484 | S22: 0.0079491712
B23: 2 años | C23: 0.0094612686 | D23: 0.011408199 | E23: 0.011441514 | F23: 0.011248603 | G23: 0.010945424 | H23: 0.011974128 | I23: 0.01227026 | J23: 0.012633216 | K23: 0.012569108 | L23: 0.012466832 | M23: 0.01178684 | N23: 0.010995629 | O23: 0.010612971 | P23: 0.0085217803 | Q23: 0.0095742771 | R23: 0.0084780786 | S23: 0.0080353138
B24: 3 años | C24: 0.0096482238 | D24: 0.010629499 | E24: 0.011033978 | F24: 0.010265663 | G24: 0.010399469 | H24: 0.011233314 | I24: 0.011127698 | J24: 0.011610165 | K24: 0.012113409 | L24: 0.011679433 | M24: 0.011404664 | N24: 0.0111462 | O24: 0.010751884 | P24: 0.0085060138 | Q24: 0.0099674794 | R24: 0.0089521028 | S24: 0.0080391941
B25: 4 años | C25: 0.0094829687 | D25: 0.010245239 | E25: 0.010338117 | F25: 0.0096004955 | G25: 0.0095542239 | H25: 0.010260995 | I25: 0.010652995 | J25: 0.010882337 | K25: 0.011522687 | L25: 0.010918344 | M25: 0.010895098 | N25: 0.011131542 | O25: 0.010670673 | P25: 0.0088911663 | Q25: 0.010360682 | R25: 0.0090664121 | S25: 0.0085964044
B26: 5 años | C26: 0.0096048234 | D26: 0.010311403 | E26: 0.0099998891 | F26: 0.0097162939 | G26: 0.0091496905 | H26: 0.010086476 | I26: 0.0099327558 | J26: 0.010686496 | K26: 0.010903032 | L26: 0.010273767 | M26: 0.010550208 | N26: 0.010685161 | O26: 0.010749747 | P26: 0.0090082887 | Q26: 0.010836496 | R26: 0.0096243698 | S26: 0.0091854331
B27: 6 años | C27: 0.0097700785 | D27: 0.010433552 | E27: 0.0095951251 | F27: 0.0091857756 | G27: 0.008718846 | H27: 0.0091426496 | I27: 0.0094711479 | J27: 0.0097774426 | K27: 0.010476266 | L27: 0.010083964 | M27: 0.0099878201 | N27: 0.010412003 | O27: 0.010108609 | P27: 0.0095015541 | Q27: 0.010978684 | R27: 0.0099736929 | S27: 0.0095113778
B28: 7 años | C28: 0.010355983 | D28: 0.0099831282 | E28: 0.0096422551 | F28: 0.0091049861 | G28: 0.0093667572 | H28: 0.0090856638 | I28: 0.0091601354 | J28: 0.0093769913 | K28: 0.0098373225 | L28: 0.0098847654 | M28: 0.0098076075 | N28: 0.010045571 | O28: 0.0099889297 | P28: 0.0092898329 | Q28: 0.010907987 | R28: 0.010076012 | S28: 0.01008799
B29: 8 años | C29: 0.011245689 | D29: 0.010756738 | E29: 0.0099749379 | F29: 0.0093446618 | G29: 0.0093272905 | H29: 0.0094810024 | I29: 0.0093729334 | J29: 0.0094851424 | K29: 0.0096275561 | L29: 0.0097513399 | M29: 0.009538842 | N29: 0.0099829442 | O29: 0.0097709428 | P29: 0.0090950043 | Q29: 0.010986628 | R29: 0.010290242 | S29: 0.010472915
B30: 9 años | C30: 0.011487729 | D30: 0.011476907 | E30: 0.010332572 | F30: 0.0096166534 | G30: 0.0095673795 | H30: 0.0099297651 | I30: 0.009628291 | J30: 0.0093419153 | K30: 0.0095335228 | L30: 0.0094638172 | M30: 0.0092716302 | N30: 0.0097750773 | O30: 0.0096085212 | P30: 0.0089666201 | Q30: 0.010835702 | R30: 0.010334207 | S30: 0.01056449
B31: 10 años | C31: 0.011544484 | D31: 0.011522713 | E31: 0.010961897 | F31: 0.010168716 | G31: 0.0097811573 | H31: 0.010549485 | I31: 0.0098476366 | J31: 0.0096459075 | K31: 0.0098903669 | L31: 0.0092965655 | M31: 0.0090277217 | N31: 0.0095871975 | O31: 0.0098072739 | P31: 0.0088799045 | Q31: 0.010666506 | R31: 0.01014076 | S31: 0.010728238
B32: 11 años | C32: 0.011869986 | D32: 0.011540527 | E32: 0.010834368 | F32: 0.010599593 | G32: 0.010458669 | H32: 0.010677703 | I32: 0.010544959 | J32: 0.0098622097 | K32: 0.010030211 | L32: 0.0093379086 | M32: 0.008791581 | N32: 0.0091914508 | O32: 0.0091725473 | P32: 0.0091445561 | Q32: 0.010790424 | R32: 0.010207108 | S32: 0.010815933
... B111: 90 y más años | C111: 0.0002687481 | D111: 0.00041734209 | E111: 0.00054892654 | F111: 0.00046050063 | G111: 0.0013484447 | H111: 0.0013177952 | I111: 0.0017122054 | J111: 0.0014615011 | K111: 0.0012827097 | L111: 0.00096404651 | M111: 0.0011076864 | N111: 0.0010006929 | O111: 0.0016263533 | P111: 0.0012568134 | Q111: 0.00084518633 | R111: 0.00087610542 | S111: 0.00076131377

Sheet Anexo I. Gr 15A
A1: Índice de gráficos
B2: ANEXO I. GRÁFICO 15. PROYECCIONES DE FLUJOS MIGRATORIOS (MILES DE PERSONAS)
B3: ANEXO I. GRÁFIO 15A. FLUJO NETO DE INMIGRACIÓN
B18: Fuente: | C18: INE, Eurostat y AIReF
B19: Flujo de inmigración neta
C20: Histórico | D20: AIReF 2026 | E20: Bandas | G20: EUROPOP2025 | H20: AIReF 2025
B21: 2002
B22: 2003 | C22: ='Anexo I. Gr 13B'!C20 -> 662375
B23: 2004 | C23: ='Anexo I. Gr 13B'!C21 -> 664816
B24: 2005 | C24: ='Anexo I. Gr 13B'!C22 -> 635680
B25: 2006 | C25: ='Anexo I. Gr 13B'!C23 -> 663362
B26: 2007 | C26: ='Anexo I. Gr 13B'!C24 -> 777594
B27: 2008 | C27: ='Anexo I. Gr 13B'!C25 -> 434856
B28: 2009 | C28: ='Anexo I. Gr 13B'!C26 -> 138566
B29: 2010 | C29: ='Anexo I. Gr 13B'!C27 -> 77349
B30: 2011 | C30: ='Anexo I. Gr 13B'!C28 -> 68399
B31: 2012 | C31: ='Anexo I. Gr 13B'!C29 -> -155964
B32: 2013 | C32: ='Anexo I. Gr 13B'!C30 -> -252202
B33: 2014 | C33: ='Anexo I. Gr 13B'!C31 -> -101787
... B39: 2020 | C39: ='Anexo I. Gr 13B'!C37 -> 235209
B40: 2021 | C40: 191094
B41: 2022 | C41: 727005
B42: 2023 | C42: 642296 | H42: 642296
B43: 2024 | C43: 626268 | D43: 626268 | E43: 626268 | F43: 626268 | G43: 626268 | H43: 570745.99
B44: 2025 | D44: 552496.23 | E44: 592353.96 | F44: 512638.51 | G44: 568240 | H44: 399150.38
B45: 2026 | D45: 599380.81 | E45: 641656.31 | F45: 557105.31 | G45: 524861 | H45: 360425.06
B46: 2027 | D46: 608963.89 | E46: 653056.02 | F46: 564871.75 | G46: 485772 | H46: 307568.6
B47: 2028 | D47: 593608.16 | E47: 639156.81 | F47: 548059.51 | G47: 446676 | H47: 283109.95
B48: 2029 | D48: 496810.49 | E48: 543696.61 | F48: 449924.38 | G48: 407589 | H48: 262481.89
B49: 2030 | D49: 399541.24 | E49: 447886.94 | F49: 351195.54 | G49: 368487 | H49: 249816.16
B50: 2031 | D50: 346602.1 | E50: 396545.21 | F50: 296658.99 | G50: 330493 | H50: 242153.23
B51: 2032 | D51: 306567.87 | E51: 358088.72 | F51: 255047.03 | G51: 333441 | H51: 238139.9
B52: 2033 | D52: 268830.31 | E52: 321890.75 | F52: 215769.88 | G52: 332614 | H52: 236447.91
B53: 2034 | D53: 251281.26 | E53: 305824.68 | F53: 196737.84 | G53: 332196 | H53: 236207.14
B54: 2035 | D54: 233789 | E54: 289740.35 | F54: 177837.64 | G54: 332095 | H54: 236836.48
B55: 2036 | D55: 231618.53 | E55: 288910.16 | F55: 174326.91 | G55: 333530 | H55: 238036.04
... B69: 2050 | D69: 269122.41 | E69: 340111.08 | F69: 198133.74 | G69: 290950 | H69: 271566.83

Sheet Anexo I. Gr 15B
A1: Índice de gráficos
B2: ANEXO I. GRÁFICO 15. PROYECCIONES DE FLUJOS MIGRATORIOS (MILES DE PERSONAS)
B3: ANEXO I. GRÁFICO 15B. FLUJOS DE INMIGRACIÓN Y EMIGRACIÓN EXTERIOR
B18: Fuente: | C18: INE y AIReF
B19: Flujos de entrada y salida
C20: Inmig. observada | D20: Emig. observada | E20: Inmig. proyectada | F20: Emig. proyectada
B21: 2002
B22: 2003 | C22: ='Anexo I. Gr 13A'!C21 -> 789156.37 | D22: ='Anexo I. Gr 13A'!D21 -> 126781.37
B23: 2004 | C23: ='Anexo I. Gr 13A'!C22 -> 1149391.9 | D23: ='Anexo I. Gr 13A'!D22 -> 484575.87
B24: 2005 | C24: ='Anexo I. Gr 13A'!C23 -> 1207692.5 | D24: ='Anexo I. Gr 13A'!D23 -> 572012.49
B25: 2006 | C25: ='Anexo I. Gr 13A'!C24 -> 1411794.2 | D25: ='Anexo I. Gr 13A'!D24 -> 748432.21
B26: 2007 | C26: ='Anexo I. Gr 13A'!C25 -> 1608948.1 | D26: ='Anexo I. Gr 13A'!D25 -> 831354.14
B27: 2008 | C27: ='Anexo I. Gr 13A'!C26 -> 1005857.5 | D27: ='Anexo I. Gr 13A'!D26 -> 571001.45
B28: 2009 | C28: ='Anexo I. Gr 13A'!C27 -> 659792.88 | D28: ='Anexo I. Gr 13A'!D27 -> 521226.88
B29: 2010 | C29: ='Anexo I. Gr 13A'!C28 -> 605629.37 | D29: ='Anexo I. Gr 13A'!D28 -> 528280.37
B30: 2011 | C30: ='Anexo I. Gr 13A'!C29 -> 623479.03 | D30: ='Anexo I. Gr 13A'!D29 -> 555080.03
B31: 2012 | C31: ='Anexo I. Gr 13A'!C30 -> 510512.86 | D31: ='Anexo I. Gr 13A'!D30 -> 666476.86
B32: 2013 | C32: ='Anexo I. Gr 13A'!C31 -> 471421.91 | D32: ='Anexo I. Gr 13A'!D31 -> 723623.91
B33: 2014 | C33: ='Anexo I. Gr 13A'!C32 -> 512863.49 | D33: ='Anexo I. Gr 13A'!D32 -> 614650.49
... B39: 2020 | C39: ='Anexo I. Gr 13A'!C38 -> 785643.86 | D39: ='Anexo I. Gr 13A'!D38 -> 550434.86
B40: 2021 | C40: 887960 | D40: 696866
B41: 2022 | C41: 1258894 | D41: 531889
B42: 2023 | C42: 1250991 | D42: 608695
B43: 2024 | C43: 1288562 | D43: 662294 | E43: 1288562 | F43: 662294
B44: 2025 | E44: 1160184 | F44: 607687.78
B45: 2026 | E45: 1212848.3 | F45: 613467.53
B46: 2027 | E46: 1234986 | F46: 626022.09
B47: 2028 | E47: 1240584.7 | F47: 646976.54
B48: 2029 | E48: 1161090.7 | F48: 664280.23
B49: 2030 | E49: 1075247.6 | F49: 675706.35
B50: 2031 | E50: 1029334.3 | F50: 682732.19
B51: 2032 | E51: 993723.38 | F51: 687155.51
B52: 2033 | E52: 958316.53 | F52: 689486.21
B53: 2034 | E53: 941705.58 | F53: 690424.32
B54: 2035 | E54: 924378.06 | F54: 690589.06
B55: 2036 | E55: 922055.37 | F55: 690436.83
... B69: 2050 | E69: 973910.09 | F69: 704787.68

Sheet Anexo I. Gr 16A
A1: Índice de gráficos
B2: ANEXO I. GRÁFICO 16. PÍRAMIDES DE POBLACIÓN (MILES DE PERSONAS)
B3: ANEXO I. GRÁFICO 16A. POBLACIÓN RESIDENTE ESPAÑOLA. MILES DE PERSONAS. GRUPOS QUINQUENALES DE EDAD
B18: Fuente: | C18: INE y AIReF
B19: Población española
C20: Hombres | E20: Mujeres
C21: 2025 | D21: 2050 | E21: 2025 | F21: 2050
B22: De 0 a 4 años | C22: -749532 | D22: -617016.32 | E22: 709382 | F22: 582633.77
B23: De 5 a 9 años | C23: -945797 | D23: -726571.6 | E23: 894337 | F23: 686808.94
B24: De 10 a 14 años | C24: -1101770 | D24: -784213.9 | E24: 1039496 | F24: 741526.71
B25: De 15 a 19 años | C25: -1209572 | D25: -837098.13 | E25: 1141606 | F25: 791707.63
B26: De 20 a 24 años | C26: -1129214 | D26: -897895.99 | E26: 1075534 | F26: 852864.32
B27: De 25 a 29 años | C27: -1036221 | D27: -1008056.2 | E27: 994234 | F27: 965944.3
B28: De 30 a 34 años | C28: -1079288 | D28: -1179473.6 | E28: 1048013 | F28: 1139779.3
B29: De 35 a 39 años | C29: -1162988 | D29: -1325218.4 | E29: 1150980 | F29: 1299995.6
B30: De 40 a 44 años | C30: -1415824 | D30: -1428170.2 | E30: 1418418 | F30: 1424734.6
B31: De 45 a 49 años | C31: -1736494 | D31: -1370665.2 | E31: 1729140 | F31: 1402421.7
B32: De 50 a 54 años | C32: -1727702 | D32: -1299468.1 | E32: 1731007 | F32: 1356000.4
B33: De 55 a 59 años | C33: -1628360 | D33: -1315091.8 | E33: 1674635 | F33: 1390039.1
... B41: 95 y más años | C41: -36858.996 | D41: -127166 | E41: 114913.51 | F41: 318557.15

Sheet Anexo I. Gr 16B
A1: Índice de gráficos
B2: ANEXO I. GRÁFICO 16. PÍRAMIDES DE POBLACIÓN (MILES DE PERSONAS)
B3: ANEXO I. GRÁFICO 16B. POBLACIÓN RESIDENTE EXTRANJERA. MILES DE PERSONAS. GRUPOS QUINQUENALES DE EDAD
B18: Fuente: | C18: INE y AIReF
B19: Poblacón extranjera
C20: Hombres | E20: Mujeres
C21: 2025 | D21: 2050 | E21: 2025 | F21: 2050
B22: De 0 a 4 años | C22: -129938 | D22: -248753.61 | E22: 123416 | F22: 235398.79
B23: De 5 a 9 años | C23: -158049 | D23: -217792.88 | E23: 150690 | F23: 207095.42
B24: De 10 a 14 años | C24: -176798 | D24: -221419.29 | E24: 164858 | F24: 208670.46
B25: De 15 a 19 años | C25: -186784 | D25: -244028.88 | E25: 159304 | F25: 223417.27
B26: De 20 a 24 años | C26: -261566 | D26: -294600.55 | E26: 227317 | F26: 271097.03
B27: De 25 a 29 años | C27: -345819 | D27: -370422.04 | E27: 321697 | F27: 350130.36
B28: De 30 a 34 años | C28: -379224 | D28: -437279.04 | E28: 367161 | F28: 417491.45
B29: De 35 a 39 años | C29: -369805 | D29: -457635.88 | E29: 378369 | F29: 437364.95
B30: De 40 a 44 años | C30: -355157 | D30: -441055.42 | E30: 357482 | F30: 423359.35
B31: De 45 a 49 años | C31: -318317 | D31: -402784.98 | E31: 303334 | F31: 392351.12
B32: De 50 a 54 años | C32: -246311 | D32: -347871.68 | E32: 238961 | F32: 346956.45
B33: De 55 a 59 años | C33: -182695 | D33: -286237.97 | E33: 188259 | F33: 292893.26
... B41: 95 y más años | C41: -676.00425 | D41: -4830.0134 | E41: 1555.4861 | F41: 11582.479

Sheet Anexo I. Gr 16C
A1: Índice de gráficos
B2: ANEXO I. GRÁFICO 16. PÍRAMIDES DE POBLACIÓN (MILES DE PERSONAS)
B3: ANEXO I. GRÁFICO 16C. POBLACIÓN TOTAL RESIDENTE. MILES DE PERSONAS. GRUPOS QUINQUENALES DE EDAD
B18: Fuente: | C18: INE y AIReF
B19: Población total
C20: Hombres | E20: Mujeres
C21: 2025 | D21: 2050 | E21: 2025 | F21: 2050
B22: De 0 a 4 años | C22: -879470 | D22: -865769.92 | E22: 832798 | F22: 818032.56
B23: De 5 a 9 años | C23: -1103846 | D23: -944364.48 | E23: 1045027 | F23: 893904.36
B24: De 10 a 14 años | C24: -1278568 | D24: -1005633.2 | E24: 1204354 | F24: 950197.16
B25: De 15 a 19 años | C25: -1396356 | D25: -1081127 | E25: 1300910 | F25: 1015124.9
B26: De 20 a 24 años | C26: -1390780 | D26: -1192496.5 | E26: 1302851 | F26: 1123961.4
B27: De 25 a 29 años | C27: -1382040 | D27: -1378478.2 | E27: 1315931 | F27: 1316074.7
B28: De 30 a 34 años | C28: -1458512 | D28: -1616752.7 | E28: 1415174 | F28: 1557270.7
B29: De 35 a 39 años | C29: -1532793 | D29: -1782854.3 | E29: 1529349 | F29: 1737360.5
B30: De 40 a 44 años | C30: -1770981 | D30: -1869225.6 | E30: 1775900 | F30: 1848094
B31: De 45 a 49 años | C31: -2054811 | D31: -1773450.1 | E31: 2032474 | F31: 1794772.8
B32: De 50 a 54 años | C32: -1974013 | D32: -1647339.8 | E32: 1969968 | F32: 1702956.9
B33: De 55 a 59 años | C33: -1811055 | D33: -1601329.7 | E33: 1862894 | F33: 1682932.3
... B41: 95 y más años | C41: -37535 | D41: -131996.01 | E41: 116469 | F41: 330139.63
